Workbook

Sheet Cover
B7: Financial Modeling - Practice
B11: Adani Power
B12: Sep 25, 2026
B16: Disclaimer: This analysis is not a solicitation, offer, or recommendation to buy, hold, or sell any security, commodity, or financial instrument. This financial model and the accompanying analysis are for educational, practice, and informational purposes only. Nothing contained in this post or model constitutes financial, investment, legal, or tax advice. Harsh Aryan 2026 © — shared for educational purposes; please credit if referenced

Sheet Data & Assumption >>

Sheet Historical Data
B1: =Cover!B11 -> Adani Power
A2: # | B2: Income Statement
B3: (₹ Crore)
H5: 2017 | I5: =H5+1 -> 2018 | J5: =I5+1 -> 2019 | K5: =J5+1 -> 2020 | L5: =K5+1 -> 2021 | M5: =L5+1 -> 2022 | N5: =M5+1 -> 2023 | O5: =N5+1 -> 2024 | P5: =O5+1 -> 2025 | Q5: =P5+1 -> 2026
B7: Revenue
C8: Sales | H8: 22615.51 | I8: 20304.28 | J8: 23884.18 | K8: 26467.72 | L8: 26221.48 | M8: 27711.18 | N8: 38773.3 | O8: 50351.25 | P8: 56203.09 | Q8: 54240.52
B10: COGS
C11: Power and Fuel | H11: 14630.49 | I11: 12535.25 | J11: 15952.45 | K11: 17580.39 | L11: 14781.15 | M11: 14762.21 | N11: 25480.85 | O11: 28452.64 | P11: 30273.25 | Q11: 29168.02
C12: Other Mfr. Exp | H12: 1260.02 | I12: 1551.86 | J12: 1680.59 | K12: 1864.95 | L12: 1838.18 | M12: 2066.68 | N12: 1718.27 | O12: 1856.84 | P12: 2231.05 | Q12: 2565.39
C13: Gross Profit | H13: =H8-SUM(H11:H12) -> 6725 | I13: =I8-SUM(I11:I12) -> 6217.17 | J13: =J8-SUM(J11:J12) -> 6251.14 | K13: =K8-SUM(K11:K12) -> 7022.38 | L13: =L8-SUM(L11:L12) -> 9602.15 | M13: =M8-SUM(M11:M12) -> 10882.29 | N13: =N8-SUM(N11:N12) -> 11574.18 | O13: =O8-SUM(O11:O12) -> 20041.77 | ... Q13: =Q8-SUM(Q11:Q12) -> 22507.11
B15: SG&A
C16: Employee Cost | H16: 361.01 | I16: 353.9 | J16: 363.47 | K16: 427.04 | L16: 431.89 | M16: 470.72 | N16: 570.46 | O16: 644.17 | P16: 786.63 | Q16: 857.81
C17: Selling and admin | H17: 307.25 | I17: 225.3 | J17: 222.73 | K17: 454.63 | L17: 281.14 | M17: 233.67 | N17: 443.65 | O17: 454.82 | P17: 543.57 | Q17: 581.01
C18: Other Expenses | H18: 76.7 | I18: 202.04 | J18: 681.53 | K18: 407.07 | L18: 200.96 | M18: 296.49 | N18: 463.73 | O18: 715.16 | P18: 950.26 | Q18: 1262.18
C19: Other Income | H19: -3666.12 | I19: 754.1 | J19: 2447.87 | K19: 322.76 | L19: 1908.56 | M19: 3908.04 | N19: 4215.54 | O19: 9883.31 | P19: 2589.85 | Q19: 3624.76
C20: EBITDA | H20: =H13-SUM(H16:H18)+H19 -> 2313.92 | I20: =I13-SUM(I16:I18)+I19 -> 6190.03 | J20: =J13-SUM(J16:J18)+J19 -> 7431.28 | K20: =K13-SUM(K16:K18)+K19 -> 6056.4 | L20: =L13-SUM(L16:L18)+L19 -> 10596.72 | M20: =M13-SUM(M16:M18)+M19 -> 13789.45 | N20: =N13-SUM(N16:N18)+N19 -> 14311.88 | O20: =O13-SUM(O16:O18)+O19 -> 28110.93 | ... Q20: =Q13-SUM(Q16:Q18)+Q19 -> 23430.87
C22: Depreciation | H22: 2672.36 | I22: 2698.72 | J22: 2750.62 | K22: 3006.5 | L22: 3201.65 | M22: 3117.54 | N22: 3303.68 | O22: 3931.33 | P22: 4308.88 | Q22: 4564.53
C23: EBIT | H23: =H20-H22 -> -358.44 | I23: =I20-I22 -> 3491.31 | J23: =J20-J22 -> 4680.66 | K23: =K20-K22 -> 3049.9 | L23: =L20-L22 -> 7395.07 | M23: =M20-M22 -> 10671.91 | N23: =N20-N22 -> 11008.2 | O23: =O20-O22 -> 24179.6 | ... Q23: =Q20-Q22 -> 18866.34
C25: Interest | H25: 5901.73 | I25: 5570.23 | J25: 5656.52 | K25: 5314.82 | L25: 5106.33 | M25: 4094.78 | N25: 3333.5 | O25: 3388.09 | P25: 3339.79 | Q25: 3366.83
C26: EBT | H26: =H23-H25 -> -6260.17 | I26: =I23-I25 -> -2078.92 | J26: =J23-J25 -> -975.86 | K26: =K23-K25 -> -2264.92 | L26: =L23-L25 -> 2288.74 | M26: =M23-M25 -> 6577.13 | N26: =N23-N25 -> 7674.7 | O26: =O23-O25 -> 20791.51 | ... Q26: =Q23-Q25 -> 15499.51
C28: Tax | H28: -86.07 | I28: -5.15 | J28: 8.54 | K28: 9.85 | L28: 1018.76 | M28: 1665.55 | N28: -3051.94 | O28: -37.28 | P28: 3609.9 | Q28: 2528.43
C30: Net Profit | H30: =H26-H28 -> -6174.1 | I30: =I26-I28 -> -2073.77 | J30: =J26-J28 -> -984.4 | K30: =K26-K28 -> -2274.77 | L30: =L26-L28 -> 1269.98 | M30: =M26-M28 -> 4911.58 | N30: =N26-N28 -> 10726.64 | O30: =O26-O28 -> 20828.79 | ... Q30: =Q26-Q28 -> 12971.08
B34: =B1 -> Adani Power
A35: =A2 -> # | B35: Balance Sheet
B36: =B3 -> (₹ Crore)
H37: =H5 -> 2017 | I37: =I5 -> 2018 | J37: =J5 -> 2019 | K37: =K5 -> 2020 | L37: =L5 -> 2021 | M37: =M5 -> 2022 | N37: =N5 -> 2023 | O37: =O5 -> 2024 | ... Q37: =Q5 -> 2026
B39: ASSETS
C40: Inventories | H40: 1760.41 | I40: 873.98 | J40: 1224.08 | K40: 2522.77 | L40: 2025.11 | M40: 2258.27 | N40: 3075.2 | O40: 4142.1 | P40: 3317.28 | Q40: 3623.48
C42: Receivables over 6m | H42: 0 | I42: 0 | J42: 0 | K42: 0 | L42: 0 | M42: 0 | N42: 0 | O42: 5644 | P42: 6551 | Q42: 4617
C43: Receivables under 6m | H43: 7704 | I43: 6070 | J43: 8551 | K43: 8366 | L43: 11438 | M43: 9561 | N43: 11529 | O43: 6033 | P43: 6471 | Q43: 7175
C44: Prov for Doubtful | H44: 0 | I44: 0 | J44: 0 | K44: 0 | L44: 0 | M44: 0 | N44: 0 | O44: 0 | P44: 0 | Q44: 0
C45: Total Trade receivables | H45: =SUM(H42:H44) -> 7704 | I45: =SUM(I42:I44) -> 6070 | J45: =SUM(J42:J44) -> 8551 | K45: =SUM(K42:K44) -> 8366 | L45: =SUM(L42:L44) -> 11438 | M45: =SUM(M42:M44) -> 9561 | N45: =SUM(N42:N44) -> 11529 | O45: =SUM(O42:O44) -> 11677 | ... Q45: =SUM(Q42:Q44) -> 11792
C47: Cash Equivalents | H47: 604.17 | I47: 856.61 | J47: 915.88 | K47: 1979.31 | L47: 1607.32 | M47: 2364.68 | N47: 1873.65 | O47: 7211.76 | P47: 6119.88 | Q47: 6926.32
C48: Loans n Advances | H48: 771 | I48: 752 | J48: 659 | K48: 880 | L48: 909 | M48: 1474 | N48: 1802 | O48: 1242 | P48: 1057 | Q48: 1479
C49: Other asset items | H49: 5991 | I49: 8719 | J49: 5863 | K49: 3081 | L49: 3245 | M49: 2596 | N49: 2556 | O49: 3421 | P49: 6902 | Q49: 11677
C51: Total Current Assets | H51: =H40+H45+SUM(H47:H49) -> 16830.58 | I51: =I40+I45+SUM(I47:I49) -> 17271.59 | J51: =J40+J45+SUM(J47:J49) -> 17212.96 | K51: =K40+K45+SUM(K47:K49) -> 16829.08 | L51: =L40+L45+SUM(L47:L49) -> 19224.43 | M51: =M40+M45+SUM(M47:M49) -> 18253.95 | N51: =N40+N45+SUM(N47:N49) -> 20835.85 | O51: =O40+O45+SUM(O47:O49) -> 27693.86 | ... Q51: =Q40+Q45+SUM(Q47:Q49) -> 35497.8
C53: Land | H53: 228 | I53: 275 | J53: 821 | K53: 797 | L53: 874 | M53: 1017 | N53: 1085 | O53: 2076 | P53: 4103 | Q53: 4214
C54: Building | H54: 1409 | I54: 1476 | J54: 1497 | K54: 2415 | L54: 1725 | M54: 1633 | N54: 1900 | O54: 2158 | P54: 2978 | Q54: 3200
C55: Plant Machinery | H55: 58202 | I55: 58515 | J55: 58967 | K55: 65724 | L55: 66252 | M55: 69592 | N55: 69793 | O55: 85315 | P55: 92737 | Q55: 96779
C56: Equipments | H56: 45 | I56: 45 | J56: 45 | K56: 49 | L56: 56 | M56: 69 | N56: 86 | O56: 104 | P56: 124 | Q56: 151
C57: Computers | H57: 23 | I57: 27 | J57: 28 | K57: 33 | L57: 39 | M57: 45 | N57: 59 | O57: 79 | P57: 97 | Q57: 123
C58: Furniture n fittings | H58: 23 | I58: 24 | J58: 26 | K58: 32 | L58: 34 | M58: 36 | N58: 35 | O58: 40 | P58: 45 | Q58: 48
C59: Railway sidings | H59: 255 | I59: 255 | J59: 255 | K59: 255 | L59: 474 | M59: 479 | N59: 480 | O59: 675 | P59: 682 | Q59: 796
C60: Vehicles | H60: 13 | I60: 13 | J60: 17 | K60: 18 | L60: 23 | M60: 25 | N60: 32 | O60: 34 | P60: 43 | Q60: 48
C61: Intangible Assets | H61: 191 | I61: 191 | J61: 191 | K61: 191 | L61: 191 | M61: 191 | N61: 191 | O61: 191 | P61: 205 | Q61: 208
C62: Other fixed assets | H62: 13 | I62: 14 | J62: 15 | K62: 763 | L62: 797 | M62: 857 | N62: 1668 | O62: 38 | P62: 98 | Q62: 152
C63: Gross Block | H63: =SUM(H53:H62) -> 60402 | I63: =SUM(I53:I62) -> 60835 | J63: =SUM(J53:J62) -> 61862 | K63: =SUM(K53:K62) -> 70277 | L63: =SUM(L53:L62) -> 70465 | M63: =SUM(M53:M62) -> 73944 | N63: =SUM(N53:N62) -> 75329 | O63: =SUM(O53:O62) -> 90710 | ... Q63: =SUM(Q53:Q62) -> 105719
C65: Accumulated Depreciation | H65: =H63-H66 -> 6011.07 | I65: =I63-I66 -> 8697.86 | J65: =J63-J66 -> 11443.24 | K65: =K63-K66 -> 14431.19 | L65: =L63-L66 -> 17613.7 | M65: =M63-M66 -> 20669.79 | N65: =N63-N66 -> 23877.62 | O65: =O63-O66 -> 27694.15 | ... Q65: =Q63-Q66 -> 36317.54
C66: Net Block | H66: 54390.93 | I66: 52137.14 | J66: 50418.76 | K66: 55845.81 | L66: 52851.3 | M66: 53274.21 | N66: 51451.38 | O66: 63015.85 | P66: 69297.45 | Q66: 69401.46
C68: Capital Work in Progress | H68: 124.61 | I68: 119.86 | J68: 350.08 | K68: 2346.77 | L68: 6439.42 | M68: 10269.74 | N68: 12879.54 | O68: 925.12 | P68: 12104.42 | Q68: 35053.46
C69: Investments | H69: 164.33 | I69: 0.01 | J69: 2.72 | K69: 2.8 | L69: 20.1 | M69: 183.25 | N69: 654.05 | O69: 373.51 | P69: 1097.21 | Q69: 1515.99
C71: Total Non-Current Asset | H71: =H66+H68+H69 -> 54679.87 | I71: =I66+I68+I69 -> 52257.01 | J71: =J66+J68+J69 -> 50771.56 | K71: =K66+K68+K69 -> 58195.38 | L71: =L66+L68+L69 -> 59310.82 | M71: =M66+M68+M69 -> 63727.2 | N71: =N66+N68+N69 -> 64984.97 | O71: =O66+O68+O69 -> 64314.48 | ... Q71: =Q66+Q68+Q69 -> 105970.91
C73: Total Assets | H73: =H51+H71 -> 71510.45 | I73: =I51+I71 -> 69528.6 | J73: =J51+J71 -> 67984.52 | K73: =K51+K71 -> 75024.46 | L73: =L51+L71 -> 78535.25 | M73: =M51+M71 -> 81981.15 | N73: =N51+N71 -> 85820.82 | O73: =O51+O71 -> 92008.34 | ... Q73: =Q51+Q71 -> 141468.71
B76: LIABILITIES AND EQUITY
C77: Short term Borrowings | H77: 12580 | I77: 14560 | J77: 7074 | K77: 7802 | L77: 9683 | M77: 10924 | N77: 8549 | O77: 7862 | P77: 10688 | Q77: 10726
C78: Trade Payables | H78: 7400 | I78: 7626 | J78: 6362 | K78: 5596 | L78: 3803 | M78: 3508 | N78: 3079 | O78: 3609 | P78: 2978 | Q78: 2841
C79: Advance from Customers | H79: 709 | I79: 130 | J79: 72 | K79: 38 | L79: 753 | M79: 53 | N79: 33 | O79: 5 | P79: 21 | Q79: 116
C80: Total Current Liabilities | H80: =SUM(H77:H79) -> 20689 | I80: =SUM(I77:I79) -> 22316 | J80: =SUM(J77:J79) -> 13508 | K80: =SUM(K77:K79) -> 13436 | L80: =SUM(L77:L79) -> 14239 | M80: =SUM(M77:M79) -> 14485 | N80: =SUM(N77:N79) -> 11661 | O80: =SUM(O77:O79) -> 11476 | ... Q80: =SUM(Q77:Q79) -> 13683
C82: Long term Borrowings | H82: 36651 | I82: 34560 | J82: 36410 | K82: 44566 | L82: 39957 | M82: 37871 | N82: 33703 | O82: 26595 | P82: 27647 | Q82: 42830
C83: Preference Capital | H83: 0 | I83: 0 | J83: 0 | K83: 76 | L83: 88 | M83: 401 | N83: 416 | O83: 431 | P83: 139 | Q83: 152
C84: Lease Liabilities | H84: 0 | I84: 0 | J84: 0 | K84: 0 | L84: 0 | M84: 103 | N84: 97 | O84: 159 | P84: 1160 | Q84: 1115
C85: Other Borrowings | H85: 3254 | I85: 3715 | J85: 3496 | K85: 2754 | L85: 2683 | M85: -154 | N85: -169 | O85: -184 | P85: -139 | Q85: -152
C86: Other liability items | H86: 7918 | I86: 8047 | J86: 6859 | K86: 7712 | L86: 8456 | M86: 10818 | N86: 10484 | O86: 10635 | P86: 12750 | Q86: 17439
C87: Total Non-Current Liabilities | H87: =SUM(H82:H86) -> 47823 | I87: =SUM(I82:I86) -> 46322 | J87: =SUM(J82:J86) -> 46765 | K87: =SUM(K82:K86) -> 55108 | L87: =SUM(L82:L86) -> 51184 | M87: =SUM(M82:M86) -> 49039 | N87: =SUM(N82:N86) -> 44531 | O87: =SUM(O82:O86) -> 37636 | ... Q87: =SUM(Q82:Q86) -> 61384
C89: Equity Share Capital | H89: 3856.94 | I89: 3856.94 | J89: 3856.94 | K89: 3856.94 | L89: 3856.94 | M89: 3856.94 | N89: 3856.94 | O89: 3856.94 | P89: 3856.94 | Q89: 3856.94
C90: Reserves | H90: -857.38 | I90: -2967.61 | J90: 3855.35 | K90: 2623.5 | L90: 9255.65 | M90: 14599.95 | N90: 25772.17 | O90: 39041.54 | P90: 52490.15 | Q90: 61079.94
C91: Shareholder's Equity | H91: =SUM(H89:H90) -> 2999.56 | I91: =SUM(I89:I90) -> 889.33 | J91: =SUM(J89:J90) -> 7712.29 | K91: =SUM(K89:K90) -> 6480.44 | L91: =SUM(L89:L90) -> 13112.59 | M91: =SUM(M89:M90) -> 18456.89 | N91: =SUM(N89:N90) -> 29629.11 | O91: =SUM(O89:O90) -> 42898.48 | ... Q91: =SUM(Q89:Q90) -> 64936.88
C93: Non controlling int | H93: 0 | I93: 0 | J93: 0 | K93: 0 | L93: 0 | M93: 0 | N93: 0 | O93: 0 | P93: 1326 | Q93: 1465
C95: Total Liabilities and Equity | H95: =H80+H87+H91+H93 -> 71511.56 | I95: =I80+I87+I91+I93 -> 69527.33 | J95: =J80+J87+J91+J93 -> 67985.29 | K95: =K80+K87+K91+K93 -> 75024.44 | L95: =L80+L87+L91+L93 -> 78535.59 | M95: =M80+M87+M91+M93 -> 81980.89 | N95: =N80+N87+N91+N93 -> 85821.11 | O95: =O80+O87+O91+O93 -> 92010.48 | ... Q95: =Q80+Q87+Q91+Q93 -> 141468.88
C97: Check | H97: =ROUND(H73-H95, 2) -> -1.11 | I97: =ROUND(I73-I95, 2) -> 1.27 | J97: =ROUND(J73-J95, 2) -> -0.77 | K97: =ROUND(K73-K95, 2) -> 0.02 | L97: =ROUND(L73-L95, 2) -> -0.34 | M97: =ROUND(M73-M95, 2) -> 0.26 | N97: =ROUND(N73-N95, 2) -> -0.29 | O97: =ROUND(O73-O95, 2) -> -2.14 | ... Q97: =ROUND(Q73-Q95, 2) -> -0.17
C99: No. of Equity Shares | H99: 385.69389 | I99: 385.69389 | J99: 385.69389 | K99: 385.69389 | L99: 385.69389 | M99: 385.69389 | N99: 385.69389 | O99: 385.69389 | P99: 385.69389 | Q99: 1928.4695
C100: Face value | H100: 10 | I100: 10 | J100: 10 | K100: 10 | L100: 10 | M100: 10 | N100: 10 | O100: 10 | P100: 10 | Q100: 2
C102: Adjusted Equity Shares in Cr | H102: =H99*($H$100/$Q$100) -> 1928.4695 | I102: =I99*($H$100/$Q$100) -> 1928.4695 | J102: =J99*($H$100/$Q$100) -> 1928.4695 | K102: =K99*($H$100/$Q$100) -> 1928.4695 | L102: =L99*($H$100/$Q$100) -> 1928.4695 | M102: =M99*($H$100/$Q$100) -> 1928.4695 | N102: =N99*($H$100/$Q$100) -> 1928.4695 | O102: =O99*($H$100/$Q$100) -> 1928.4695 | P102: =P99*($H$100/$Q$100) -> 1928.4695 | Q102: =Q99 -> 1928.4695
B106: =B1 -> Adani Power
A107: =A2 -> # | B107: Cash Flow Statement
B108: =B3 -> (₹ Crore)
H109: =H37 -> 2017 | I109: =I37 -> 2018 | J109: =J37 -> 2019 | K109: =K37 -> 2020 | L109: =L37 -> 2021 | M109: =M37 -> 2022 | N109: =N37 -> 2023 | O109: =O37 -> 2024 | ... Q109: =Q37 -> 2026
B110: Operating Activities
C111: Net Income | H111: =H26 -> -6260.17 | I111: =I26 -> -2078.92 | J111: =J26 -> -975.86 | K111: =K26 -> -2264.92 | L111: =L26 -> 2288.74 | M111: =M26 -> 6577.13 | N111: =N26 -> 7674.7 | O111: =O26 -> 20791.51 | ... Q111: =Q26 -> 15499.51
C112: Depreciation & Amortization | H112: =H22 -> 2672.36 | I112: =I22 -> 2698.72 | J112: =J22 -> 2750.62 | K112: =K22 -> 3006.5 | L112: =L22 -> 3201.65 | M112: =M22 -> 3117.54 | N112: =N22 -> 3303.68 | O112: =O22 -> 3931.33 | ... Q112: =Q22 -> 4564.53
C113: Interest Expenses | H113: =H25 -> 5901.73 | I113: =I25 -> 5570.23 | J113: =J25 -> 5656.52 | K113: =K25 -> 5314.82 | L113: =L25 -> 5106.33 | M113: =M25 -> 4094.78 | N113: =N25 -> 3333.5 | O113: =O25 -> 3388.09 | ... Q113: =Q25 -> 3366.83
C114: Profit/Loss on sale of Fixed Assets | H114: 8.39 | I114: 35.05 | J114: 29.58 | K114: 48.34 | L114: 19.64 | M114: 67.25 | N114: 85.65 | O114: 78.35 | P114: 112.89 | Q114: 0
C115: Profit/Loss on sale of investments | H115: -2.19 | I115: -36.46 | J115: -1.6 | K115: -4.09 | L115: -0.02 | M115: -0.83 | N115: -707.55 | O115: -275.82 | P115: 0 | Q115: -23.45
C116: Interest Income | H116: -235.48 | I116: -393.56 | J116: -1993.62 | K116: -959.63 | L116: -1045.45 | M116: -3558.27 | N116: -3607.19 | O116: -8921.11 | P116: -1443.96 | Q116: -1953.05
C117: Effect of Exchange Rate Change | H117: -398.42 | I117: -46.9 | J117: 261.66 | K117: 84.1 | L117: -336.75 | M117: 61.55 | N117: 101.61 | O117: -2.49 | P117: -91.13 | Q117: -109.91
C118: Provision & Written Off | H118: -299.84 | I118: -308.21 | J118: -311.88 | K118: -346.5 | L118: -611.87 | M118: -246.55 | N118: -333.3 | O118: -484.27 | P118: -593.69 | Q118: -509.05
C119: Excess of cost over fair value of investments | H119: 0 | I119: 0 | J119: 0 | K119: 0 | L119: 0 | M119: 0 | N119: 0 | O119: 0 | P119: -97.24 | Q119: -48.06
C120: Bad debts irrecoverable written off | H120: 0 | I120: 1.43 | J120: 124.17 | K120: 216.84 | L120: 43.05 | M120: 0.42 | N120: 8.68 | O120: 7.53 | P120: 36.77 | Q120: 71.15
C121: Provision for doubtful debts & advances | H121: 0 | I121: 0 | J121: 0 | K121: 0 | L121: 0 | M121: 0 | N121: 0 | O121: 164.53 | P121: 17.73 | Q121: 0
C122: Other Adjustments | H122: 4076.69 | I122: 0 | J122: 0 | K122: 1002.99 | L122: 0 | M122: 39.44 | N122: 0 | O122: 0 | P122: 0 | Q122: 0
C123: Changes In working Capital | H123: -734.33 | I123: -327.03 | J123: 79.55 | K123: -443.08 | L123: -1645.42 | M123: 304.61 | N123: -1350.6 | O123: -4450.08 | P123: -440.1 | Q123: -447.11
C124: Tax Paid | H124: -3.54 | I124: -13.2 | J124: -8.76 | K124: -57.82 | L124: -5.55 | M124: -224.34 | N124: -78.65 | O124: -57.42 | P124: -8.34 | Q124: 102.26
C125: Operating Cash Flow | H125: =H111+SUM(H112:H124) -> 4725.2 | I125: =I111+SUM(I112:I124) -> 5101.15 | J125: =J111+SUM(J112:J124) -> 5610.38 | K125: =K111+SUM(K112:K124) -> 5597.55 | L125: =L111+SUM(L112:L124) -> 7014.35 | M125: =M111+SUM(M112:M124) -> 10232.73 | N125: =N111+SUM(N112:N124) -> 8430.53 | O125: =O111+SUM(O112:O124) -> 14170.15 | ... Q125: =Q111+SUM(Q112:Q124) -> 20513.65
B128: Investing Activities
C129: Purchase of Fixed Assets | H129: -854.29 | I129: -942.57 | J129: -1211.53 | K129: -2226.56 | L129: -3617.61 | M129: -3434.55 | N129: -3243.68 | O129: -2602.45 | P129: -11559.04 | Q129: -23350.09
C130: Sale of Fixed Assets | H130: 10.17 | I130: 15.46 | J130: 252.55 | K130: 6.72 | L130: 9.96 | M130: 1.24 | N130: 0.83 | O130: 0.56 | P130: 15.16 | Q130: 19.4
C131: Total CAPEX | H131: =H129+H130 -> -844.12 | I131: =I129+I130 -> -927.11 | J131: =J129+J130 -> -958.98 | K131: =K129+K130 -> -2219.84 | L131: =L129+L130 -> -3607.65 | M131: =M129+M130 -> -3433.31 | N131: =N129+N130 -> -3242.85 | O131: =O129+O130 -> -2601.89 | ... Q131: =Q129+Q130 -> -23330.69
C133: Other | H133: -367.92 | I133: 406.68 | J133: -25.26 | K133: -108.27 | L133: 1420.08 | M133: 4005.42 | N133: 4787.28 | O133: 6084.21 | P133: -5598.17 | Q133: -3129.87
C134: Investing Cash Flow | H134: =H131+H133 -> -1212.04 | I134: =I131+I133 -> -520.43 | J134: =J131+J133 -> -984.24 | K134: =K131+K133 -> -2328.11 | L134: =L131+L133 -> -2187.57 | M134: =M131+M133 -> 572.11 | N134: =N131+N133 -> 1544.43 | O134: =O131+O133 -> 3482.32 | ... Q134: =Q131+Q133 -> -26460.56
B137: Financing Activities
...

Sheet Assumptions
B1: =Cover!B11 -> Adani Power
B2: Inputs and Assumptions
C4: GENERAL | J4: EQUITY
C8: - | D8: First Year of Forecast in Financial Model: | H8: 2027 | J8: - | K8: Stock Price - 25/9/26 | O8: 202.71
C9: - | D9: Scenarios : | J9: - | K9: ="Fully Diluted Shares O/S (Cr) - Dec. 31, "&H8-1 -> Fully Diluted Shares O/S (Cr) - Dec. 31, 2026 | O9: =19284694705/10000000 -> 1928.4695
D10: CAPACITY SCENARIOS - Capacity Commissioned, Plant Availability | J10: - | K10: Face value | O10: 2
D11: TARIFF SCENARIO - New-PPA Capacity Charge, Merchant Tariff | J11: - | K11: Book value per share | O11: ='Historical Data'!Q91/Assumptions!O9 -> 33.672755
D12: ECONOMIC SCENARIOS - Cost of Incremental Debt, Cost Inflation | J12: - | K12: EPS | O12: ='Historical Data'!Q30/Assumptions!O9 -> 6.7261008
C13: - | D13: Terminal Growth Rate | H13: 0.0456
C16: INSTALLED CAPACITY | J16: OPERATING PARAMETERS
C20: Fiscal Year | E20: Capacity added (MW) | G20: Cumulative (MW) | J20: Parameter
C21: =$H$8-1 -> 2026 | E21: - | G21: 18150 | J21: - | K21: Plant Availability | O21: 0.9
C22: =C21+1 -> 2027 | E22: 2920 | G22: =G21+E22 -> 21070 | J22: - | K22: Plant Load Factor (PLF) | O22: 0.68
C23: =C22+1 -> 2028 | E23: 2400 | G23: =G22+E23 -> 23470 | J23: - | K23: Auxiliary power consumption | O23: 0.06
C24: =C23+1 -> 2029 | E24: 2400 | G24: =G23+E24 -> 25870 | J24: - | K24: Contracted capacity | O24: 0.96
C25: =C24+1 -> 2030 | E25: 8000 | G25: =G24+E25 -> 33870 | J25: - | K25: Legacy capacity charge | O25: 2.6
C26: =C25+1 -> 2031 | E26: 5600 | G26: =G25+E26 -> 39470 | J26: - | K26: New-PPA capacity charge — tied 13,320 MW | O26: 4.11
C27: =C26+1 -> 2032 | E27: 2400 | G27: =G26+E27 -> 41870 | J27: - | K27: New-PPA capacity charge — untied 10,400 MW | O27: 4.2
J28: - | K28: Capacity-charge escalation | O28: 0.02
J29: - | K29: Merchant tariff | O29: 5.2
C32: COST | J32: DEPRECIATION
C36: - | D36: Electricity Generation | H36: =(((G21*O60)*O58*(O22-0.01))-((G21*O60)*O58*(O22-0.01)*O23))/10000 -> 9913.3077 | J36: - | K36: Depreciation Methodology Used: | O36: Straight Line
C37: - | D37: Fuel Cost | H37: ='Historical Data'!Q11/H36 -> 2.9423096 | J37: - | K37: Years remaining for depreciation of existing assets: | O37: ='Historical Data'!Q66/'Historical Data'!Q22 -> 15.204514
C38: - | D38: Coal cost inflation / Other income growth | H38: 0.03 | J38: - | K38: Years used for depreciation of new assets: | O38: 25
C41: TAXES | J41: INTEREST RATE
C45: - | D45: Tax rate assumed in the Model: | H45: 0.25168 | J45: - | K45: Interest earned on cash balances | O45: 0.065
J46: - | K46: Interest rate on bank revolver / working capital | O46: 0.068
J47: - | K47: Interest rate on senior secured term debt | O47: 0.085
C50: CAPEX & CWIP | J50: Extended - OPERATING PARAMETERS
C54: - | D54: Total capex program | H54: 202000 | J54: Parameter
C55: - | D55: Capex per MW — blended | H55: 8.4 | J55: - | K55: Pipeline — PSA tied | O55: 13320
C56: - | D56: Capex per MW — greenfield | H56: 10 | J56: - | K56: Pipeline — total | O56: 23720
C57: - | D57: Opening CWIP | H57: ='Historical Data'!Q68 -> 35053.46 | J57: - | K57: Tied share of additions | O57: =O55/O56 -> 0.56155143
C58: - | D58: Maintenance capex per MW | H58: 0.05 | J58: - | K58: Hours per year | O58: =24*365 -> 8760
C59: S-curve weights | J59: - | K59: Normative availability | O59: 0.85
C60: - | D60: Year T−3 | H60: 0.15 | J60: - | K60: Effective capacity factor | O60: 0.99
C61: - | D61: Year T−2 | H61: 0.35
C62: - | D62: Year T−1 | H62: 0.35
C63: - | D63: Year T (COD) | H63: 0.15
C66: ADJUSTMENT | J66: WORKING CAPITAL DAYS
C70: - | D70: FY'24 Total income includes ₹9,322 crore of one-time prior-period | J70: - | K70: Inventory days | O70: =('Historical Data'!Q40/'Historical Data'!Q11)*365 -> 45.34316
D71: revenue (domestic coal shortfall, carrying costs, late-payment surcharges). | J71: - | K71: Receivable days | O71: =('Historical Data'!Q45/Model!J76)*365 -> 78.512389
J72: - | K72: Loans & advances days | O72: =('Historical Data'!Q48/'Historical Data'!Q8)*365 -> 9.9526148
J73: - | K73: Other asset items days | O73: =('Historical Data'!Q49/'Historical Data'!Q8)*365 -> 78.577879
J74: - | K74: Trade payable days | O74: =('Historical Data'!Q78/'Historical Data'!Q11)*365 -> 35.551436
J75: - | K75: Advance from customers days | O75: =('Historical Data'!Q79/'Historical Data'!Q8)*365 -> 0.78059724
C78: DEBT | J78: TAX
C82: - | D82: Opening term debt (incl. NCDs) | H82: 45523 | J82: - | K82: Opening DTL | O82: 5827.15
C83: - | D83: Opening revolver | H83: 8033 | J83: - | K83: Opening DTA | O83: 811.39
C84: - | D84: Opening lease liabilities | H84: 1114.75 | J84: - | K84: Current tax payable at FY26 | O84: 1555.27
C85: - | D85: Minimum cash balance | H85: 5000 | J85: - | K85: Tax depreciation rate (WDV) | O85: 0.15
C86: Repayment Ladder | J86: - | K86: Opening tax WDV | O86: ='Historical Data'!Q66-(Assumptions!O82/Assumptions!H45) -> 46248.448
C87: - | D87: =H8 -> 2027 | H87: 3665
C88: - | D88: =D87+1 -> 2028 | H88: 4525
C89: - | D89: =D88+1 -> 2029 | H89: 4425
C90: - | D90: =D89+1 -> 2030 | H90: 4939
C91: - | D91: =D90+1 -> 2031 | H91: 8489
C92: - | D92: =D91+1 -> 2032 | H92: 5336

Sheet Comp Data
B1: =Cover!B11 -> Adani Power
B2: Comparable Company Data
B5: S.No. | C5: Company | E5: CMP | F5: No. Eq. Shares | G5: Debt | H5: Cash | I5: Net Debt | J5: Mar Cap | K5: EV | L5: Sales | M5: EBITDA | N5: PAT 12M Rs.Cr.
B6: 1 | C6: NTPC | E6: 325.9 | F6: 969.67 | G6: 271004.58 | H6: 8003.78 | I6: =G6-H6 -> 263000.8 | J6: 316014.36 | K6: 579015.16 | L6: 191058.77 | M6: 60059.41 | N6: 27762.97
B7: =B6+1 -> 2 | C7: Tata Power Co. | E7: 366.05 | F7: 319.53 | G7: 76141.27 | H7: 13644 | I7: =G7-H7 -> 62497.27 | J7: 116965.4 | K7: 179462.67 | L7: 63444.78 | M7: 17228.43 | N7: 3915.45
B8: =B7+1 -> 3 | C8: JSW Energy | E8: 514.2 | F8: 183.35 | G8: 76945.78 | H8: 5765.22 | I8: =G8-H8 -> 71180.56 | J8: 94277.69 | K8: 165458.25 | L8: 18964.89 | M8: 11097.94 | N8: 2006.08
B9: =B8+1 -> 4 | C9: Torrent Power | E9: 1250 | F9: 50.39 | G9: 13970.56 | H9: 831.43 | I9: =G9-H9 -> 13139.13 | J9: 62987.94 | K9: 76127.07 | L9: 29184.09 | M9: 5894.85 | N9: 2323.84
B10: =B9+1 -> 5 | C10: CESC | E10: 141.75 | F10: 132.56 | G10: 21670.57 | H10: 5572.03 | I10: =G10-H10 -> 16098.54 | J10: 18789.96 | K10: 34888.5 | L10: 18853 | M10: 4676 | N10: 1554

Sheet Model >>

Sheet Scenarios
B1: =Cover!B11 -> Adani Power
B2: Capacity, Tariff and Economic Scenario
B5: SCENARIO SWITCH: | D5: 1 | G5: =Assumptions!H8 -> 2027 | H5: =G5+1 -> 2028 | I5: =H5+1 -> 2029 | J5: =I5+1 -> 2030 | K5: =J5+1 -> 2031 | L5: =K5+1 -> 2032 | M5: =L5+1 -> 2033
B9: CAPACITY SCENARIOS | G9: CHOOSE / OFFSET / INDEX
B11: Capacity Commissioned (MW) | G11: {=INDEX(G13:G15,$D$5)} -> 2920 | H11: {=INDEX(H13:H15,$D$5)} -> 2400 | I11: {=INDEX(I13:I15,$D$5)} -> 2400 | J11: {=INDEX(J13:J15,$D$5)} -> 8000 | K11: {=INDEX(K13:K15,$D$5)} -> 5600 | L11: {=INDEX(L13:L15,$D$5)} -> 2400 | M11: 0
C13: Base Case | G13: =Assumptions!E22 -> 2920 | H13: =Assumptions!E23 -> 2400 | I13: =Assumptions!E24 -> 2400 | J13: =Assumptions!E25 -> 8000 | K13: =Assumptions!E26 -> 5600 | L13: =Assumptions!E27 -> 2400 | M13: 0
C14: Best Case | G14: 2920 | H14: 2400 | I14: 2400 | J14: 8000 | K14: 5600 | L14: 2400 | M14: 0
C15: Worst Case | G15: 1600 | H15: 3720 | I15: 2400 | J15: 4000 | K15: 5600 | L15: 4400 | M15: 2000
B17: Plant Availability (%) | G17: {=INDEX(G19:G21,$D$5)} -> 0.9 | H17: {=INDEX(H19:H21,$D$5)} -> 0.9 | I17: {=INDEX(I19:I21,$D$5)} -> 0.905 | J17: {=INDEX(J19:J21,$D$5)} -> 0.905 | K17: {=INDEX(K19:K21,$D$5)} -> 0.91 | L17: {=INDEX(L19:L21,$D$5)} -> 0.91
C19: =C13 -> Base Case | G19: =Assumptions!O21 -> 0.9 | H19: 0.9 | I19: 0.905 | J19: 0.905 | K19: 0.91 | L19: 0.91
C20: =C14 -> Best Case | G20: 0.91 | H20: 0.915 | I20: 0.92 | J20: 0.92 | K20: 0.925 | L20: 0.925
C21: =C15 -> Worst Case | G21: 0.88 | H21: 0.875 | I21: 0.87 | J21: 0.87 | K21: 0.87 | L21: 0.87
B25: TARIFF SCENARIOS
B27: New-PPA Capacity Charge — untied capacity (₹/kWh) | G27: {=INDEX(G29:G31,$D$5)} -> 4.2 | H27: {=INDEX(H29:H31,$D$5)} -> 4.284 | I27: {=INDEX(I29:I31,$D$5)} -> 4.36968 | J27: {=INDEX(J29:J31,$D$5)} -> 4.4570736 | K27: {=INDEX(K29:K31,$D$5)} -> 4.5462151 | L27: {=INDEX(L29:L31,$D$5)} -> 4.6371394
C29: =C19 -> Base Case | G29: =Assumptions!O27 -> 4.2 | H29: =G29*(1+Assumptions!$O$28) -> 4.284 | I29: =H29*(1+Assumptions!$O$28) -> 4.36968 | J29: =I29*(1+Assumptions!$O$28) -> 4.4570736 | K29: =J29*(1+Assumptions!$O$28) -> 4.5462151 | L29: =K29*(1+Assumptions!$O$28) -> 4.6371394
A30: 0.07 | C30: =C20 -> Best Case | G30: =G29*(1+$A30) -> 4.494 | H30: =H29*(1+$A30) -> 4.58388 | I30: =I29*(1+$A30) -> 4.6755576 | J30: =J29*(1+$A30) -> 4.7690688 | K30: =K29*(1+$A30) -> 4.8644501 | L30: =L29*(1+$A30) -> 4.9617391
A31: -0.07 | C31: =C21 -> Worst Case | G31: =G29*($A$31+1) -> 3.906 | H31: =H29*($A$31+1) -> 3.98412 | I31: =I29*($A$31+1) -> 4.0638024 | J31: =J29*($A$31+1) -> 4.1450784 | K31: =K29*($A$31+1) -> 4.22798 | L31: =L29*($A$31+1) -> 4.3125396
B34: Merchant Tariff (₹/kWh) | G34: =OFFSET(G35,$D$5,0) -> 5.2 | H34: =OFFSET(H35,$D$5,0) -> 5.15 | I34: =OFFSET(I35,$D$5,0) -> 5.1 | J34: =OFFSET(J35,$D$5,0) -> 5.05 | K34: =OFFSET(K35,$D$5,0) -> 5 | L34: =OFFSET(L35,$D$5,0) -> 5
C36: =C13 -> Base Case | G36: =Assumptions!O29 -> 5.2 | H36: 5.15 | I36: 5.1 | J36: 5.05 | K36: 5 | L36: 5
C37: =C14 -> Best Case | G37: 6 | H37: 6 | I37: 5.9 | J37: 5.9 | K37: 5.8 | L37: 5.8
C38: =C15 -> Worst Case | G38: 4.5 | H38: 4.4 | I38: 4.3 | J38: 4.25 | K38: 4.2 | L38: 4.2
B42: ECONOMIC SCENARIOS
B44: Cost of Incremental Debt (%) | G44: {=INDEX(G46:G48,$D$5)} -> 0.085 | H44: {=INDEX(H46:H48,$D$5)} -> 0.085 | I44: {=INDEX(I46:I48,$D$5)} -> 0.085 | J44: {=INDEX(J46:J48,$D$5)} -> 0.085 | K44: {=INDEX(K46:K48,$D$5)} -> 0.085 | L44: {=INDEX(L46:L48,$D$5)} -> 0.085
C46: =C36 -> Base Case | G46: 0.085 | H46: 0.085 | I46: 0.085 | J46: 0.085 | K46: 0.085 | L46: 0.085
C47: =C37 -> Best Case | G47: 0.0825 | H47: 0.08 | I47: 0.08 | J47: 0.0775 | K47: 0.0775 | L47: 0.0775
C48: =C38 -> Worst Case | G48: 0.09 | H48: 0.0925 | I48: 0.095 | J48: 0.095 | K48: 0.0975 | L48: 0.0975
B51: Cost Inflation (%) — fixed O&M only | G51: =OFFSET(G52,$D$5,0) -> 0.05 | H51: =OFFSET(H52,$D$5,0) -> 0.0475 | I51: =OFFSET(I52,$D$5,0) -> 0.0475 | J51: =OFFSET(J52,$D$5,0) -> 0.045 | K51: =OFFSET(K52,$D$5,0) -> 0.045 | L51: =OFFSET(L52,$D$5,0) -> 0.045
C53: =C46 -> Base Case | G53: 0.05 | H53: 0.0475 | I53: 0.0475 | J53: 0.045 | K53: 0.045 | L53: 0.045
C54: =C47 -> Best Case | G54: 0.045 | H54: 0.0425 | I54: 0.0425 | J54: 0.04 | K54: 0.04 | L54: 0.04
C55: =C48 -> Worst Case | G55: 0.06 | H55: 0.0575 | I55: 0.0575 | J55: 0.055 | K55: 0.055 | L55: 0.055
B59: DCF SCENARIO
B61: WACC (%) | G61: {=INDEX(G63:G65,$D$5)} -> 0.086480245 | H61: {=INDEX(H63:H65,$D$5)} -> 0.088980245 | I61: {=INDEX(I63:I65,$D$5)} -> 0.091480245 | J61: {=INDEX(J63:J65,$D$5)} -> 0.093980245 | K61: {=INDEX(K63:K65,$D$5)} -> 0.096480245
C63: =C53 -> Base Case | G63: =H63-0.25% -> 0.086480245 | H63: =I63-0.25% -> 0.088980245 | I63: =WACC!G48 -> 0.091480245 | J63: =I63+0.25% -> 0.093980245 | K63: =J63+0.25% -> 0.096480245
C64: =C54 -> Best Case | G64: =H64-0.25% -> 0.076480245 | H64: =I64-0.25% -> 0.078980245 | I64: =I63-1% -> 0.081480245 | J64: =I64+0.25% -> 0.083980245 | K64: =J64+0.25% -> 0.086480245
C65: =C55 -> Worst Case | G65: =H65-0.25% -> 0.096480245 | H65: =I65-0.25% -> 0.098980245 | I65: =I63+1% -> 0.10148025 | J65: =I65+0.25% -> 0.10398025 | K65: =J65+0.25% -> 0.10648025
B68: Terminal Growth Rate (%) | G68: {=INDEX(G70:G72,$D$5)} -> 0.04 | H68: {=INDEX(H70:H72,$D$5)} -> 0.0425 | I68: {=INDEX(I70:I72,$D$5)} -> 0.045 | J68: {=INDEX(J70:J72,$D$5)} -> 0.0475 | K68: {=INDEX(K70:K72,$D$5)} -> 0.05
C70: =C63 -> Base Case | G70: 0.04 | H70: 0.0425 | I70: 0.045 | J70: 0.0475 | K70: 0.05
C71: =C64 -> Best Case | G71: 0.045 | H71: 0.0475 | I71: 0.05 | J71: 0.0525 | K71: 0.055
C72: =C65 -> Worst Case | G72: 0.03 | H72: 0.0325 | I72: 0.035 | J72: 0.0375 | K72: 0.04

Sheet Model
P1: =UPPER("CURRENTLY RUNNING: " & CHOOSE(Scenarios!D5,Scenarios!C13,Scenarios!C14,Scenarios!C15) & " Scenario") -> CURRENTLY RUNNING: BASE CASE SCENARIO
B2: =Cover!B11 -> Adani Power
B3: Capacity & Commissioning Schedule
B5: (MW)
K6: Projected
H7: =I7-1 -> 2024 | I7: =J7-1 -> 2025 | J7: =K7-1 -> 2026 | K7: =Assumptions!H8 -> 2027 | L7: =K7+1 -> 2028 | M7: =L7+1 -> 2029 | N7: =M7+1 -> 2030 | O7: =N7+1 -> 2031 | P7: =O7+1 -> 2032
B8: Installed Capacity
C9: Capacity commissioned | F9: (MW) | J9: 0 | K9: =Scenarios!G11 -> 2920 | L9: =Scenarios!H11 -> 2400 | M9: =Scenarios!I11 -> 2400 | N9: =Scenarios!J11 -> 8000 | O9: =Scenarios!K11 -> 5600 | P9: =Scenarios!L11 -> 2400
C10: Cumulative capacity | F10: (MW) | J10: =Assumptions!G21 -> 18150 | K10: =J10+K9 -> 21070 | L10: =K10+L9 -> 23470 | M10: =L10+M9 -> 25870 | N10: =M10+N9 -> 33870 | O10: =N10+O9 -> 39470 | P10: =O10+P9 -> 41870
C11: Effective capacity | F11: (MW) | J11: 18000 | K11: =J10+(K9/2) -> 19610 | L11: =K10+(L9/2) -> 22270 | M11: =L10+(M9/2) -> 24670 | N11: =M10+(N9/2) -> 29870 | O11: =N10+(O9/2) -> 36670 | P11: =O10+(P9/2) -> 40670
B14: Operating Parameters
C15: Plant availability | F15: (%) | J15: 0.89 | K15: =Scenarios!G17 -> 0.9 | L15: =Scenarios!H17 -> 0.9 | M15: =Scenarios!I17 -> 0.905 | N15: =Scenarios!J17 -> 0.905 | O15: =Scenarios!K17 -> 0.91 | P15: =Scenarios!L17 -> 0.91
C16: Plant load factor | F16: (%) | J16: 0.67 | K16: =Assumptions!$O$22 -> 0.68 | L16: =Assumptions!$O$22 -> 0.68 | M16: =Assumptions!$O$22 -> 0.68 | N16: =Assumptions!$O$22 -> 0.68 | O16: =Assumptions!$O$22 -> 0.68 | P16: =Assumptions!$O$22 -> 0.68
C17: Auxiliary consumption | F17: (%) | J17: =Assumptions!$O$23 -> 0.06 | K17: =Assumptions!$O$23 -> 0.06 | L17: =Assumptions!$O$23 -> 0.06 | M17: =Assumptions!$O$23 -> 0.06 | N17: =Assumptions!$O$23 -> 0.06 | O17: =Assumptions!$O$23 -> 0.06 | P17: =Assumptions!$O$23 -> 0.06
C18: Contracted capacity | F18: (%) | J18: 0.95 | K18: =Assumptions!$O$24 -> 0.96 | L18: =Assumptions!$O$24 -> 0.96 | M18: =Assumptions!$O$24 -> 0.96 | N18: =Assumptions!$O$24 -> 0.96 | O18: =Assumptions!$O$24 -> 0.96 | P18: =Assumptions!$O$24 -> 0.96
B21: Capacity by Vintage
C22: Tied additions | F22: (MW) | J22: 0 | K22: =K9*Assumptions!$O$57 -> 1639.7302 | L22: =L9*Assumptions!$O$57 -> 1347.7234 | M22: =M9*Assumptions!$O$57 -> 1347.7234 | N22: =N9*Assumptions!$O$57 -> 4492.4115 | O22: =O9*Assumptions!$O$57 -> 3144.688 | P22: =P9*Assumptions!$O$57 -> 1347.7234
C23: Untied additions | F23: (MW) | J23: 0 | K23: =K9-K22 -> 1280.2698 | L23: =L9-L22 -> 1052.2766 | M23: =M9-M22 -> 1052.2766 | N23: =N9-N22 -> 3507.5885 | O23: =O9-O22 -> 2455.312 | P23: =P9-P22 -> 1052.2766
C25: Legacy — cumulative | F25: (MW) | J25: =J10 -> 18150 | K25: =J25 -> 18150 | L25: =K25 -> 18150 | M25: =L25 -> 18150 | N25: =M25 -> 18150 | O25: =N25 -> 18150 | P25: =O25 -> 18150
C26: New tied — cumulative | F26: (MW) | J26: 0 | K26: =J26+K22 -> 1639.7302 | L26: =K26+L22 -> 2987.4536 | M26: =L26+M22 -> 4335.1771 | N26: =M26+N22 -> 8827.5885 | O26: =N26+O22 -> 11972.277 | P26: =O26+P22 -> 13320
C27: New untied — cumulative | F27: (MW) | J27: 0 | K27: =J27+K23 -> 1280.2698 | L27: =K27+L23 -> 2332.5464 | M27: =L27+M23 -> 3384.8229 | N27: =M27+N23 -> 6892.4115 | O27: =N27+O23 -> 9347.7234 | P27: =O27+P23 -> 10400
C29: Legacy — effective | F29: (MW) | J29: =J11 -> 18000 | K29: =K25 -> 18150 | L29: =L25 -> 18150 | M29: =M25 -> 18150 | N29: =N25 -> 18150 | O29: =O25 -> 18150 | P29: =P25 -> 18150
C30: New tied — effective | F30: (MW) | J30: 0 | K30: =J26+(K22/2) -> 819.86509 | L30: =K26+(L22/2) -> 2313.5919 | M30: =L26+(M22/2) -> 3661.3153 | N30: =M26+(N22/2) -> 6581.3828 | O30: =N26+(O22/2) -> 10399.933 | P30: =O26+(P22/2) -> 12646.138
C31: New untied — effective | F31: (MW) | J31: 0 | K31: =J27+(K23/2) -> 640.13491 | L31: =K27+(L23/2) -> 1806.4081 | M31: =L27+(M23/2) -> 2858.6847 | N31: =M27+(N23/2) -> 5138.6172 | O31: =N27+(O23/2) -> 8120.0675 | P31: =O27+(P23/2) -> 9873.8617
C33: Check: total effective | K33: =ROUND(SUM(K29:K31) - K11, 1) -> 0 | L33: =ROUND(SUM(L29:L31) - L11, 1) -> 0 | M33: =ROUND(SUM(M29:M31) - M11, 1) -> 0 | N33: =ROUND(SUM(N29:N31) - N11, 1) -> 0 | O33: =ROUND(SUM(O29:O31) - O11, 1) -> 0 | P33: =ROUND(SUM(P29:P31) - P11, 1) -> 0
P36: =P1 -> CURRENTLY RUNNING: BASE CASE SCENARIO
B37: =B2 -> Adani Power
B38: Revenue Schedule
B40: (₹ Crore)
K41: =K6 -> Projected
H42: =H7 -> 2024 | I42: =I7 -> 2025 | J42: =J7 -> 2026 | K42: =K7 -> 2027 | L42: =L7 -> 2028 | M42: =M7 -> 2029 | N42: =N7 -> 2030 | O42: =O7 -> 2031 | P42: =P7 -> 2032
B43: VOLUMES
C44: Gross generation — legacy | F44: (cr kWh) | J44: =(J29*Assumptions!$O$58*Model!J16)/10000 -> 10564.56 | K44: =(K29*Assumptions!$O$58*Model!K16)/10000 -> 10811.592 | L44: =(L29*Assumptions!$O$58*Model!L16)/10000 -> 10811.592 | M44: =(M29*Assumptions!$O$58*Model!M16)/10000 -> 10811.592 | N44: =(N29*Assumptions!$O$58*Model!N16)/10000 -> 10811.592 | O44: =(O29*Assumptions!$O$58*Model!O16)/10000 -> 10811.592 | P44: =(P29*Assumptions!$O$58*Model!P16)/10000 -> 10811.592
C45: Less: Auxiliary consumption | F45: (cr kWh) | J45: =-J44*J17 -> -633.8736 | K45: =-K44*K17 -> -648.69552 | L45: =-L44*L17 -> -648.69552 | M45: =-M44*M17 -> -648.69552 | N45: =-N44*N17 -> -648.69552 | O45: =-O44*O17 -> -648.69552 | P45: =-P44*P17 -> -648.69552
C46: Net saleable — legacy | F46: (cr kWh) | J46: =J44+J45 -> 9930.6864 | K46: =K44+K45 -> 10162.896 | L46: =L44+L45 -> 10162.896 | M46: =M44+M45 -> 10162.896 | N46: =N44+N45 -> 10162.896 | O46: =O44+O45 -> 10162.896 | P46: =P44+P45 -> 10162.896
C48: PPA units — legacy | F48: (cr kWh) | J48: =J46*J18 -> 9434.1521 | K48: =K46*K18 -> 9756.3806 | L48: =L46*L18 -> 9756.3806 | M48: =M46*M18 -> 9756.3806 | N48: =N46*N18 -> 9756.3806 | O48: =O46*O18 -> 9756.3806 | P48: =P46*P18 -> 9756.3806
C49: Merchant units — legacy | F49: (cr kWh) | J49: =J46-J48 -> 496.53432 | K49: =K46-K48 -> 406.51586 | L49: =L46-L48 -> 406.51586 | M49: =M46-M48 -> 406.51586 | N49: =N46-N48 -> 406.51586 | O49: =O46-O48 -> 406.51586 | P49: =P46-P48 -> 406.51586
C51: Billable capacity — new tied | F51: (cr kWh) | J51: =(J30*Assumptions!$O$58*Assumptions!$O$59)/10000 -> 0 | K51: =(K30*Assumptions!$O$58*Assumptions!$O$59)/10000 -> 610.47155 | L51: =(L30*Assumptions!$O$58*Assumptions!$O$59)/10000 -> 1722.7005 | M51: =(M30*Assumptions!$O$58*Assumptions!$O$59)/10000 -> 2726.2154 | N51: =(N30*Assumptions!$O$58*Assumptions!$O$59)/10000 -> 4900.4976 | O51: =(O30*Assumptions!$O$58*Assumptions!$O$59)/10000 -> 7743.7898 | P51: =(P30*Assumptions!$O$58*Assumptions!$O$59)/10000 -> 9416.3146
C52: Billable capacity — new untied | F52: (cr kWh) | J52: =(J31*Assumptions!$O$58*Assumptions!$O$59)/10000 -> 0 | K52: =(K31*Assumptions!$O$58*Assumptions!$O$59)/10000 -> 476.64445 | L52: =(L31*Assumptions!$O$58*Assumptions!$O$59)/10000 -> 1345.0515 | M52: =(M31*Assumptions!$O$58*Assumptions!$O$59)/10000 -> 2128.5766 | N52: =(N31*Assumptions!$O$58*Assumptions!$O$59)/10000 -> 3826.2144 | O52: =(O31*Assumptions!$O$58*Assumptions!$O$59)/10000 -> 6046.2022 | P52: =(P31*Assumptions!$O$58*Assumptions!$O$59)/10000 -> 7352.0774
C53: Net saleable — new | F53: (cr kWh) | J53: =((J30+J31)*Assumptions!$O$58*Model!J16*(1-Model!J17))/10000 -> 0 | K53: =(K30+K31)*Assumptions!$O$58*Model!K16*(1-Model!K17)/10000 -> 817.51123 | L53: =(L30+L31)*Assumptions!$O$58*Model!L16*(1-Model!L17)/10000 -> 2306.9495 | M53: =(M30+M31)*Assumptions!$O$58*Model!M16*(1-Model!M17)/10000 -> 3650.8036 | N53: =(N30+N31)*Assumptions!$O$58*Model!N16*(1-Model!N17)/10000 -> 6562.4874 | O53: =(O30+O31)*Assumptions!$O$58*Model!O16*(1-Model!O17)/10000 -> 10370.074 | P53: =(P30+P31)*Assumptions!$O$58*Model!P16*(1-Model!P17)/10000 -> 12609.831
B55: TARIFFS
C56: Legacy capacity charge | F56: (₹/kWh) | J56: =Assumptions!$O$25 -> 2.6 | K56: =Assumptions!$O$25 -> 2.6 | L56: =Assumptions!$O$25 -> 2.6 | M56: =Assumptions!$O$25 -> 2.6 | N56: =Assumptions!$O$25 -> 2.6 | O56: =Assumptions!$O$25 -> 2.6 | P56: =Assumptions!$O$25 -> 2.6
C57: Legacy energy charge | F57: (₹/kWh) | J57: ='Historical Data'!Q11/Model!J46 -> 2.9371605 | K57: =J57*(1+Assumptions!$H$38) -> 3.0252753 | L57: =K57*(1+Assumptions!$H$38) -> 3.1160336 | M57: =L57*(1+Assumptions!$H$38) -> 3.2095146 | N57: =M57*(1+Assumptions!$H$38) -> 3.3058 | O57: =N57*(1+Assumptions!$H$38) -> 3.404974 | P57: =O57*(1+Assumptions!$H$38) -> 3.5071233
C58: New tied capacity charge | F58: (₹/kWh) | J58: 0 | K58: =Assumptions!O26 -> 4.11 | L58: =K58*(1+Assumptions!$O$28) -> 4.1922 | M58: =L58*(1+Assumptions!$O$28) -> 4.276044 | N58: =M58*(1+Assumptions!$O$28) -> 4.3615649 | O58: =N58*(1+Assumptions!$O$28) -> 4.4487962 | P58: =O58*(1+Assumptions!$O$28) -> 4.5377721
C59: New untied capacity charge | F59: (₹/kWh) | J59: 0 | K59: =Scenarios!G27 -> 4.2 | L59: =Scenarios!H27 -> 4.284 | M59: =Scenarios!I27 -> 4.36968 | N59: =Scenarios!J27 -> 4.4570736 | O59: =Scenarios!K27 -> 4.5462151 | P59: =Scenarios!L27 -> 4.6371394
C60: Merchant tariff | F60: (₹/kWh) | J60: =Assumptions!O29 -> 5.2 | K60: =Scenarios!G34 -> 5.2 | L60: =Scenarios!H34 -> 5.15 | M60: =Scenarios!I34 -> 5.1 | N60: =Scenarios!J34 -> 5.05 | O60: =Scenarios!K34 -> 5 | P60: =Scenarios!L34 -> 5
C61: Energy charge — new | F61: (₹/kWh) | J61: =J57 -> 2.9371605 | K61: =K57 -> 3.0252753 | L61: =L57 -> 3.1160336 | M61: =M57 -> 3.2095146 | N61: =N57 -> 3.3058 | O61: =O57 -> 3.404974 | P61: =P57 -> 3.5071233
C62: Availability factor | F62: (%) | J62: =J15/$J$15 -> 1 | K62: =K15/$J$15 -> 1.011236 | L62: =L15/$J$15 -> 1.011236 | M62: =M15/$J$15 -> 1.0168539 | N62: =N15/$J$15 -> 1.0168539 | O62: =O15/$J$15 -> 1.0224719 | P62: =P15/$J$15 -> 1.0224719
B64: REVENUE
C65: Capacity charge — legacy | F65: (₹ cr) | J65: =J48*J56*J62 -> 24528.795 | K65: =K48*K56*K62 -> 25651.607 | L65: =L48*L56*L62 -> 25651.607 | M65: =M48*M56*M62 -> 25794.116 | N65: =N48*N56*N62 -> 25794.116 | O65: =O48*O56*O62 -> 25936.625 | P65: =P48*P56*P62 -> 25936.625
C66: Capacity charge — new tied | F66: (₹ cr) | J66: =J51*J58 -> 0 | K66: =K51*K58 -> 2509.0381 | L66: =L51*L58 -> 7221.9052 | M66: =M51*M58 -> 11657.417 | N66: =N51*N58 -> 21373.838 | O66: =O51*O58 -> 34450.542 | P66: =P51*P58 -> 42729.09
C67: Capacity charge — new untied | F67: (₹ cr) | J67: =J52*J59 -> 0 | K67: =K52*K59 -> 2001.9067 | L67: =L52*L59 -> 5762.2005 | M67: =M52*M59 -> 9301.1986 | N67: =N52*N59 -> 17053.719 | O67: =O52*O59 -> 27487.336 | P67: =P52*P59 -> 34092.608
C68: Total capacity charge | F68: (₹ cr) | J68: =SUM(J65:J67) -> 24528.795 | K68: =SUM(K65:K67) -> 30162.552 | L68: =SUM(L65:L67) -> 38635.713 | M68: =SUM(M65:M67) -> 46752.732 | N68: =SUM(N65:N67) -> 64221.674 | O68: =SUM(O65:O67) -> 87874.503 | P68: =SUM(P65:P67) -> 102758.32
C70: Energy charge — legacy | F70: (₹ cr) | J70: =J48*J57 -> 27709.619 | K70: =K48*K57 -> 29515.738 | L70: =L48*L57 -> 30401.21 | M70: =M48*M57 -> 31313.246 | N70: =N48*N57 -> 32252.643 | O70: =O48*O57 -> 33220.223 | P70: =P48*P57 -> 34216.829
C71: Energy charge — new | F71: (₹ cr) | J71: =J53*J61 -> 0 | K71: =K53*K61 -> 2473.1966 | L71: =L53*L61 -> 7188.5322 | M71: =M53*M61 -> 11717.307 | N71: =N53*N61 -> 21694.271 | O71: =O53*O61 -> 35309.833 | P71: =P53*P61 -> 44224.231
C72: Total energy charge | F72: (₹ cr) | J72: =SUM(J70:J71) -> 27709.619 | K72: =SUM(K70:K71) -> 31988.934 | L72: =SUM(L70:L71) -> 37589.742 | M72: =SUM(M70:M71) -> 43030.553 | N72: =SUM(N70:N71) -> 53946.915 | O72: =SUM(O70:O71) -> 68530.055 | P72: =SUM(P70:P71) -> 78441.06
C74: Merchant revenue | F74: (₹ cr) | J74: =J49*J60 -> 2581.9785 | K74: =K49*K60 -> 2113.8825 | L74: =L49*L60 -> 2093.5567 | M74: =M49*M60 -> 2073.2309 | N74: =N49*N60 -> 2052.9051 | O74: =O49*O60 -> 2032.5793 | P74: =P49*P60 -> 2032.5793
C76: Revenue from operations | F76: (₹ cr) | J76: =J68+J72+J74 -> 54820.393 | K76: =K68+K72+K74 -> 64265.369 | L76: =L68+L72+L74 -> 78319.012 | M76: =M68+M72+M74 -> 91856.516 | N76: =N68+N72+N74 -> 120221.49 | O76: =O68+O72+O74 -> 158437.14 | P76: =P68+P72+P74 -> 183231.96
C77: Other income | F77: (₹ cr) | J77: ='Historical Data'!Q19 -> 3624.76 | K77: =J77*(1+Assumptions!$H$38) -> 3733.5028 | L77: =K77*(1+Assumptions!$H$38) -> 3845.5079 | M77: =L77*(1+Assumptions!$H$38) -> 3960.8731 | N77: =M77*(1+Assumptions!$H$38) -> 4079.6993 | O77: =N77*(1+Assumptions!$H$38) -> 4202.0903 | P77: =O77*(1+Assumptions!$H$38) -> 4328.153
C79: Total income | F79: (₹ cr) | J79: =J76+J77 -> 58445.153 | K79: =K76+K77 -> 67998.872 | L79: =L76+L77 -> 82164.52 | M79: =M76+M77 -> 95817.389 | N79: =N76+N77 -> 124301.19 | O79: =O76+O77 -> 162639.23 | P79: =P76+P77 -> 187560.12
C81: Check vs reported | J81: =ROUND(J76/'Historical Data'!Q8,3) -> 1.011
P84: =P36 -> CURRENTLY RUNNING: BASE CASE SCENARIO
B85: =B37 -> Adani Power
B86: Cost Schedule
B88: (₹ Crore)
K89: =K41 -> Projected
H90: =H42 -> 2024 | I90: =I42 -> 2025 | J90: =J42 -> 2026 | K90: =K42 -> 2027 | L90: =L42 -> 2028 | M90: =M42 -> 2029 | N90: =N42 -> 2030 | O90: =O42 -> 2031 | P90: =P42 -> 2032
B91: DRIVERS
C92: Effective capacity | F92: (MW) | J92: =J11 -> 18000 | K92: =K11 -> 19610 | L92: =L11 -> 22270 | M92: =M11 -> 24670 | N92: =N11 -> 29870 | O92: =O11 -> 36670 | P92: =P11 -> 40670
C93: Net saleable units | F93: (cr kWh) | J93: =J46+J53 -> 9930.6864 | K93: =K46+K53 -> 10980.408 | L93: =L46+L53 -> 12469.846 | M93: =M46+M53 -> 13813.7 | N93: =N46+N53 -> 16725.384 | O93: =O46+O53 -> 20532.97 | P93: =P46+P53 -> 22772.727
C94: Cost inflation | F94: (%) | J94: =Assumptions!$H$38 -> 0.03 | K94: =Scenarios!G51 -> 0.05 | L94: =Scenarios!H51 -> 0.0475 | M94: =Scenarios!I51 -> 0.0475 | N94: =Scenarios!J51 -> 0.045 | O94: =Scenarios!K51 -> 0.045 | P94: =Scenarios!L51 -> 0.045
C95: Coal cost inflation | F95: (%) | J95: =Assumptions!$H$38 -> 0.03 | K95: =Assumptions!$H$38 -> 0.03 | L95: =Assumptions!$H$38 -> 0.03 | M95: =Assumptions!$H$38 -> 0.03 | N95: =Assumptions!$H$38 -> 0.03 | O95: =Assumptions!$H$38 -> 0.03 | P95: =Assumptions!$H$38 -> 0.03
B97: VARIABLE — per kWh
C98: Fuel cost | F98: (₹/kWh) | J98: ='Historical Data'!Q11/Model!J93 -> 2.9371605 | K98: =J98*(1+K95) -> 3.0252753 | L98: =K98*(1+L95) -> 3.1160336 | M98: =L98*(1+M95) -> 3.2095146 | N98: =M98*(1+N95) -> 3.3058 | O98: =N98*(1+O95) -> 3.404974 | P98: =O98*(1+P95) -> 3.5071233
B100: FIXED — per MW
C101: Other Mfr. Exp | F101: (₹ cr/MW) | J101: ='Historical Data'!Q12/Model!J11 -> 0.14252167 | K101: =J101*(1+K$94) -> 0.14964775 | L101: =K101*(1+L$94) -> 0.15675602 | M101: =L101*(1+M$94) -> 0.16420193 | N101: =M101*(1+N$94) -> 0.17159102 | O101: =N101*(1+O$94) -> 0.17931261 | P101: =O101*(1+P$94) -> 0.18738168
C102: Employee Cost | F102: (₹ cr/MW) | J102: ='Historical Data'!Q16/Model!J11 -> 0.047656111 | K102: =J102*(1+K$94) -> 0.050038917 | L102: =K102*(1+L$94) -> 0.052415765 | M102: =L102*(1+M$94) -> 0.054905514 | N102: =M102*(1+N$94) -> 0.057376262 | O102: =N102*(1+O$94) -> 0.059958194 | P102: =O102*(1+P$94) -> 0.062656313
C103: Selling & admin | F103: (₹ cr/MW) | J103: ='Historical Data'!Q17/Model!J11 -> 0.032278333 | K103: =J103*(1+K$94) -> 0.03389225 | L103: =K103*(1+L$94) -> 0.035502132 | M103: =L103*(1+M$94) -> 0.037188483 | N103: =M103*(1+N$94) -> 0.038861965 | O103: =N103*(1+O$94) -> 0.040610753 | P103: =O103*(1+P$94) -> 0.042438237
C104: Other Expenses | F104: (₹ cr/MW) | J104: ='Historical Data'!Q18/Model!J11 -> 0.070121111 | K104: =J104*(1+K$94) -> 0.073627167 | L104: =K104*(1+L$94) -> 0.077124457 | M104: =L104*(1+M$94) -> 0.080787869 | N104: =M104*(1+N$94) -> 0.084423323 | O104: =N104*(1+O$94) -> 0.088222372 | P104: =O104*(1+P$94) -> 0.092192379
C105: Total fixed | F105: (₹ cr/MW) | J105: =SUM(J101:J104) -> 0.29257722 | K105: =SUM(K101:K104) -> 0.30720608 | L105: =SUM(L101:L104) -> 0.32179837 | M105: =SUM(M101:M104) -> 0.33708379 | N105: =SUM(N101:N104) -> 0.35225257 | O105: =SUM(O101:O104) -> 0.36810393 | P105: =SUM(P101:P104) -> 0.38466861
B107: COSTS
C108: Power and Fuel | F108: (₹ cr) | J108: =J98*J93 -> 29168.02 | K108: =K98*K93 -> 33218.757 | L108: =L98*L93 -> 38856.459 | M108: =M98*M93 -> 44335.272 | N108: =N98*N93 -> 55290.775 | O108: =O98*O93 -> 69914.231 | P108: =P98*P93 -> 79866.761
C110: Other Mfr. Exp | F110: (₹ cr) | J110: =J101*J$92 -> 2565.39 | K110: =K101*K$92 -> 2934.5924 | L110: =L101*L$92 -> 3490.9565 | M110: =M101*M$92 -> 4050.8616 | N110: =N101*N$92 -> 5125.4236 | O110: =O101*O$92 -> 6575.3935 | P110: =P101*P$92 -> 7620.8129
C111: Employee Cost | F111: (₹ cr) | J111: =J102*J$92 -> 857.81 | K111: =K102*K$92 -> 981.26316 | L111: =L102*L$92 -> 1167.2991 | M111: =M102*M$92 -> 1354.519 | N111: =N102*N$92 -> 1713.829 | O111: =O102*O$92 -> 2198.667 | P111: =P102*P$92 -> 2548.2322
C112: Selling & admin | F112: (₹ cr) | J112: =J103*J$92 -> 581.01 | K112: =K103*K$92 -> 664.62702 | L112: =L103*L$92 -> 790.63248 | M112: =M103*M$92 -> 917.43988 | N112: =N103*N$92 -> 1160.8069 | O112: =O103*O$92 -> 1489.1963 | P112: =P103*P$92 -> 1725.9631
C113: Other Expenses | F113: (₹ cr) | J113: =J104*J$92 -> 1262.18 | K113: =K104*K$92 -> 1443.8287 | L113: =L104*L$92 -> 1717.5617 | M113: =M104*M$92 -> 1993.0367 | N113: =N104*N$92 -> 2521.7247 | O113: =O104*O$92 -> 3235.1144 | P113: =P104*P$92 -> 3749.4641
C114: Total fixed costs | F114: (₹ cr) | J114: =SUM(J110:J113) -> 5266.39 | K114: =SUM(K110:K113) -> 6024.3113 | L114: =SUM(L110:L113) -> 7166.4498 | M114: =SUM(M110:M113) -> 8315.8572 | N114: =SUM(N110:N113) -> 10521.784 | O114: =SUM(O110:O113) -> 13498.371 | P114: =SUM(P110:P113) -> 15644.472
C116: Total Operating Cost | F116: (₹ cr) | J116: =J108+J114 -> 34434.41 | K116: =K108+K114 -> 39243.068 | L116: =L108+L114 -> 46022.909 | M116: =M108+M114 -> 52651.129 | N116: =N108+N114 -> 65812.559 | O116: =O108+O114 -> 83412.603 | P116: =P108+P114 -> 95511.234
C118: Check vs reported | J118: =ROUND(J116/('Historical Data'!Q11+'Historical Data'!Q12+'Historical Data'!Q16+'Historical Data'!Q17+'Historical Data'!Q18)-1,3) -> 0
P121: =P84 -> CURRENTLY RUNNING: BASE CASE SCENARIO
B122: =B85 -> Adani Power
B123: Income Statement
B125: (₹ Crore)
K126: =K89 -> Projected
H127: =H90 -> 2024 | I127: =I90 -> 2025 | J127: =J90 -> 2026 | K127: =K90 -> 2027 | L127: =L90 -> 2028 | M127: =M90 -> 2029 | N127: =N90 -> 2030 | O127: =O90 -> 2031 | P127: =P90 -> 2032
B128: REVENUE
C129: Sales | H129: ='Historical Data'!O8 -> 50351.25 | I129: ='Historical Data'!P8 -> 56203.09 | J129: =J76 -> 54820.393 | K129: =K76 -> 64265.369 | L129: =L76 -> 78319.012 | M129: =M76 -> 91856.516 | N129: =N76 -> 120221.49 | O129: =O76 -> 158437.14 | P129: =P76 -> 183231.96
C130: Sales Growth | F130: (%) | I130: =IFERROR(I129/H129-1,0) -> 0.11622035 | J130: =IFERROR(J129/I129-1,0) -> -0.024601799 | K130: =IFERROR(K129/J129-1,0) -> 0.17228946 | L130: =IFERROR(L129/K129-1,0) -> 0.21868143 | M130: =IFERROR(M129/L129-1,0) -> 0.17285081 | N130: =IFERROR(N129/M129-1,0) -> 0.30879657 | O130: =IFERROR(O129/N129-1,0) -> 0.31787697 | P130: =IFERROR(P129/O129-1,0) -> 0.15649629
B132: COGS
C133: Power and Fuel | H133: ='Historical Data'!O11 -> 28452.64 | I133: ='Historical Data'!P11 -> 30273.25 | J133: =J108 -> 29168.02 | K133: =K108 -> 33218.757 | L133: =L108 -> 38856.459 | M133: =M108 -> 44335.272 | N133: =N108 -> 55290.775 | O133: =O108 -> 69914.231 | P133: =P108 -> 79866.761
...

Sheet DCF>>

Sheet WACC
B1: =Cover!B11 -> Adani Power
B2: WACC
J5: Debt / | K5: Debt / | L5: Levered | M5: Unlevered
B6: Name of the Company | F6: Country | G6: Total Debt (Cr) | H6: Total Equity (Cr) | I6: Tax rate1 | J6: Equity | K6: Capital | L6: Beta2 | M6: Beta3
B10: Adani Power | F10: India | G10: =Model!J240+Model!J245+Model!J247 -> 54671 | H10: =Model!J255 -> 64936.88 | I10: 0.2517 | J10: =G10/H10 -> 0.84190987 | K10: =G10/(G10+H10) -> 0.45708527 | L10: =Beta!J14 -> 1.1923462 | M10: =L10/(1+(1-I10)*J10) -> 0.73150024
B11: NTPC | F11: India | G11: 271004.58 | H11: =G11/J11 -> 203762.84 | I11: 0.2517 | J11: 1.33 | K11: =G11/(H11+G11) -> 0.57081545 | L11: =NTPC!J14 -> 0.86462711 | M11: =L11/(1+(1-I11)*J11) -> 0.43334513
B12: Tata Power Co. | F12: India | G12: 76141.27 | H12: =G12/J12 -> 39451.435 | I12: 0.2517 | J12: 1.93 | K12: =G12/(H12+G12) -> 0.65870307 | L12: ='Tata Power'!J14 -> 1.2074572 | M12: =L12/(1+(1-I12)*J12) -> 0.49400533
B13: JSW Energy | F13: India | G13: 76945.78 | H13: =G13/J13 -> 30778.312 | I13: 0.2517 | J13: 2.5 | K13: =G13/(H13+G13) -> 0.71428571 | L13: ='JSW Energy'!J14 -> 1.0201684 | M13: =L13/(1+(1-I13)*J13) -> 0.35536652
B14: Torrent Power | F14: India | G14: 13970.56 | H14: =G14/J14 -> 19137.753 | I14: 0.2517 | J14: 0.73 | K14: =G14/(H14+G14) -> 0.42196532 | L14: ='Torrent Power'!J14 -> 1.1182002 | M14: =L14/(1+(1-I14)*J14) -> 0.72316488
B15: CESC | F15: India | G15: 21670.57 | H15: =G15/J15 -> 12526.341 | I15: 0.2517 | J15: 1.73 | K15: =G15/(H15+G15) -> 0.63369963 | L15: =CESE!J14 -> 1.032776 | M15: =L15/(1+(1-I15)*J15) -> 0.45009783
H17: Average | I17: =AVERAGE(I11:I15) -> 0.2517 | J17: =AVERAGE(J11:J15) -> 1.644 | K17: =AVERAGE(K11:K15) -> 0.59989384 | L17: =AVERAGE(L11:L15) -> 1.0486458 | M17: =AVERAGE(M11:M15) -> 0.49119594
H18: Median | I18: =MEDIAN(I11:I15) -> 0.2517 | J18: =MEDIAN(J11:J15) -> 1.73 | K18: =MEDIAN(K11:K15) -> 0.63369963 | L18: =MEDIAN(L11:L15) -> 1.032776 | M18: =MEDIAN(M11:M15) -> 0.45009783
B21: Cost of Debt | I21: Cost of Equity
B25: Pre tax cost of Debt | G25: =Scenarios!L44 -> 0.085 | I25: Risk Free Rate | M25: 0.07073
B26: Tax Rate | G26: =Assumptions!H45 -> 0.25168 | I26: Equity Risk Premium | M26: =Rm!G7-WACC!M25 -> 0.058773341
B27: Post Tax Cost of Debt | G27: =G25*(1-G26) -> 0.0636072 | I27: Levered Beta4 | M27: =M38 -> 0.68793349
I28: Cost of Equity | M28: =M25+(M26*M27) -> 0.11116215
B31: Capital Structure | I31: Levered Beta
F35: Current | G35: Target | I35: Peers Median Unlevered Beta | M35: =M18 -> 0.45009783
B36: Total Debt | E36: =G10 -> 54671 | F36: =K10 -> 0.45708527 | G36: ='Ratio Analysis'!N44 -> 0.4138771 | I36: Target Debt / Equity | M36: =G39 -> 0.70612683
B37: Equity | E37: =H10 -> 64936.88 | F37: =1-F36 -> 0.54291473 | G37: =1-G36 -> 0.5861229 | I37: Tax Rate | M37: =G26 -> 0.25168
I38: Levered Beta | M38: =M35*(1+(1-M37)*M36) -> 0.68793349
B39: Debt / Equity | F39: =F36/F37 -> 0.84190987 | G39: =G36/G37 -> 0.70612683
B41: Weighted Average Cost of Capital (WACC)
F45: Total Cost | G45: Total Weight
B46: Debt | F46: =G27 -> 0.0636072 | G46: =G36 -> 0.4138771
B47: Equity | F47: =M28 -> 0.11116215 | G47: =G37 -> 0.5861229
B48: WACC | G48: =(F46*G46)+(F47*G47) -> 0.091480245

Sheet Beta
B1: =Cover!B11 -> Adani Power
B2: Regression Beta - 5Y Weekly
B5: Adani Power Weekly returns | F5: NIFTY Weekly Return | I5: Beta Drifting
B9: Date | C9: Price | D9: Weekly Returns | F9: Price | G9: Return | I9: Levered Raw Beta | J9: =J17 -> 1.2564617
B10: 44458 | C10: 19.17 | D10: 0 | F10: 17853.2 | G10: 0 | I10: Raw Beta Weight | J10: 0.75
B11: 44465 | C11: 19.39 | D11: =C11/C10-1 -> 0.011476265 | F11: 17532.05 | G11: =F11/F10-1 -> -0.017988372 | I11: Market Beta | J11: 1
B12: 44472 | C12: 20.32 | D12: =C12/C11-1 -> 0.047962867 | F12: 17895.2 | G12: =F12/F11-1 -> 0.020713493 | I12: Market Beta Weight | J12: 0.25
B13: 44479 | C13: 22.4 | D13: =C13/C12-1 -> 0.1023622 | F13: 18338.55 | G13: =F13/F12-1 -> 0.0247748
B14: 44486 | C14: 23.41 | D14: =C14/C13-1 -> 0.045089286 | F14: 18114.9 | G14: =F14/F13-1 -> -0.012195621 | I14: Adjusted Beta | J14: =(J9*J10)+(J11*J12) -> 1.1923462
B15: 44493 | C15: 20.1 | D15: =C15/C14-1 -> -0.14139257 | F15: 17671.65 | G15: =F15/F14-1 -> -0.024468807
B16: 44500 | C16: 21.08 | D16: =C16/C15-1 -> 0.048756219 | F16: 17916.8 | G16: =F16/F15-1 -> 0.013872502
B17: 44507 | C17: 21.69 | D17: =C17/C16-1 -> 0.028937381 | F17: 18102.75 | G17: =F17/F16-1 -> 0.010378527 | I17: Beta1 | J17: =J36 -> 1.2564617
B18: 44514 | C18: 20.58 | D18: =C18/C17-1 -> -0.051175657 | F18: 17764.8 | G18: =F18/F17-1 -> -0.018668434
B19: 44521 | C19: 20.25 | D19: =C19/C18-1 -> -0.016034985 | F19: 17026.45 | G19: =F19/F18-1 -> -0.041562528 | I19: SUMMARY OUTPUT
B20: 44528 | C20: 20.16 | D20: =C20/C19-1 -> -0.0044444444 | F20: 17196.7 | G20: =F20/F19-1 -> 0.0099991484
B21: 44535 | C21: 20.81 | D21: =C21/C20-1 -> 0.032242063 | F21: 17511.3 | G21: =F21/F20-1 -> 0.018294208 | I21: Regression Statistics
B22: 44542 | C22: 20.02 | D22: =C22/C21-1 -> -0.037962518 | F22: 16985.2 | G22: =F22/F21-1 -> -0.030043458 | I22: Multiple R | J22: 0.32939894
B23: 44549 | C23: 19.73 | D23: =C23/C22-1 -> -0.014485514 | F23: 17003.75 | G23: =F23/F22-1 -> 0.0010921273 | I23: R Square | J23: 0.10850366
B24: 44556 | C24: 19.94 | D24: =C24/C23-1 -> 0.01064369 | F24: 17354.05 | G24: =F24/F23-1 -> 0.020601338 | I24: Adjusted R Square | J24: 0.10504825
B25: 44563 | C25: 20.04 | D25: =C25/C24-1 -> 0.0050150451 | F25: 17812.7 | G25: =F25/F24-1 -> 0.026428989 | I25: Standard Error | J25: 0.065376334
B26: 44570 | C26: 23.43 | D26: =C26/C25-1 -> 0.16916168 | F26: 18255.75 | G26: =F26/F25-1 -> 0.024872703 | I26: Observations | J26: 260
B27: 44577 | C27: 21.99 | D27: =C27/C26-1 -> -0.061459667 | F27: 17617.15 | G27: =F27/F26-1 -> -0.034980759
B28: 44584 | C28: 21.15 | D28: =C28/C27-1 -> -0.038199181 | F28: 17101.95 | G28: =F28/F27-1 -> -0.029244231 | I28: ANOVA
B29: 44591 | C29: 21.71 | D29: =C29/C28-1 -> 0.026477541 | F29: 17516.3 | G29: =F29/F28-1 -> 0.024228231 | J29: df | K29: SS | L29: MS | M29: F | N29: Significance F
B30: 44598 | C30: 25 | D30: =C30/C29-1 -> 0.15154307 | F30: 17374.75 | G30: =F30/F29-1 -> -0.0080810445 | I30: Regression | J30: 1 | K30: 0.13421024 | L30: 0.13421024 | M30: 31.401076 | N30: 5.3780532e-08
B31: 44605 | C31: 26.32 | D31: =C31/C30-1 -> 0.0528 | F31: 17276.3 | G31: =F31/F30-1 -> -0.0056662686 | I31: Residual | J31: 258 | K31: 1.1027088 | L31: 0.0042740651
B32: 44612 | C32: 24.81 | D32: =C32/C31-1 -> -0.057370821 | F32: 16658.4 | G32: =F32/F31-1 -> -0.03576576 | I32: Total | J32: 259 | K32: 1.236919
B33: 44619 | C33: 23.95 | D33: =C33/C32-1 -> -0.034663442 | F33: 16245.35 | G33: =F33/F32-1 -> -0.024795298
B34: 44626 | C34: 24.36 | D34: =C34/C33-1 -> 0.017118998 | F34: 16630.45 | G34: =F34/F33-1 -> 0.023705245 | J34: Coefficients | K34: Standard Error | L34: t Stat | M34: P-value | N34: Lower 95% | O34: Upper 95% | P34: Lower 95.0% | Q34: Upper 95.0%
B35: 44633 | C35: 25.02 | D35: =C35/C34-1 -> 0.027093596 | F35: 17287.05 | G35: =F35/F34-1 -> 0.039481794 | I35: Intercept | J35: 0.0099154452 | K35: 0.0040627796 | L35: 2.440557 | M35: 0.015337984 | N35: 0.001915014 | O35: 0.017915876 | P35: 0.001915014 | Q35: 0.017915876
B36: 44640 | C36: 28.64 | D36: =C36/C35-1 -> 0.14468425 | F36: 17153 | G36: =F36/F35-1 -> -0.0077543595 | I36: X Variable 1 | J36: 1.2564617 | K36: 0.22422136 | L36: 5.6036663 | M36: 5.3780532e-08 | N36: 0.81492465 | O36: 1.6979987 | P36: 0.81492465 | Q36: 1.6979987
B37: 44647 | C37: 40.69 | D37: =C37/C36-1 -> 0.42074022 | F37: 17670.45 | G37: =F37/F36-1 -> 0.030166735
B38: 44654 | C38: 44.19 | D38: =C38/C37-1 -> 0.08601622 | F38: 17784.35 | G38: =F38/F37-1 -> 0.0064457894
B39: 44661 | C39: 44.65 | D39: =C39/C38-1 -> 0.010409595 | F39: 17475.65 | G39: =F39/F38-1 -> -0.017357958
B40: 44668 | C40: 51.82 | D40: =C40/C39-1 -> 0.16058231 | F40: 17171.95 | G40: =F40/F39-1 -> -0.017378467
B41: 44675 | C41: 56.07 | D41: =C41/C40-1 -> 0.082014666 | F41: 17102.55 | G41: =F41/F40-1 -> -0.0040414746
B42: 44682 | C42: 58.41 | D42: =C42/C41-1 -> 0.041733547 | F42: 16411.25 | G42: =F42/F41-1 -> -0.040420873
B43: 44689 | C43: 50.93 | D43: =C43/C42-1 -> -0.12806026 | F43: 15782.15 | G43: =F43/F42-1 -> -0.03833346
B44: 44696 | C44: 62.45 | D44: =C44/C43-1 -> 0.22619281 | F44: 16266.15 | G44: =F44/F43-1 -> 0.030667558
B45: 44703 | C45: 65.62 | D45: =C45/C44-1 -> 0.050760608 | F45: 16352.45 | G45: =F45/F44-1 -> 0.0053054964
B46: 44710 | C46: 56.82 | D46: =C46/C45-1 -> -0.13410546 | F46: 16584.3 | G46: =F46/F45-1 -> 0.014178304
B47: 44717 | C47: 56.02 | D47: =C47/C46-1 -> -0.014079549 | F47: 16201.8 | G47: =F47/F46-1 -> -0.023063982
B48: 44724 | C48: 52.26 | D48: =C48/C47-1 -> -0.067118886 | F48: 15293.5 | G48: =F48/F47-1 -> -0.056061672
... B270: 46278 | C270: 202.25 | D270: =C270/C269-1 -> -0.036767157 | F270: 23118.6 | G270: =F270/F269-1 -> -0.011945414

Sheet Rm
B1: NIFTY Return - Last 20 Yr
B4: Year | C4: Return
B5: 2025 | C5: 0.1051 | E5: Average Return | G5: {=(PRODUCT(1+C5:C30)^(1/COUNT(C5:C30)))-1} -> 0.11650334
B6: 2024 | C6: 0.0875 | E6: Dividend Yield | G6: 0.013
B7: 2023 | C7: 0.1942 | E7: Total Market Return | G7: =G5+G6 -> 0.12950334
B8: 2022 | C8: 0.0432
B9: 2021 | C9: 0.2412
B10: 2020 | C10: 0.149
B11: 2019 | C11: 0.1202
B12: 2018 | C12: 0.0315
B13: 2017 | C13: 0.2865
B14: 2016 | C14: 0.0301
B15: 2015 | C15: -0.0406
B16: 2014 | C16: 0.3139
B17: 2013 | C17: 0.0676
B18: 2012 | C18: 0.277
B19: 2011 | C19: -0.2462
... B30: 2000 | C30: -0.1465

Sheet Intrinsic Growth
B1: =Cover!B11 -> Adani Power
B4: Calculation of Reinvestment Rate
H6: =Model!K6 -> Projected
G7: =Model!J7 -> 2026 | H7: =Model!K7 -> 2027 | I7: =Model!L7 -> 2028 | J7: =Model!M7 -> 2029 | K7: =Model!N7 -> 2030 | L7: =Model!O7 -> 2031 | M7: =Model!P7 -> 2032
B9: Net Capex | G9: =-Model!K195-Model!K143 -> 27407.871 | H9: =-Model!L195-Model!L143 -> 40051.938 | I9: =-Model!M195-Model!M143 -> 45272.463 | J9: =-Model!N195-Model!N143 -> 32571.775 | K9: =-Model!O195-Model!O143 -> 12710.386 | L9: =-Model!P195-Model!P143 -> 1308.0359 | M9: =-Model!Q195-Model!Q143 -> 0
B10: Changes in Working Capital | G10: =Model!J371 -> -447.11 | H10: =Model!K371 -> -4410.9781 | I10: =Model!L371 -> -6552.8592 | J10: =Model!M371 -> -6313.489 | K10: =Model!N371 -> -13214.518 | L10: =Model!O371 -> -17800.025 | M10: =Model!P371 -> -11561.36
B11: Reinvestment | G11: =G9+G10 -> 26960.761 | H11: =H9+H10 -> 35640.96 | I11: =I9+I10 -> 38719.604 | J11: =J9+J10 -> 26258.286 | K11: =K9+K10 -> -504.13269 | L11: =L9+L10 -> -16491.989 | M11: =M9+M10 -> -11561.36
B13: EBIT | G13: =Model!J153 -> 19446.213 | H13: =Model!K153 -> 23625.494 | I13: =Model!L153 -> 30073.001 | J13: =Model!M153 -> 36241.91 | K13: =Model!N153 -> 49757.344 | L13: =Model!O153 -> 68137.196 | M13: =Model!P153 -> 79534.111
B14: Marginal Tax Rate | G14: =Assumptions!$H$45 -> 0.25168 | H14: =Assumptions!$H$45 -> 0.25168 | I14: =Assumptions!$H$45 -> 0.25168 | J14: =Assumptions!$H$45 -> 0.25168 | K14: =Assumptions!$H$45 -> 0.25168 | L14: =Assumptions!$H$45 -> 0.25168 | M14: =Assumptions!$H$45 -> 0.25168
B15: Post Tax EBIT | G15: =G13*(1-G14) -> 14551.99 | H15: =H13*(1-H14) -> 17679.43 | I15: =I13*(1-I14) -> 22504.228 | J15: =J13*(1-J14) -> 27120.546 | K15: =K13*(1-K14) -> 37234.416 | L15: =L13*(1-L14) -> 50988.426 | M15: =M13*(1-M14) -> 59516.966
B17: Reinvestment Rate | G17: =G11/G15 -> 1.8527199 | H17: =H11/H15 -> 2.0159565 | I17: =I11/I15 -> 1.720548 | J17: =J11/J15 -> 0.9682064 | K17: =K11/K15 -> -0.013539428 | L17: =L11/L15 -> -0.32344574 | M17: =M11/M15 -> -0.19425319
J19: Average Reinvestment Rate | M19: =AVERAGE(G17:M17) -> 0.86088463
J20: Median Reinvestment Rate | M20: =MEDIAN(G17:M17) -> 0.9682064
B22: Calculation of Intrinsic Growth Rate
H24: =H6 -> Projected
G25: =G7 -> 2026 | H25: =H7 -> 2027 | I25: =I7 -> 2028 | J25: =J7 -> 2029 | K25: =K7 -> 2030 | L25: =L7 -> 2031 | M25: =M7 -> 2032
B27: Reinvestment Rate | G27: =G17 -> 1.8527199 | H27: =H17 -> 2.0159565 | I27: =I17 -> 1.720548 | J27: =J17 -> 0.9682064 | K27: =K17 -> -0.013539428 | L27: =L17 -> -0.32344574 | M27: =M17 -> -0.19425319
B28: ROIC | G28: ='Ratio Analysis'!F32 -> 0.091024748 | H28: ='Ratio Analysis'!G32 -> 0.088029704 | I28: ='Ratio Analysis'!H32 -> 0.086218652 | J28: ='Ratio Analysis'!I32 -> 0.082669914 | K28: ='Ratio Analysis'!J32 -> 0.10188157 | L28: ='Ratio Analysis'!K32 -> 0.13899603 | M28: ='Ratio Analysis'!L32 -> 0.16624719
B30: Intrinsic Growth | G30: =G27*G28 -> 0.16864336 | H30: =H27*H28 -> 0.17746405 | I30: =I27*I28 -> 0.14834333 | J30: =J27*J28 -> 0.08004154 | K30: =K27*K28 -> -0.0013794182 | L30: =L27*L28 -> -0.044957672 | M30: =M27*M28 -> -0.032294046
J32: Average Intrinsic Growth | M32: =AVERAGE(G30:M30) -> 0.070837306
J33: Median Intrinsic Growth | M33: =MEDIAN(G30:M30) -> 0.08004154

Sheet DCF
B1: =Cover!B11 -> Adani Power
B2: DCF Valuation
B5: Calculation of PV of FCFF
B7: Terminal Growth Rate | D7: =Scenarios!I68 -> 0.045
B8: WACC | D8: =Scenarios!I61 -> 0.091480245 | H8: =Model!K126 -> Projected
G9: =Model!J127 -> 2026 | H9: =Model!K127 -> 2027 | I9: =Model!L127 -> 2028 | J9: =Model!M127 -> 2029 | K9: =Model!N127 -> 2030 | L9: =Model!O127 -> 2031 | M9: =Model!P127 -> 2032
B11: CFO | G11: =Model!J190 -> 21649.046 | H11: =Model!K190 -> 19356.54 | I11: =Model!L190 -> 25192.708 | J11: =Model!M190 -> 31400.288 | K11: =Model!N190 -> 38730 | L11: =Model!O190 -> 52505.559 | M11: =Model!P190 -> 68373.615
B12: Add: Tax adjusted Interest | G12: =Model!J156*Assumptions!$H$45 -> 847.36377 | H12: =Model!K156*Assumptions!$H$45 -> 844.79773 | I12: =Model!L156*Assumptions!$H$45 -> 1063.6242 | J12: =Model!M156*Assumptions!$H$45 -> 1321.5756 | K12: =Model!N156*Assumptions!$H$45 -> 1550.2616 | L12: =Model!O156*Assumptions!$H$45 -> 1994.9078 | M12: =Model!P156*Assumptions!$H$45 -> 2101.3951
B13: Less: Capex | G13: =Model!J284 -> 23350.09 | H13: =Model!K284 -> 28851.7 | I13: =Model!L284 -> 41769.5 | J13: =Model!M284 -> 47265.5 | K13: =Model!N284 -> 35093.5 | L13: =Model!O284 -> 15945.5 | M13: =Model!P284 -> 5057.5
B14: Free Cash Flow to Firm | G14: =G11+G12-G13 -> -853.68004 | H14: =H11+H12-H13 -> -8650.3623 | I14: =I11+I12-I13 -> -15513.168 | J14: =J11+J12-J13 -> -14543.637 | K14: =K11+K12-K13 -> 5186.7618 | L14: =L11+L12-L13 -> 38554.967 | M14: =M11+M12-M13 -> 65417.51
B16: Mid Year Convention | H16: 0.5 | I16: =H16+1 -> 1.5 | J16: =I16+1 -> 2.5 | K16: =J16+1 -> 3.5 | L16: =K16+1 -> 4.5 | M16: =L16+1 -> 5.5
B17: Discounting Factor | H17: =1/(1+$D$8)^H16 -> 0.95717657 | I17: =1/(1+$D$8)^I16 -> 0.87695272 | J17: =1/(1+$D$8)^J16 -> 0.80345267 | K17: =1/(1+$D$8)^K16 -> 0.73611289 | L17: =1/(1+$D$8)^L16 -> 0.67441705 | M17: =1/(1+$D$8)^M16 -> 0.61789213
B19: PV of FCFF | H19: =H14*H17 -> -8279.9241 | I19: =I14*I17 -> -13604.315 | J19: =J14*J17 -> -11685.124 | K19: =K14*K17 -> 3818.0422 | L19: =L14*L17 -> 26002.127 | M19: =M14*M17 -> 40420.965
B21: Calculation of Terminal Value
B22: FCFF (n+1) | D22: =M14*(1+D7) -> 68361.298
B23: WACC | D23: =D8 -> 0.091480245
B24: Terminal Growth Rate | D24: =D7 -> 0.045
B25: Terminal Value | D25: =D22/(D23-D24) -> 1470760.3
B27: Calculation of Equity Value Per Share | G27: Senstivity Analysis
B28: PV of FCFF | E28: =SUM(H19:M19) -> 36671.771 | M28: =Model!P1 -> CURRENTLY RUNNING: BASE CASE SCENARIO
B29: PV of Terminal Value | E29: =D25*M17 -> 908771.2 | G29: Equity Value Per Share
B30: Enterprise Value | E30: =SUM(E28:E29) -> 945442.97 | I30: WACC
H31: =E37 -> 465.4978 | I31: =Scenarios!G61 -> 0.086480245 | J31: =Scenarios!H61 -> 0.088980245 | K31: =Scenarios!I61 -> 0.091480245 | L31: =Scenarios!J61 -> 0.093980245 | M31: =Scenarios!K61 -> 0.096480245
B32: Add: Cash | E32: =Model!J225 -> 6926.32 | G32: Terminal Growth Rate | H32: =Scenarios!G68 -> 0.04 | I32: 465.4978 | J32: 441.44526 | K32: 419.72882 | L32: 400.0239 | M32: 382.06338
B33: Less: Debt | E33: =Model!J240+Model!J245+Model!J247 -> 54671 | H33: =Scenarios!H68 -> 0.0425 | I33: 492.2848 | J33: 465.4978 | K33: 441.44526 | L33: 419.72882 | M33: 400.0239
B34: Value of Equity | E34: =E30+E32-E33 -> 897698.29 | H34: =Scenarios!I68 -> 0.045 | I34: 522.30069 | J34: 492.2848 | K34: 465.4978 | L34: 441.44526 | M34: 419.72882
B35: No. of Shares | E35: =Assumptions!O9 -> 1928.4695 | H35: =Scenarios!J68 -> 0.0475 | I35: 556.16673 | J35: 522.30069 | K35: 492.2848 | L35: 465.4978 | M35: 441.44526
H36: =Scenarios!K68 -> 0.05 | I36: 594.67445 | J36: 556.16673 | K36: 522.30069 | L36: 492.2848 | M36: 465.4978
B37: Equity Value per Share | E37: =E34/E35 -> 465.4978
B39: Share Price | E39: =Assumptions!O8 -> 202.71
B40: Discount / Premium | E40: =E39/E37 -> 0.4354693

Sheet Relative Valuation>>

Sheet Comp Valuation
B1: =Cover!B11 -> Adani Power
B2: Peers Valuation
B4: (₹ Crore)
D6: Market Data | J6: Financials | N6: Valuation
B7: Company | C7: Ticker | D7: Share Price | E7: Shares Outstading | F7: Equity Value | G7: Net Debt | H7: Enterprise Value | J7: Revenue | K7: EBITDA | L7: Net Income | N7: EV/Revenue | O7: EV/EBITDA | P7: P/E
B9: Adani Power | D9: =Assumptions!O8 -> 202.71 | E9: =Assumptions!O9 -> 1928.4695 | F9: =E9*D9 -> 390920.05 | G9: ='Historical Data'!Q82+'Historical Data'!Q77+'Historical Data'!Q84-'Historical Data'!Q47 -> 47744.68 | H9: =F9+G9 -> 438664.73 | J9: ='Historical Data'!Q8 -> 54240.52 | K9: ='Historical Data'!Q20 -> 23430.87 | L9: ='Historical Data'!Q30 -> 12971.08 | N9: =H9/J9 -> 8.087399 | O9: =H9/K9 -> 18.721658 | P9: =F9/L9 -> 30.137818
B10: ='Comp Data'!C6 -> NTPC | D10: ='Comp Data'!E6 -> 325.9 | E10: ='Comp Data'!F6 -> 969.67 | F10: =E10*D10 -> 316015.45 | G10: ='Comp Data'!I6 -> 263000.8 | H10: =F10+G10 -> 579016.25 | J10: ='Comp Data'!L6 -> 191058.77 | K10: ='Comp Data'!M6 -> 60059.41 | L10: ='Comp Data'!N6 -> 27762.97 | N10: =H10/J10 -> 3.0305662 | O10: =H10/K10 -> 9.640725 | P10: =F10/L10 -> 11.382624
B11: ='Comp Data'!C7 -> Tata Power Co. | D11: ='Comp Data'!E7 -> 366.05 | E11: ='Comp Data'!F7 -> 319.53 | F11: =E11*D11 -> 116963.96 | G11: ='Comp Data'!I7 -> 62497.27 | H11: =F11+G11 -> 179461.23 | J11: ='Comp Data'!L7 -> 63444.78 | K11: ='Comp Data'!M7 -> 17228.43 | L11: ='Comp Data'!N7 -> 3915.45 | N11: =H11/J11 -> 2.8286208 | O11: =H11/K11 -> 10.416575 | P11: =F11/L11 -> 29.872417
B12: ='Comp Data'!C8 -> JSW Energy | D12: ='Comp Data'!E8 -> 514.2 | E12: ='Comp Data'!F8 -> 183.35 | F12: =E12*D12 -> 94278.57 | G12: ='Comp Data'!I8 -> 71180.56 | H12: =F12+G12 -> 165459.13 | J12: ='Comp Data'!L8 -> 18964.89 | K12: ='Comp Data'!M8 -> 11097.94 | L12: ='Comp Data'!N8 -> 2006.08 | N12: =H12/J12 -> 8.7244972 | O12: =H12/K12 -> 14.908995 | P12: =F12/L12 -> 46.996416
B13: ='Comp Data'!C9 -> Torrent Power | D13: ='Comp Data'!E9 -> 1250 | E13: ='Comp Data'!F9 -> 50.39 | F13: =E13*D13 -> 62987.5 | G13: ='Comp Data'!I9 -> 13139.13 | H13: =F13+G13 -> 76126.63 | J13: ='Comp Data'!L9 -> 29184.09 | K13: ='Comp Data'!M9 -> 5894.85 | L13: ='Comp Data'!N9 -> 2323.84 | N13: =H13/J13 -> 2.6084976 | O13: =H13/K13 -> 12.914091 | P13: =F13/L13 -> 27.104921
B14: ='Comp Data'!C10 -> CESC | D14: ='Comp Data'!E10 -> 141.75 | E14: ='Comp Data'!F10 -> 132.56 | F14: =E14*D14 -> 18790.38 | G14: ='Comp Data'!I10 -> 16098.54 | H14: =F14+G14 -> 34888.92 | J14: ='Comp Data'!L10 -> 18853 | K14: ='Comp Data'!M10 -> 4676 | L14: ='Comp Data'!N10 -> 1554 | N14: =H14/J14 -> 1.8505766 | O14: =H14/K14 -> 7.4612746 | P14: =F14/L14 -> 12.091622
B16: High | N16: =MAX(N10:N14) -> 8.7244972 | O16: =MAX(O10:O14) -> 14.908995 | P16: =MAX(P10:P14) -> 46.996416
B17: 75th Percentile | N17: =QUARTILE(N10:N14,3) -> 3.0305662 | O17: =QUARTILE(O10:O14,3) -> 12.914091 | P17: =QUARTILE(P10:P14,3) -> 29.872417
B18: Average | N18: =AVERAGE(N10:N14) -> 3.8085517 | O18: =AVERAGE(O10:O14) -> 11.068332 | P18: =AVERAGE(P10:P14) -> 25.4896
B19: Median | N19: =QUARTILE(N10:N14,2) -> 2.8286208 | O19: =QUARTILE(O10:O14,2) -> 10.416575 | P19: =QUARTILE(P10:P14,2) -> 27.104921
B20: 25th Percentile | N20: =QUARTILE(N10:N14,1) -> 2.6084976 | O20: =QUARTILE(O10:O14,1) -> 9.640725 | P20: =QUARTILE(P10:P14,1) -> 12.091622
B21: Low | N21: =MIN(N10:N14) -> 1.8505766 | O21: =MIN(O10:O14) -> 7.4612746 | P21: =MIN(P10:P14) -> 11.382624
B24: =B1 -> Adani Power
B25: Comparable Valuation
B27: =B4 -> (₹ Crore)
N28: =N7 -> EV/Revenue | O28: =O7 -> EV/EBITDA | P28: =P7 -> P/E
B29: Implied Enterprise Valuation | N29: =N$19*J9 -> 153425.86 | O29: =O$19*K9 -> 244069.41 | P29: =P31+P30 -> 399324.78
B30: Net Debt | N30: =$G$9 -> 47744.68 | O30: =$G$9 -> 47744.68 | P30: =$G$9 -> 47744.68
B31: Implied Market Value | N31: =N29-N30 -> 105681.18 | O31: =O29-O30 -> 196324.73 | P31: =P19*L9 -> 351580.1
B32: Shares Outstanding | N32: =$E$9 -> 1928.4695 | O32: =$E$9 -> 1928.4695 | P32: =$E$9 -> 1928.4695
B34: Implied Value Per Share | N34: =N31/N32 -> 54.800549 | O34: =O31/O32 -> 101.80339 | P34: =P31/P32 -> 182.31043

Sheet Analysis>>

Sheet Ratio Analysis
B1: =Cover!B11 -> Adani Power
B2: Ratio Analysis
G5: Projected
F6: =G6-1 -> 2026 | G6: =Assumptions!H8 -> 2027 | H6: =G6+1 -> 2028 | I6: =H6+1 -> 2029 | J6: =I6+1 -> 2030 | K6: =J6+1 -> 2031 | L6: =K6+1 -> 2032 | M6: Trend | N6: MEAN | O6: MEDIAN
B8: GROWTH OVER PRIOR PERIOD
C9: Revenue Growth | F9: =Model!J130 -> -0.024601799 | G9: =Model!K130 -> 0.17228946 | H9: =Model!L130 -> 0.21868143 | I9: =Model!M130 -> 0.17285081 | J9: =Model!N130 -> 0.30879657 | K9: =Model!O130 -> 0.31787697 | L9: =Model!P130 -> 0.15649629 | N9: =AVERAGE(F9:L9) -> 0.18891282 | O9: =MEDIAN(F9:L9) -> 0.17285081
C10: Gross Profit Growth | F10: =(Model!J137/Model!I137)-1 -> -0.025815965 | G10: =(Model!K137/Model!J137)-1 -> 0.21765672 | H10: =(Model!L137/Model!K137)-1 -> 0.27958063 | I10: =(Model!M137/Model!L137)-1 -> 0.2084641 | J10: =(Model!N137/Model!M137)-1 -> 0.37577107 | K10: =(Model!O137/Model!N137)-1 -> 0.37023842 | L10: =(Model!P137/Model!O137)-1 -> 0.16836233 | N10: =AVERAGE(F10:L10) -> 0.22775105 | O10: =MEDIAN(F10:L10) -> 0.21765672
C11: EBITDA Growth | F11: =(Model!J147/Model!I147)-1 -> 0.00010674995 | G11: =(Model!K147/Model!J147)-1 -> 0.19762241 | H11: =(Model!L147/Model!K147)-1 -> 0.25684579 | I11: =(Model!M147/Model!L147)-1 -> 0.19436459 | J11: =(Model!N147/Model!M147)-1 -> 0.35496181 | K11: =(Model!O147/Model!N147)-1 -> 0.35456448 | L11: =(Model!P147/Model!O147)-1 -> 0.16184276 | N11: =AVERAGE(F11:L11) -> 0.21718694 | O11: =MEDIAN(F11:L11) -> 0.19762241
C12: EBIT Growth | F12: =(Model!J153/Model!I153)-1 -> -0.012847519 | G12: =(Model!K153/Model!J153)-1 -> 0.2149149 | H12: =(Model!L153/Model!K153)-1 -> 0.27290465 | I12: =(Model!M153/Model!L153)-1 -> 0.20513115 | J12: =(Model!N153/Model!M153)-1 -> 0.37292278 | K12: =(Model!O153/Model!N153)-1 -> 0.36938973 | L12: =(Model!P153/Model!O153)-1 -> 0.16726423 | N12: =AVERAGE(F12:L12) -> 0.22709713 | O12: =MEDIAN(F12:L12) -> 0.2149149
C13: EBT Growth | F13: =(Model!J159/Model!I159)-1 -> -0.017123198 | G13: =(Model!K159/Model!J159)-1 -> 0.26054959 | H13: =(Model!L159/Model!K159)-1 -> 0.27520266 | I13: =(Model!M159/Model!L159)-1 -> 0.19901769 | J13: =(Model!N159/Model!M159)-1 -> 0.40679033 | K13: =(Model!O159/Model!N159)-1 -> 0.38105549 | L13: =(Model!P159/Model!O159)-1 -> 0.18225641 | N13: =AVERAGE(F13:L13) -> 0.24110699 | O13: =MEDIAN(F13:L13) -> 0.26054959
C14: Net Profit Growth | F14: =(Model!J165/Model!I165)-1 -> 0.062852344 | G14: =(Model!K165/Model!J165)-1 -> 0.11930084 | H14: =(Model!L165/Model!K165)-1 -> 0.27520266 | I14: =(Model!M165/Model!L165)-1 -> 0.19901769 | J14: =(Model!N165/Model!M165)-1 -> 0.40679033 | K14: =(Model!O165/Model!N165)-1 -> 0.38105549 | L14: =(Model!P165/Model!O165)-1 -> 0.18225641 | N14: =AVERAGE(F14:L14) -> 0.23235368 | O14: =MEDIAN(F14:L14) -> 0.19901769
C15: EPS Growth | F15: =Model!J173 -> 0.173768 | G15: =Model!K173 -> 0.11930084 | H15: =Model!L173 -> 0.27520266 | I15: =Model!M173 -> 0.19901769 | J15: =Model!N173 -> 0.40679033 | K15: =Model!O173 -> 0.38105549 | L15: =Model!P173 -> 0.18225641 | N15: =AVERAGE(F15:L15) -> 0.24819877 | O15: =MEDIAN(F15:L15) -> 0.19901769
B17: MARGIN ANALYSIS
C18: Gross profit Margin | F18: =Model!J138 -> 0.42113859 | G18: =Model!K138 -> 0.43743653 | H18: =Model!L138 -> 0.45929584 | I18: =Model!M138 -> 0.47324223 | J18: =Model!N138 -> 0.49745926 | K18: =Model!O138 -> 0.51722414 | L18: =Model!P138 -> 0.52253104 | N18: =AVERAGE(F18:L18) -> 0.47547538 | O18: =MEDIAN(F18:L18) -> 0.47324223
C19: SG&A Margin | F19: =(SUM(Model!J141:J143)-Model!J144)/Model!J129 -> -0.016850664 | G19: =(SUM(Model!K141:K143)-Model!K144)/Model!K129 -> -0.010017586 | H19: =(SUM(Model!L141:L143)-Model!L144)/Model!L129 -> -0.0021707968 | I19: =(SUM(Model!M141:M143)-Model!M144)/Model!M129 -> 0.0033108431 | J19: =(SUM(Model!N141:N143)-Model!N144)/Model!N129 -> 0.010951962 | K19: =(SUM(Model!O141:O143)-Model!O144)/Model!O129 -> 0.017173293 | L19: =(SUM(Model!P141:P143)-Model!P144)/Model!P129 -> 0.020168459 | N19: =AVERAGE(F19:L19) -> 0.0032236444 | O19: =MEDIAN(F19:L19) -> 0.0033108431
C20: EBITDA Margin | F20: =Model!J148 -> 0.43798925 | G20: =Model!K148 -> 0.44745412 | H20: =Model!L148 -> 0.46146664 | I20: =Model!M148 -> 0.46993139 | J20: =Model!N148 -> 0.4865073 | K20: =Model!O148 -> 0.50005085 | L20: =Model!P148 -> 0.50236258 | N20: =AVERAGE(F20:L20) -> 0.47225173 | O20: =MEDIAN(F20:L20) -> 0.46993139
C21: EBT Margin | F21: =Model!J154 -> 0.35472589 | G21: =Model!K154 -> 0.36762403 | H21: =Model!L154 -> 0.38398085 | I21: =Model!M154 -> 0.39454915 | J21: =Model!N154 -> 0.4138806 | K21: =Model!O154 -> 0.43005823 | L21: =Model!P154 -> 0.43406243 | N21: =AVERAGE(F21:L21) -> 0.39698303 | O21: =MEDIAN(F21:L21) -> 0.39454915
C22: Net Profit Margin | F22: =Model!J166 -> 0.24718818 | G22: =Model!K166 -> 0.23601503 | H22: =Model!L166 -> 0.24696117 | I22: =Model!M166 -> 0.252471 | J22: =Model!N166 -> 0.2713743 | K22: =Model!O166 -> 0.28438388 | L22: =Model!P166 -> 0.29071833 | N22: =AVERAGE(F22:L22) -> 0.2613017 | O22: =MEDIAN(F22:L22) -> 0.252471
B24: COMMON SIZING
C25: COGS % Sales | F25: =Model!J135 -> 0.57886141 | G25: =Model!K135 -> 0.56256347 | H25: =Model!L135 -> 0.54070416 | I25: =Model!M135 -> 0.52675777 | J25: =Model!N135 -> 0.50254074 | K25: =Model!O135 -> 0.48277586 | L25: =Model!P135 -> 0.47746896 | N25: =AVERAGE(F25:L25) -> 0.52452462 | O25: =MEDIAN(F25:L25) -> 0.52675777
C26: SG&A % Sales | F26: =Model!J145 -> -0.016850664 | G26: =Model!K145 -> -0.010017586 | H26: =Model!L145 -> -0.0021707968 | I26: =Model!M145 -> 0.0033108431 | J26: =Model!N145 -> 0.010951962 | K26: =Model!O145 -> 0.017173293 | L26: =Model!P145 -> 0.020168459 | N26: =AVERAGE(F26:L26) -> 0.0032236444 | O26: =MEDIAN(F26:L26) -> 0.0033108431
C27: Depreciation % Sales | F27: =Model!J151 -> 0.083263358 | G27: =Model!K151 -> 0.079830087 | H27: =Model!L151 -> 0.077485784 | I27: =Model!M151 -> 0.07538224 | J27: =Model!N151 -> 0.072626697 | K27: =Model!O151 -> 0.069992617 | L27: =Model!P151 -> 0.068300147 | N27: =AVERAGE(F27:L27) -> 0.075268704 | O27: =MEDIAN(F27:L27) -> 0.07538224
B29: PROFITABILITY
C30: Return on Asset | F30: =Model!J165/AVERAGE(Model!I237:J237) -> 0.10812959 | G30: =Model!K165/AVERAGE(Model!J237:K237) -> 0.099995193 | H30: =Model!L165/AVERAGE(Model!K237:L237) -> 0.10303905 | I30: =Model!M165/AVERAGE(Model!L237:M237) -> 0.098905921 | J30: =Model!N165/AVERAGE(Model!M237:N237) -> 0.11604617 | K30: =Model!O165/AVERAGE(Model!N237:O237) -> 0.13852512 | L30: =Model!P165/AVERAGE(Model!O237:P237) -> 0.14212842 | N30: =AVERAGE(F30:L30) -> 0.11525278 | O30: =MEDIAN(F30:L30) -> 0.10812959
C31: Return on Capital Employed | F31: =Model!J153/(Model!J255+Model!J240+Model!J245+Model!J246+Model!J247+Model!J248) -> 0.16258304 | G31: =Model!K153/(Model!K255+Model!K240+Model!K245+Model!K246+Model!K247+Model!K248) -> 0.16105152 | H31: =Model!L153/(Model!L255+Model!L240+Model!L245+Model!L246+Model!L247+Model!L248) -> 0.16000711 | I31: =Model!M153/(Model!M255+Model!M240+Model!M245+Model!M246+Model!M247+Model!M248) -> 0.1547625 | J31: =Model!N153/(Model!N255+Model!N240+Model!N245+Model!N246+Model!N247+Model!N248) -> 0.18278396 | K31: =Model!O153/(Model!O255+Model!O240+Model!O245+Model!O246+Model!O247+Model!O248) -> 0.22099915 | L31: =Model!P153/(Model!P255+Model!P240+Model!P245+Model!P246+Model!P247+Model!P248) -> 0.22360648 | N31: =AVERAGE(F31:L31) -> 0.18082768 | O31: =MEDIAN(F31:L31) -> 0.16258304
C32: Return on Invested Capital | F32: =Model!J153*(1-Assumptions!$H$45)/(Model!J235+Model!J251) -> 0.091024748 | G32: =Model!K153*(1-Assumptions!$H$45)/(Model!K235+Model!K251) -> 0.088029704 | H32: =Model!L153*(1-Assumptions!$H$45)/(Model!L235+Model!L251) -> 0.086218652 | I32: =Model!M153*(1-Assumptions!$H$45)/(Model!M235+Model!M251) -> 0.082669914 | J32: =Model!N153*(1-Assumptions!$H$45)/(Model!N235+Model!N251) -> 0.10188157 | K32: =Model!O153*(1-Assumptions!$H$45)/(Model!O235+Model!O251) -> 0.13899603 | L32: =Model!P153*(1-Assumptions!$H$45)/(Model!P235+Model!P251) -> 0.16624719 | N32: =AVERAGE(F32:L32) -> 0.10786683 | O32: =MEDIAN(F32:L32) -> 0.091024748
C33: Return on Equity | F33: =Model!J168/AVERAGE(Model!I255:J255) -> 0.22111196 | G33: =Model!K168/AVERAGE(Model!J255:K255) -> 0.20717996 | H33: =Model!L168/AVERAGE(Model!K255:L255) -> 0.2138051 | I33: =Model!M168/AVERAGE(Model!L255:M255) -> 0.20756224 | J33: =Model!N168/AVERAGE(Model!M255:N255) -> 0.23363847 | K33: =Model!O168/AVERAGE(Model!N255:O255) -> 0.2524484 | L33: =Model!P168/AVERAGE(Model!O255:P255) -> 0.23400204 | N33: =AVERAGE(F33:L33) -> 0.22424974 | O33: =MEDIAN(F33:L33) -> 0.22111196
B35: ASSET TURNOVER
C36: Total Asset Turnover | F36: =Model!J129/AVERAGE(Model!I237:J237) -> 0.43743835 | G36: =Model!K129/AVERAGE(Model!J237:K237) -> 0.42368146 | H36: =Model!L129/AVERAGE(Model!K237:L237) -> 0.41722774 | I36: =Model!M129/AVERAGE(Model!L237:M237) -> 0.39175162 | J36: =Model!N129/AVERAGE(Model!M237:N237) -> 0.42762402 | K36: =Model!O129/AVERAGE(Model!N237:O237) -> 0.48710609 | L36: =Model!P129/AVERAGE(Model!O237:P237) -> 0.48888703 | N36: =AVERAGE(F36:L36) -> 0.43910233 | O36: =MEDIAN(F36:L36) -> 0.42762402
C37: Fixed Asset Turnover | F37: =Model!J129/AVERAGE(Model!I235:J235) -> 0.59352917 | G37: =Model!K129/AVERAGE(Model!J235:K235) -> 0.56046002 | H37: =Model!L129/AVERAGE(Model!K235:L235) -> 0.53787208 | I37: =Model!M129/AVERAGE(Model!L235:M235) -> 0.49553468 | J37: =Model!N129/AVERAGE(Model!M235:N235) -> 0.54295383 | K37: =Model!O129/AVERAGE(Model!N235:O235) -> 0.66117965 | L37: =Model!P129/AVERAGE(Model!O235:P235) -> 0.76437716 | N37: =AVERAGE(F37:L37) -> 0.59370094 | O37: =MEDIAN(F37:L37) -> 0.56046002
C38: Inventory Turnover | F38: =(Model!J135*Model!J129)/AVERAGE(Model!I223:J223) -> 9.1440736 | G38: =(Model!K135*Model!K129)/AVERAGE(Model!J223:K223) -> 9.3296868 | H38: =(Model!L135*Model!L129)/AVERAGE(Model!K223:L223) -> 9.4591483 | I38: =(Model!M135*Model!M129)/AVERAGE(Model!L223:M223) -> 9.3637937 | J38: =(Model!N135*Model!N129)/AVERAGE(Model!M223:N223) -> 9.7631862 | K38: =(Model!O135*Model!O129)/AVERAGE(Model!N223:O223) -> 9.8353974 | L38: =(Model!P135*Model!P129)/AVERAGE(Model!O223:P223) -> 9.4037429 | N38: =AVERAGE(F38:L38) -> 9.4712898 | O38: =MEDIAN(F38:L38) -> 9.4037429
C39: Trade Receivable Turnover | F39: =Model!J129/AVERAGE(Model!I224:J224) -> 4.4185051 | G39: =Model!K129/AVERAGE(Model!J224:K224) -> 5.017667 | H39: =Model!L129/AVERAGE(Model!K224:L224) -> 5.1071653 | I39: =Model!M129/AVERAGE(Model!L224:M224) -> 5.0187728 | J39: =Model!N129/AVERAGE(Model!M224:N224) -> 5.2707346 | K39: =Model!O129/AVERAGE(Model!N224:O224) -> 5.2865112 | L39: =Model!P129/AVERAGE(Model!O224:P224) -> 4.9863206 | N39: =AVERAGE(F39:L39) -> 5.0150966 | O39: =MEDIAN(F39:L39) -> 5.0187728
C40: Trade payable Turnover | F40: =Model!J241/AVERAGE(Model!I129:J129) -> 0.051178362 | G40: =Model!K241/AVERAGE(Model!J129:K129) -> 0.054339772 | H40: =Model!L241/AVERAGE(Model!K129:L129) -> 0.053086678 | I40: =Model!M241/AVERAGE(Model!L129:M129) -> 0.050751228 | J40: =Model!N241/AVERAGE(Model!M129:N129) -> 0.050786855 | K40: =Model!O241/AVERAGE(Model!N129:O129) -> 0.048875067 | L40: =Model!P241/AVERAGE(Model!O129:P129) -> 0.045535976 | N40: =AVERAGE(F40:L40) -> 0.050650562 | O40: =MEDIAN(F40:L40) -> 0.050786855
B42: SOLVENCY RATIO
C43: Debt / Equity | F43: =(Model!J240+Model!J245+Model!J247)/Model!J255 -> 0.84190987 | G43: =(Model!K240+Model!K245+Model!K247)/Model!K255 -> 0.83494734 | H43: =(Model!L240+Model!L245+Model!L247)/Model!L255 -> 0.89685656 | I43: =(Model!M240+Model!M245+Model!M247)/Model!M255 -> 0.91899338 | J43: =(Model!N240+Model!N245+Model!N247)/Model!N255 -> 0.76406241 | K43: =(Model!O240+Model!O245+Model!O247)/Model!O255 -> 0.55011405 | L43: =(Model!P240+Model!P245+Model!P247)/Model!P255 -> 0.41366228 | N43: =AVERAGE(F43:L43) -> 0.74579227 | O43: =MEDIAN(F43:L43) -> 0.83494734
C44: Debt / Capital | F44: =(Model!J240+Model!J245+Model!J247)/(Model!J243+Model!J245+Model!J255) -> 0.45015277 | G44: =(Model!K240+Model!K245+Model!K247)/(Model!K243+Model!K245+Model!K255) -> 0.44812674 | H44: =(Model!L240+Model!L245+Model!L247)/(Model!L243+Model!L245+Model!L255) -> 0.46578022 | I44: =(Model!M240+Model!M245+Model!M247)/(Model!M243+Model!M245+Model!M255) -> 0.47203995 | J44: =(Model!N240+Model!N245+Model!N247)/(Model!N243+Model!N245+Model!N255) -> 0.42604042 | K44: =(Model!O240+Model!O245+Model!O247)/(Model!O243+Model!O245+Model!O255) -> 0.34807425 | L44: =(Model!P240+Model!P245+Model!P247)/(Model!P243+Model!P245+Model!P255) -> 0.28692537 | N44: =AVERAGE(F44:L44) -> 0.4138771 | O44: =MEDIAN(F44:L44) -> 0.44812674
C45: Total Liab / Total Asset | F45: =(Model!J243+Model!J251)/Model!J237 -> 0.51786825 | G45: =(Model!K243+Model!K251)/Model!K237 -> 0.51399039 | H45: =(Model!L243+Model!L251)/Model!L237 -> 0.51902518 | I45: =(Model!M243+Model!M251)/Model!M237 -> 0.51697743 | J45: =(Model!N243+Model!N251)/Model!N237 -> 0.47152306 | K45: =(Model!O243+Model!O251)/Model!O237 -> 0.40003898 | L45: =(Model!P243+Model!P251)/Model!P237 -> 0.34267423 | N45: =AVERAGE(F45:L45) -> 0.46887107 | O45: =MEDIAN(F45:L45) -> 0.51399039
C46: Interest Coverate ratio | F46: =Model!J153/Model!J156 -> 5.7758226 | G46: =Model!K153/Model!K156 -> 7.0384473 | H46: =Model!L153/Model!L156 -> 7.1160218 | I46: =Model!M153/Model!M156 -> 6.9018857 | J46: =Model!N153/Model!N156 -> 8.0779455 | K46: =Model!O153/Model!O156 -> 8.5962718 | L46: =Model!P153/Model!P156 -> 9.5256456 | N46: =AVERAGE(F46:L46) -> 7.5760058 | O46: =MEDIAN(F46:L46) -> 7.1160218
C47: Total Debt / EBITDA | F47: =(Model!J240+Model!J245+Model!J247)/Model!J147 -> 2.2769391 | G47: =(Model!K240+Model!K245+Model!K247)/Model!K147 -> 2.321272 | H47: =(Model!L240+Model!L245+Model!L247)/Model!L147 -> 2.4587733 | I47: =(Model!M240+Model!M245+Model!M247)/Model!M147 -> 2.5980041 | J47: =(Model!N240+Model!N245+Model!N247)/Model!N147 -> 2.01587 | K47: =(Model!O240+Model!O245+Model!O247)/Model!O147 -> 1.3810569 | L47: =(Model!P240+Model!P245+Model!P247)/Model!P147 -> 1.1307088 | N47: =AVERAGE(F47:L47) -> 2.0260892 | O47: =MEDIAN(F47:L47) -> 2.2769391
B49: DAYS
C50: Inventories | F50: =365/F38 -> 39.916564 | G50: =365/G38 -> 39.122428 | H50: =365/H38 -> 38.586983 | I50: =365/I38 -> 38.979928 | J50: =365/J38 -> 37.385336 | K50: =365/K38 -> 37.110854 | L50: =365/L38 -> 38.814332 | N50: =AVERAGE(F50:L50) -> 38.559489 | O50: =MEDIAN(F50:L50) -> 38.814332
C51: Trade receivables | F51: =365/F39 -> 82.607124 | G51: =365/G39 -> 72.74297 | H51: =365/H39 -> 71.468218 | I51: =365/I39 -> 72.726943 | J51: =365/J39 -> 69.250309 | K51: =365/K39 -> 69.043644 | L51: =365/L39 -> 73.200267 | N51: =AVERAGE(F51:L51) -> 73.005639 | O51: =MEDIAN(F51:L51) -> 72.726943
C52: Trade payables | F52: =365/F40 -> 7131.9203 | G52: =365/G40 -> 6716.9954 | H52: =365/H40 -> 6875.548 | I52: =365/I40 -> 7191.9443 | J52: =365/J40 -> 7186.8991 | K52: =365/K40 -> 7468.0204 | L52: =365/L40 -> 8015.6402 | N52: =AVERAGE(F52:L52) -> 7226.7097 | O52: =MEDIAN(F52:L52) -> 7186.8991
C53: Cash Conversion Cycle | F53: =F50+F51-F52 -> -7009.3966 | G53: =G50+G51-G52 -> -6605.13 | H53: =H50+H51-H52 -> -6765.4928 | I53: =I50+I51-I52 -> -7080.2374 | J53: =J50+J51-J52 -> -7080.2635 | K53: =K50+K51-K52 -> -7361.8659 | L53: =L50+L51-L52 -> -7903.6256 | N53: =AVERAGE(F53:L53) -> -7115.1445 | O53: =MEDIAN(F53:L53) -> -7080.2374
C55: CFO/Sales | F55: =Model!J190/Model!J129 -> 0.39490863 | G55: =Model!K190/Model!K129 -> 0.30119706 | H55: =Model!L190/Model!L129 -> 0.32166784 | I55: =Model!M190/Model!M129 -> 0.34184061 | J55: =Model!N190/Model!N129 -> 0.32215537 | K55: =Model!O190/Model!O129 -> 0.33139679 | L55: =Model!P190/Model!P129 -> 0.37315332 | N55: =AVERAGE(F55:L55) -> 0.3409028 | O55: =MEDIAN(F55:L55) -> 0.33139679
C56: CFO/Total Asset | F56: =Model!J190/AVERAGE(Model!I237:J237) -> 0.17274818 | G56: =Model!K190/AVERAGE(Model!J237:K237) -> 0.12761161 | H56: =Model!L190/AVERAGE(Model!K237:L237) -> 0.13420875 | I56: =Model!M190/AVERAGE(Model!L237:M237) -> 0.13391661 | J56: =Model!N190/AVERAGE(Model!M237:N237) -> 0.13776138 | K56: =Model!O190/AVERAGE(Model!N237:O237) -> 0.1614254 | L56: =Model!P190/AVERAGE(Model!O237:P237) -> 0.18242982 | N56: =AVERAGE(F56:L56) -> 0.15001453 | O56: =MEDIAN(F56:L56) -> 0.13776138
C57: CFO/Total Debt | F57: =Model!J190/(Model!J240+Model!J245+Model!J247) -> 0.39598775 | G57: =Model!K190/(Model!K240+Model!K245+Model!K247) -> 0.28998543 | H57: =Model!L190/(Model!L240+Model!L245+Model!L247) -> 0.28349725 | I57: =Model!M190/(Model!M240+Model!M245+Model!M247) -> 0.27999442 | J57: =Model!N190/(Model!N240+Model!N245+Model!N247) -> 0.32848346 | K57: =Model!O190/(Model!O240+Model!O245+Model!O247) -> 0.47986884 | L57: =Model!P190/(Model!P240+Model!P245+Model!P247) -> 0.65693024 | N57: =AVERAGE(F57:L57) -> 0.38782106 | O57: =MEDIAN(F57:L57) -> 0.32848346

Sheet Common Size Analysis
B1: =Cover!B11 -> Adani Power
B2: Income Statement - Common Size
B4: (%)
I5: =Model!K181 -> Projected
F6: =Model!H182 -> 2024 | G6: =Model!I182 -> 2025 | H6: =Model!J182 -> 2026 | I6: =Model!K182 -> 2027 | J6: =Model!L182 -> 2028 | K6: =Model!M182 -> 2029 | L6: =Model!N182 -> 2030 | M6: =Model!O182 -> 2031 | N6: =Model!P182 -> 2032
B7: REVENUE
C8: Sales | F8: =Model!H129/Model!H$129 -> 1 | G8: =Model!I129/Model!I$129 -> 1 | H8: =Model!J129/Model!J$129 -> 1 | I8: =Model!K129/Model!K$129 -> 1 | J8: =Model!L129/Model!L$129 -> 1 | K8: =Model!M129/Model!M$129 -> 1 | L8: =Model!N129/Model!N$129 -> 1 | M8: =Model!O129/Model!O$129 -> 1 | N8: =Model!P129/Model!P$129 -> 1
B9: COGS
C10: Power and Fuel | F10: =Model!H133/Model!H$129 -> 0.56508309 | G10: =Model!I133/Model!I$129 -> 0.53864031 | H10: =Model!J133/Model!J$129 -> 0.53206514 | I10: =Model!K133/Model!K$129 -> 0.5168998 | J10: =Model!L133/Model!L$129 -> 0.49613061 | K10: =Model!M133/Model!M$129 -> 0.48265789 | L10: =Model!N133/Model!N$129 -> 0.45990757 | M10: =Model!O133/Model!O$129 -> 0.44127426 | N10: =Model!P133/Model!P$129 -> 0.43587789
C11: Other Mfr. Exp | F11: =Model!H134/Model!H$129 -> 0.036877734 | G11: =Model!I134/Model!I$129 -> 0.039696216 | H11: =Model!J134/Model!J$129 -> 0.046796272 | I11: =Model!K134/Model!K$129 -> 0.045663667 | J11: =Model!L134/Model!L$129 -> 0.044573552 | K11: =Model!M134/Model!M$129 -> 0.044099883 | L11: =Model!N134/Model!N$129 -> 0.042633172 | M11: =Model!O134/Model!O$129 -> 0.041501592 | N11: =Model!P134/Model!P$129 -> 0.041591067
C12: Gross Profit | F12: =Model!H137/Model!H$129 -> 0.39803917 | G12: =Model!I137/Model!I$129 -> 0.42166347 | H12: =Model!J137/Model!J$129 -> 0.42113859 | I12: =Model!K137/Model!K$129 -> 0.43743653 | J12: =Model!L137/Model!L$129 -> 0.45929584 | K12: =Model!M137/Model!M$129 -> 0.47324223 | L12: =Model!N137/Model!N$129 -> 0.49745926 | M12: =Model!O137/Model!O$129 -> 0.51722414 | N12: =Model!P137/Model!P$129 -> 0.52253104
B13: SG&A
C14: Employee Cost | F14: =Model!H141/Model!H$129 -> 0.012793525 | G14: =Model!I141/Model!I$129 -> 0.013996206 | H14: =Model!J141/Model!J$129 -> 0.015647644 | I14: =Model!K141/Model!K$129 -> 0.015268926 | J14: =Model!L141/Model!L$129 -> 0.014904415 | K14: =Model!M141/Model!M$129 -> 0.014746031 | L14: =Model!N141/Model!N$129 -> 0.014255595 | M14: =Model!O141/Model!O$129 -> 0.01387722 | N14: =Model!P141/Model!P$129 -> 0.013907138
C15: Selling and admin | F15: =Model!H142/Model!H$129 -> 0.0090329436 | G15: =Model!I142/Model!I$129 -> 0.0096715323 | H15: =Model!J142/Model!J$129 -> 0.010598428 | I15: =Model!K142/Model!K$129 -> 0.010341916 | J15: =Model!L142/Model!L$129 -> 0.010095026 | K15: =Model!M142/Model!M$129 -> 0.0099877495 | L15: =Model!N142/Model!N$129 -> 0.0096555687 | M15: =Model!O142/Model!O$129 -> 0.0093992882 | N15: =Model!P142/Model!P$129 -> 0.0094195526
C16: Other Expenses | F16: =Model!H143/Model!H$129 -> 0.014203421 | G16: =Model!I143/Model!I$129 -> 0.016907611 | H16: =Model!J143/Model!J$129 -> 0.023023914 | I16: =Model!K143/Model!K$129 -> 0.022466668 | J16: =Model!L143/Model!L$129 -> 0.021930329 | K16: =Model!M143/Model!M$129 -> 0.021697282 | L16: =Model!N143/Model!N$129 -> 0.020975656 | M16: =Model!O143/Model!O$129 -> 0.020418915 | N16: =Model!P143/Model!P$129 -> 0.020462937
C17: Other Income | F17: =Model!H144/Model!H$129 -> 0.19628728 | G17: =Model!I144/Model!I$129 -> 0.046080207 | H17: =Model!J144/Model!J$129 -> 0.06612065 | I17: =Model!K144/Model!K$129 -> 0.058095096 | J17: =Model!L144/Model!L$129 -> 0.049100567 | K17: =Model!M144/Model!M$129 -> 0.043120219 | L17: =Model!N144/Model!N$129 -> 0.033934858 | M17: =Model!O144/Model!O$129 -> 0.026522129 | N17: =Model!P144/Model!P$129 -> 0.023621168
C18: EBITDA | F18: =Model!H147/Model!H$129 -> 0.55829657 | G18: =Model!I147/Model!I$129 -> 0.42716833 | H18: =Model!J147/Model!J$129 -> 0.43798925 | I18: =Model!K147/Model!K$129 -> 0.44745412 | J18: =Model!L147/Model!L$129 -> 0.46146664 | K18: =Model!M147/Model!M$129 -> 0.46993139 | L18: =Model!N147/Model!N$129 -> 0.4865073 | M18: =Model!O147/Model!O$129 -> 0.50005085 | N18: =Model!P147/Model!P$129 -> 0.50236258
C19: Depreciation | F19: =Model!H150/Model!H$129 -> 0.078078101 | G19: =Model!I150/Model!I$129 -> 0.076666247 | H19: =Model!J150/Model!J$129 -> 0.083263358 | I19: =Model!K150/Model!K$129 -> 0.079830087 | J19: =Model!L150/Model!L$129 -> 0.077485784 | K19: =Model!M150/Model!M$129 -> 0.07538224 | L19: =Model!N150/Model!N$129 -> 0.072626697 | M19: =Model!O150/Model!O$129 -> 0.069992617 | N19: =Model!P150/Model!P$129 -> 0.068300147
C20: EBIT | F20: =Model!H153/Model!H$129 -> 0.48021847 | G20: =Model!I153/Model!I$129 -> 0.35050208 | H20: =Model!J153/Model!J$129 -> 0.35472589 | I20: =Model!K153/Model!K$129 -> 0.36762403 | J20: =Model!L153/Model!L$129 -> 0.38398085 | K20: =Model!M153/Model!M$129 -> 0.39454915 | L20: =Model!N153/Model!N$129 -> 0.4138806 | M20: =Model!O153/Model!O$129 -> 0.43005823 | N20: =Model!P153/Model!P$129 -> 0.43406243
C21: Interest | F21: =Model!H156/Model!H$129 -> 0.067289094 | G21: =Model!I156/Model!I$129 -> 0.059423601 | H21: =Model!J156/Model!J$129 -> 0.061415649 | I21: =Model!K156/Model!K$129 -> 0.052230842 | J21: =Model!L156/Model!L$129 -> 0.053960044 | K21: =Model!M156/Model!M$129 -> 0.057165413 | L21: =Model!N156/Model!N$129 -> 0.051235874 | M21: =Model!O156/Model!O$129 -> 0.050028459 | N21: =Model!P156/Model!P$129 -> 0.04556777
C22: EBT | F22: =Model!H159/Model!H$129 -> 0.41292937 | G22: =Model!I159/Model!I$129 -> 0.29107848 | H22: =Model!J159/Model!J$129 -> 0.29331025 | I22: =Model!K159/Model!K$129 -> 0.31539319 | J22: =Model!L159/Model!L$129 -> 0.33002081 | K22: =Model!M159/Model!M$129 -> 0.33738373 | L22: =Model!N159/Model!N$129 -> 0.36264473 | M22: =Model!O159/Model!O$129 -> 0.38002978 | N22: =Model!P159/Model!P$129 -> 0.38849466
C23: Tax | F23: =Model!H162/Model!H$129 -> -0.0007403987 | G23: =Model!I162/Model!I$129 -> 0.064229565 | H23: =Model!J162/Model!J$129 -> 0.04612207 | I23: =Model!K162/Model!K$129 -> 0.079378157 | J23: =Model!L162/Model!L$129 -> 0.083059637 | K23: =Model!M162/Model!M$129 -> 0.084912738 | L23: =Model!N162/Model!N$129 -> 0.091270425 | M23: =Model!O162/Model!O$129 -> 0.095645894 | N23: =Model!P162/Model!P$129 -> 0.097776337
C24: Net Profit | F24: =Model!H165/Model!H$129 -> 0.41366977 | G24: =Model!I165/Model!I$129 -> 0.22684892 | H24: =Model!J165/Model!J$129 -> 0.24718818 | I24: =Model!K165/Model!K$129 -> 0.23601503 | J24: =Model!L165/Model!L$129 -> 0.24696117 | K24: =Model!M165/Model!M$129 -> 0.252471 | L24: =Model!N165/Model!N$129 -> 0.2713743 | M24: =Model!O165/Model!O$129 -> 0.28438388 | N24: =Model!P165/Model!P$129 -> 0.29071833
B27: =B1 -> Adani Power
B28: Balance Sheet - Common Size
B30: =B4 -> (%)
I31: =I5 -> Projected
F32: =F6 -> 2024 | G32: =G6 -> 2025 | H32: =H6 -> 2026 | I32: =I6 -> 2027 | J32: =J6 -> 2028 | K32: =K6 -> 2029 | L32: =L6 -> 2030 | M32: =M6 -> 2031 | N32: =N6 -> 2032
B33: ASSETS
C34: Inventories | F34: =Model!H223/Model!H$237 -> 0.045018745 | G34: =Model!I223/Model!I$237 -> 0.029377976 | H34: =Model!J223/Model!J$237 -> 0.026309417 | I34: =Model!K223/Model!K$237 -> 0.024913505 | J34: =Model!L223/Model!L$237 -> 0.023009542 | K34: =Model!M223/Model!M$237 -> 0.021251372 | L34: =Model!N223/Model!N$237 -> 0.022660697 | M34: =Model!O223/Model!O$237 -> 0.02499973 | N34: =Model!P223/Model!P$237 -> 0.024670188
C35: Total Trade receivables | F35: =Model!H224/Model!H$237 -> 0.12691241 | G35: =Model!I224/Model!I$237 -> 0.1153234 | H35: =Model!J224/Model!J$237 -> 0.085619528 | I35: =Model!K224/Model!K$237 -> 0.083455484 | J35: =Model!L224/Model!L$237 -> 0.080304219 | K35: =Model!M224/Model!M$237 -> 0.076238435 | L35: =Model!N224/Model!N$237 -> 0.085315733 | M35: =Model!O224/Model!O$237 -> 0.098096412 | N35: =Model!P224/Model!P$237 -> 0.098001794
C36: Cash Equivalents | F36: =Model!H225/Model!H$237 -> 0.07838159 | G36: =Model!I225/Model!I$237 -> 0.054197924 | H36: =Model!J225/Model!J$237 -> 0.050290726 | I36: =Model!K225/Model!K$237 -> 0.03018579 | J36: =Model!L225/Model!L$237 -> 0.02383394 | K36: =Model!M225/Model!M$237 -> 0.019292508 | L36: =Model!N225/Model!N$237 -> 0.016495735 | M36: =Model!O225/Model!O$237 -> 0.066737535 | N36: =Model!P225/Model!P$237 -> 0.17903239
C37: Loans n Advances | F37: =Model!H226/Model!H$237 -> 0.013498776 | G37: =Model!I226/Model!I$237 -> 0.0093608381 | H37: =Model!J226/Model!J$237 -> 0.010738745 | I37: =Model!K226/Model!K$237 -> 0.010579226 | J37: =Model!L226/Model!L$237 -> 0.010179756 | K37: =Model!M226/Model!M$237 -> 0.0096643573 | L37: =Model!N226/Model!N$237 -> 0.01081504 | M37: =Model!O226/Model!O$237 -> 0.012435181 | N37: =Model!P226/Model!P$237 -> 0.012423187
C38: Other asset items | F38: =Model!H227/Model!H$237 -> 0.037181412 | G38: =Model!I227/Model!I$237 -> 0.061124413 | H38: =Model!J227/Model!J$237 -> 0.084784534 | I38: =Model!K227/Model!K$237 -> 0.083525097 | J38: =Model!L227/Model!L$237 -> 0.080371204 | K38: =Model!M227/Model!M$237 -> 0.076302028 | L38: =Model!N227/Model!N$237 -> 0.085386897 | M38: =Model!O227/Model!O$237 -> 0.098178237 | N38: =Model!P227/Model!P$237 -> 0.09808354
C39: Total Current Assets | F39: =Model!H228/Model!H$237 -> 0.30099293 | G39: =Model!I228/Model!I$237 -> 0.26938455 | H39: =Model!J228/Model!J$237 -> 0.25774295 | I39: =Model!K228/Model!K$237 -> 0.2326591 | J39: =Model!L228/Model!L$237 -> 0.21769866 | K39: =Model!M228/Model!M$237 -> 0.2027487 | L39: =Model!N228/Model!N$237 -> 0.2206741 | M39: =Model!O228/Model!O$237 -> 0.30044709 | N39: =Model!P228/Model!P$237 -> 0.4122111
C41: Gross Block | F41: =Model!H230/Model!H$237 -> 0.98588889 | G41: =Model!I230/Model!I$237 -> 0.89545228 | H41: =Model!J230/Model!J$237 -> 0.74042798 | I41: =Model!K230/Model!K$237 -> 0.76964336 | J41: =Model!L230/Model!L$237 -> 0.70909728 | K41: =Model!M230/Model!M$237 -> 0.65652936 | L41: =Model!N230/Model!N$237 -> 0.78798439 | M41: =Model!O230/Model!O$237 -> 0.82816794 | N41: =Model!P230/Model!P$237 -> 0.77059412
C42: Accumulated Depreciation | F42: =Model!H231/Model!H$237 -> -0.30099608 | G42: =Model!I231/Model!I$237 -> -0.28175104 | H42: =Model!J231/Model!J$237 -> -0.26369493 | I42: =Model!K231/Model!K$237 -> -0.25022722 | J42: =Model!L231/Model!L$237 -> -0.22650089 | K42: =Model!M231/Model!M$237 -> -0.21005995 | L42: =Model!N231/Model!N$237 -> -0.20841405 | M42: =Model!O231/Model!O$237 -> -0.21375422 | N42: =Model!P231/Model!P$237 -> -0.21576877
C43: Net Block | F43: =Model!H232/Model!H$237 -> 0.6848928 | G43: =Model!I232/Model!I$237 -> 0.61370124 | H43: =Model!J232/Model!J$237 -> 0.47673305 | I43: =Model!K232/Model!K$237 -> 0.51941614 | J43: =Model!L232/Model!L$237 -> 0.48259639 | K43: =Model!M232/Model!M$237 -> 0.44646941 | L43: =Model!N232/Model!N$237 -> 0.57957034 | M43: =Model!O232/Model!O$237 -> 0.61441372 | N43: =Model!P232/Model!P$237 -> 0.55482534
C44: Capital Work in Progress | F44: =Model!H233/Model!H$237 -> 0.010054741 | G44: =Model!I233/Model!I$237 -> 0.10719727 | H44: =Model!J233/Model!J$237 -> 0.25451668 | I44: =Model!K233/Model!K$237 -> 0.23877249 | J44: =Model!L233/Model!L$237 -> 0.29247855 | K44: =Model!M233/Model!M$237 -> 0.34493244 | L44: =Model!N233/Model!N$237 -> 0.19475408 | M44: =Model!O233/Model!O$237 -> 0.080775567 | N44: =Model!P233/Model!P$237 -> 0.029194059
C45: Investments | F45: =Model!H234/Model!H$237 -> 0.0040595233 | G45: =Model!I234/Model!I$237 -> 0.0097169396 | H45: =Model!J234/Model!J$237 -> 0.011007323 | I45: =Model!K234/Model!K$237 -> 0.0091522713 | J45: =Model!L234/Model!L$237 -> 0.007226403 | K45: =Model!M234/Model!M$237 -> 0.0058494497 | L45: =Model!N234/Model!N$237 -> 0.005001474 | M45: =Model!O234/Model!O$237 -> 0.0043636222 | N45: =Model!P234/Model!P$237 -> 0.0037695005
C46: Total Non-Current Assets | F46: =Model!H235/Model!H$237 -> 0.69900707 | G46: =Model!I235/Model!I$237 -> 0.73061545 | H46: =Model!J235/Model!J$237 -> 0.74225705 | I46: =Model!K235/Model!K$237 -> 0.7673409 | J46: =Model!L235/Model!L$237 -> 0.78230134 | K46: =Model!M235/Model!M$237 -> 0.7972513 | L46: =Model!N235/Model!N$237 -> 0.7793259 | M46: =Model!O235/Model!O$237 -> 0.69955291 | N46: =Model!P235/Model!P$237 -> 0.5877889
C48: TOTAL ASSETS | F48: =Model!H237/Model!H$237 -> 1 | G48: =Model!I237/Model!I$237 -> 1 | H48: =Model!J237/Model!J$237 -> 1 | I48: =Model!K237/Model!K$237 -> 1 | J48: =Model!L237/Model!L$237 -> 1 | K48: =Model!M237/Model!M$237 -> 1 | L48: =Model!N237/Model!N$237 -> 1 | M48: =Model!O237/Model!O$237 -> 1 | N48: =Model!P237/Model!P$237 -> 1
B50: LIABILITIES AND EQUITY
C51: Short term Borrowings | F51: =Model!H240/Model!H$237 -> 0.085448776 | G51: =Model!I240/Model!I$237 -> 0.094653394 | H51: =Model!J240/Model!J$237 -> 0.077879499 | I51: =Model!K240/Model!K$237 -> 0.048496491 | J51: =Model!L240/Model!L$237 -> 0.038291608 | K51: =Model!M240/Model!M$237 -> 0.030995343 | L51: =Model!N240/Model!N$237 -> 0.026502049 | M51: =Model!O240/Model!O$237 -> 0.023122169 | N51: =Model!P240/Model!P$237 -> 0.019974009
C52: Trade Payables | F52: =Model!H241/Model!H$237 -> 0.039224705 | G52: =Model!I241/Model!I$237 -> 0.026373298 | H52: =Model!J241/Model!J$237 -> 0.020627975 | I52: =Model!K241/Model!K$237 -> 0.019533506 | J52: =Model!L241/Model!L$237 -> 0.018040698 | K52: =Model!M241/Model!M$237 -> 0.0166622 | L52: =Model!N241/Model!N$237 -> 0.017767186 | M52: =Model!O241/Model!O$237 -> 0.01960111 | N52: =Model!P241/Model!P$237 -> 0.019342732
C53: Advance from Customers | F53: =Model!H242/Model!H$237 -> 5.43429e-05 | G53: =Model!I242/Model!I$237 -> 0.00018597692 | H53: =Model!J242/Model!J$237 -> 0.00084225451 | I53: =Model!K242/Model!K$237 -> 0.00082974319 | J53: =Model!L242/Model!L$237 -> 0.00079841223 | K53: =Model!M242/Model!M$237 -> 0.0007579888 | L53: =Model!N242/Model!N$237 -> 0.00084823843 | M53: =Model!O242/Model!O$237 -> 0.00097530834 | N53: =Model!P242/Model!P$237 -> 0.00097436762
C54: Total Current Liabilities | F54: =Model!H243/Model!H$237 -> 0.12472782 | G54: =Model!I243/Model!I$237 -> 0.12121267 | H54: =Model!J243/Model!J$237 -> 0.099349728 | I54: =Model!K243/Model!K$237 -> 0.06885974 | J54: =Model!L243/Model!L$237 -> 0.057130719 | K54: =Model!M243/Model!M$237 -> 0.048415531 | L54: =Model!N243/Model!N$237 -> 0.045117473 | M54: =Model!O243/Model!O$237 -> 0.043698588 | N54: =Model!P243/Model!P$237 -> 0.040291109
C56: Long term Borrowings | F56: =Model!H245/Model!H$237 -> 0.28904988 | G56: =Model!I245/Model!I$237 -> 0.24484304 | H56: =Model!J245/Model!J$237 -> 0.3109807 | I56: =Model!K245/Model!K$237 -> 0.34775415 | J56: =Model!L245/Model!L$237 -> 0.3799906 | K56: =Model!M245/Model!M$237 -> 0.39741937 | L56: =Model!N245/Model!N$237 -> 0.35880775 | M56: =Model!O245/Model!O$237 -> 0.28861329 | N56: =Model!P245/Model!P$237 -> 0.23604969
C57: Preference Capital | F57: =Model!H246/Model!H$237 -> 0.004684358 | G57: =Model!I246/Model!I$237 -> 0.0012309901 | H57: =Model!J246/Model!J$237 -> 0.0011036438 | I57: =Model!K246/Model!K$237 -> 0.00091764803 | J57: =Model!L246/Model!L$237 -> 0.00072455178 | K57: =Model!M246/Model!M$237 -> 0.00058649223 | L57: =Model!N246/Model!N$237 -> 0.00050147036 | M57: =Model!O246/Model!O$237 -> 0.00043751646 | N57: =Model!P246/Model!P$237 -> 0.00037794713
C58: Lease Liabilities | F58: =Model!H247/Model!H$237 -> 0.0017281042 | G58: =Model!I247/Model!I$237 -> 0.010273011 | H58: =Model!J247/Model!J$237 -> 0.0080958085 | I58: =Model!K247/Model!K$237 -> 0.006729922 | J58: =Model!L247/Model!L$237 -> 0.0053137769 | K58: =Model!M247/Model!M$237 -> 0.0043012646 | L58: =Model!N247/Model!N$237 -> 0.0036777242 | M58: =Model!O247/Model!O$237 -> 0.0032086939 | N58: =Model!P247/Model!P$237 -> 0.0027718195
C59: Other Borrowings | F59: =Model!H248/Model!H$237 -> -0.0019998187 | G59: =Model!I248/Model!I$237 -> -0.0012309901 | H59: =Model!J248/Model!J$237 -> -0.0011036438 | I59: =Model!K248/Model!K$237 -> -0.00091764803 | J59: =Model!L248/Model!L$237 -> -0.00072455178 | K59: =Model!M248/Model!M$237 -> -0.00058649223 | L59: =Model!N248/Model!N$237 -> -0.00050147036 | M59: =Model!O248/Model!O$237 -> -0.00043751646 | N59: =Model!P248/Model!P$237 -> -0.00037794713
C60: Deferred Tax Liability | F60: =Model!H249/Model!H$237 -> 0 | G60: =Model!I249/Model!I$237 -> 0 | H60: =Model!J249/Model!J$237 -> 0.042309857 | I60: =Model!K249/Model!K$237 -> 0.043142834 | J60: =Model!L249/Model!L$237 -> 0.039082328 | K60: =Model!M249/Model!M$237 -> 0.036480411 | L60: =Model!N249/Model!N$237 -> 0.037960579 | M60: =Model!O249/Model!O$237 -> 0.041869564 | N60: =Model!P249/Model!P$237 -> 0.04399648
C61: Other liability items | F61: =Model!H250/Model!H$237 -> 0.11556409 | G61: =Model!I250/Model!I$237 -> 0.11291588 | H61: =Model!J250/Model!J$237 -> 0.05713216 | I61: =Model!K250/Model!K$237 -> 0.047503744 | J61: =Model!L250/Model!L$237 -> 0.03750776 | K61: =Model!M250/Model!M$237 -> 0.030360853 | L61: =Model!N250/Model!N$237 -> 0.025959539 | M61: =Model!O250/Model!O$237 -> 0.022648847 | N61: =Model!P250/Model!P$237 -> 0.019565131
C62: Total Non-Current Liabilities | F62: =Model!H251/Model!H$237 -> 0.40902662 | G62: =Model!I251/Model!I$237 -> 0.36803193 | H62: =Model!J251/Model!J$237 -> 0.41851852 | I62: =Model!K251/Model!K$237 -> 0.44513065 | J62: =Model!L251/Model!L$237 -> 0.46189446 | K62: =Model!M251/Model!M$237 -> 0.4685619 | L62: =Model!N251/Model!N$237 -> 0.42640559 | M62: =Model!O251/Model!O$237 -> 0.35634039 | N62: =Model!P251/Model!P$237 -> 0.30238312
C64: Equity Share Capital | F64: =Model!H253/Model!H$237 -> 0.041919461 | G64: =Model!I253/Model!I$237 -> 0.034157229 | H64: =Model!J253/Model!J$237 -> 0.028004527 | I64: =Model!K253/Model!K$237 -> 0.023284956 | J64: =Model!L253/Model!L$237 -> 0.018385215 | K64: =Model!M253/Model!M$237 -> 0.014882009 | L64: =Model!N253/Model!N$237 -> 0.012724612 | M64: =Model!O253/Model!O$237 -> 0.011101807 | N64: =Model!P253/Model!P$237 -> 0.0095902592
... C70: TOTAL LIABILITIES AND EQUITY | F70: =Model!H259/Model!H$237 -> 1 | G70: =Model!I259/Model!I$237 -> 1 | H70: =Model!J259/Model!J$237 -> 1 | I70: =Model!K259/Model!K$237 -> 1.006458 | J70: =Model!L259/Model!L$237 -> 1.0000633 | K70: =Model!M259/Model!M$237 -> 0.99583915 | L70: =Model!N259/Model!N$237 -> 0.98860051 | M70: =Model!O259/Model!O$237 -> 0.98086398 | N70: =Model!P259/Model!P$237 -> 0.97687076

Sheet Football Field
B1: =Cover!B11 -> Adani Power
B2: Football Field Analysis
I5: =B2 & " - Data Table" -> Football Field Analysis - Data Table
K6: Open_Low | L6: Low | M6: Open_High | N6: High
I7: Comps | K7: =L7 -> 54.800549 | L7: =MIN('Comp Valuation'!N34:P34) -> 54.800549 | M7: =N7 -> 182.31043 | N7: =MAX('Comp Valuation'!N34:P34) -> 182.31043
I8: DCF Worst Case | K8: =L8 -> 181.36418 | L8: 181.36418 | M8: =N8 -> 245.18774 | N8: 245.18774
I9: DCF Base Case | K9: =L9 -> 382.06338 | L9: 382.06338 | M9: =N9 -> 594.67445 | N9: 594.67445
I10: DCF Best Case | K10: =L10 -> 611.72045 | L10: 611.72045 | M10: =N10 -> 1243.5244 | N10: 1243.5244
I11: 52Weeks H/L | K11: =L11 -> 128.1 | L11: 128.1 | M11: =N11 -> 254.2 | N11: 254.2

Sheet VaR
B1: =Cover!B11 -> Adani Power
B2: Value at Risk
B5: Adani Power Historical Weekly returns | F5: Monte Carlo Return | I5: ="Calculation of Value at Risk - " & B1 -> Calculation of Value at Risk - Adani Power
B9: Date | C9: Price | D9: Weekly Returns | F9: Replication | G9: Simulated Return
B10: 44465 | C10: 19.39 | D10: 0.011476265 | F10: 1 | G10: =_xlfn.NORM.INV(RAND(), $M$11,$M$12) -> 0.032949953 | I10: Historical Approach
B11: 44472 | C11: 20.32 | D11: 0.047962867 | F11: 2 | G11: =_xlfn.NORM.INV(RAND(), $M$11,$M$12) -> 0.05733503 | I11: Mean | M11: =AVERAGE(D10:D269) -> 0.011370956
B12: 44479 | C12: 22.4 | D12: 0.1023622 | F12: 3 | G12: =_xlfn.NORM.INV(RAND(), $M$11,$M$12) -> -0.039357533 | I12: Std Deviation | M12: =STDEV(D10:D269) -> 0.069106796
B13: 44486 | C13: 23.41 | D13: 0.045089286 | F13: 4 | G13: =_xlfn.NORM.INV(RAND(), $M$11,$M$12) -> -0.017250851 | I13: Min | M13: =MIN(D10:D269) -> -0.22585199
B14: 44493 | C14: 20.1 | D14: -0.14139257 | F14: 5 | G14: =_xlfn.NORM.INV(RAND(), $M$11,$M$12) -> 0.092379921 | I14: Max | M14: =MAX(D10:D269) -> 0.42074022
B15: 44500 | C15: 21.08 | D15: 0.048756219 | F15: 6 | G15: =_xlfn.NORM.INV(RAND(), $M$11,$M$12) -> 0.047746143 | I15: CMP | M15: =Assumptions!O8 -> 202.71
B16: 44507 | C16: 21.69 | D16: 0.028937381 | F16: 7 | G16: =_xlfn.NORM.INV(RAND(), $M$11,$M$12) -> -0.10717095
B17: 44514 | C17: 20.58 | D17: -0.051175657 | F17: 8 | G17: =_xlfn.NORM.INV(RAND(), $M$11,$M$12) -> 0.079807529 | I17: Monte Carlo Simulation
B18: 44521 | C18: 20.25 | D18: -0.016034985 | F18: 9 | G18: =_xlfn.NORM.INV(RAND(), $M$11,$M$12) -> -0.060602813 | I18: Mean | M18: =AVERAGE(G10:G10009) -> 0.011436419
B19: 44528 | C19: 20.16 | D19: -0.0044444444 | F19: 10 | G19: =_xlfn.NORM.INV(RAND(), $M$11,$M$12) -> 0.076104994 | I19: Std Deviation | M19: =STDEV(G10:G10009) -> 0.06893976
B20: 44535 | C20: 20.81 | D20: 0.032242063 | F20: 11 | G20: =_xlfn.NORM.INV(RAND(), $M$11,$M$12) -> -0.01796271 | I20: Min | M20: =MIN(G10:G10009) -> -0.23604955
B21: 44542 | C21: 20.02 | D21: -0.037962518 | F21: 12 | G21: =_xlfn.NORM.INV(RAND(), $M$11,$M$12) -> 0.00874623 | I21: Max | M21: =MAX(G10:G10009) -> 0.2701282
B22: 44549 | C22: 19.73 | D22: -0.014485514 | F22: 13 | G22: =_xlfn.NORM.INV(RAND(), $M$11,$M$12) -> 0.061475541 | I22: CMP | M22: =M15 -> 202.71
B23: 44556 | C23: 19.94 | D23: 0.01064369 | F23: 14 | G23: =_xlfn.NORM.INV(RAND(), $M$11,$M$12) -> 0.012653802
B24: 44563 | C24: 20.04 | D24: 0.0050150451 | F24: 15 | G24: =_xlfn.NORM.INV(RAND(), $M$11,$M$12) -> 0.038539569 | I24: VaR - Historical Approach
B25: 44570 | C25: 23.43 | D25: 0.16916168 | F25: 16 | G25: =_xlfn.NORM.INV(RAND(), $M$11,$M$12) -> -0.056220875 | I25: Percentile | J25: Confidence | K25: VAR% | L25: Stock Price | M25: VAR (₹)
B26: 44577 | C26: 21.99 | D26: -0.061459667 | F26: 17 | G26: =_xlfn.NORM.INV(RAND(), $M$11,$M$12) -> 0.082447627 | I26: 0.1 | J26: =100%-I26 -> 0.9 | K26: =_xlfn.PERCENTILE.INC($D$10:$D$269,I26) -> -0.055341223 | L26: =$M$15+M26 -> 191.49178 | M26: =$M$15*K26 -> -11.218219
B27: 44584 | C27: 21.15 | D27: -0.038199181 | F27: 18 | G27: =_xlfn.NORM.INV(RAND(), $M$11,$M$12) -> 0.052055359 | I27: 0.05 | J27: =100%-I27 -> 0.95 | K27: =_xlfn.PERCENTILE.INC($D$10:$D$269,I27) -> -0.07217982 | L27: =$M$15+M27 -> 188.07843 | M27: =$M$15*K27 -> -14.631571
B28: 44591 | C28: 21.71 | D28: 0.026477541 | F28: 19 | G28: =_xlfn.NORM.INV(RAND(), $M$11,$M$12) -> -0.051974213 | I28: 0.01 | J28: =100%-I28 -> 0.99 | K28: =_xlfn.PERCENTILE.INC($D$10:$D$269,I28) -> -0.14614982 | L28: =$M$15+M28 -> 173.08397 | M28: =$M$15*K28 -> -29.626031
B29: 44598 | C29: 25 | D29: 0.15154307 | F29: 20 | G29: =_xlfn.NORM.INV(RAND(), $M$11,$M$12) -> -0.0058515514 | I29: 0.005 | J29: =100%-I29 -> 0.995 | K29: =_xlfn.PERCENTILE.INC($D$10:$D$269,I29) -> -0.15760475 | L29: =$M$15+M29 -> 170.76194 | M29: =$M$15*K29 -> -31.948059
B30: 44605 | C30: 26.32 | D30: 0.0528 | F30: 21 | G30: =_xlfn.NORM.INV(RAND(), $M$11,$M$12) -> 0.024300986
B31: 44612 | C31: 24.81 | D31: -0.057370821 | F31: 22 | G31: =_xlfn.NORM.INV(RAND(), $M$11,$M$12) -> 0.018528447 | I31: VaR - Monte Carlo Approach
B32: 44619 | C32: 23.95 | D32: -0.034663442 | F32: 23 | G32: =_xlfn.NORM.INV(RAND(), $M$11,$M$12) -> -0.086401051 | I32: Percentile | J32: Confidence | K32: VAR% | L32: Stock Price | M32: VAR (₹)
B33: 44626 | C33: 24.36 | D33: 0.017118998 | F33: 24 | G33: =_xlfn.NORM.INV(RAND(), $M$11,$M$12) -> -0.016034126 | I33: 0.1 | J33: =100%-I33 -> 0.9 | K33: =_xlfn.PERCENTILE.INC($G$10:$G$10009, I33) -> -0.076434691 | L33: =$M$22+M33 -> 187.21592 | M33: =K33*$M$22 -> -15.494076
B34: 44633 | C34: 25.02 | D34: 0.027093596 | F34: 25 | G34: =_xlfn.NORM.INV(RAND(), $M$11,$M$12) -> -0.015465159 | I34: 0.05 | J34: =100%-I34 -> 0.95 | K34: =_xlfn.PERCENTILE.INC($G$10:$G$10009, I34) -> -0.10147466 | L34: =$M$22+M34 -> 182.14007 | M34: =K34*$M$22 -> -20.569929
B35: 44640 | C35: 28.64 | D35: 0.14468425 | F35: 26 | G35: =_xlfn.NORM.INV(RAND(), $M$11,$M$12) -> -0.059060256 | I35: 0.01 | J35: =100%-I35 -> 0.99 | K35: =_xlfn.PERCENTILE.INC($G$10:$G$10009, I35) -> -0.14986467 | L35: =$M$22+M35 -> 172.33093 | M35: =K35*$M$22 -> -30.379068
B36: 44647 | C36: 40.69 | D36: 0.42074022 | F36: 27 | G36: =_xlfn.NORM.INV(RAND(), $M$11,$M$12) -> -0.029063896 | I36: 0.005 | J36: =100%-I36 -> 0.995 | K36: =_xlfn.PERCENTILE.INC($G$10:$G$10009, I36) -> -0.17117548 | L36: =$M$22+M36 -> 168.01102 | M36: =K36*$M$22 -> -34.698982
B37: 44654 | C37: 44.19 | D37: 0.08601622 | F37: 28 | G37: =_xlfn.NORM.INV(RAND(), $M$11,$M$12) -> 0.085225081
B38: 44661 | C38: 44.65 | D38: 0.010409595 | F38: 29 | G38: =_xlfn.NORM.INV(RAND(), $M$11,$M$12) -> -0.087204722
B39: 44668 | C39: 51.82 | D39: 0.16058231 | F39: 30 | G39: =_xlfn.NORM.INV(RAND(), $M$11,$M$12) -> 0.044485864
B40: 44675 | C40: 56.07 | D40: 0.082014666 | F40: 31 | G40: =_xlfn.NORM.INV(RAND(), $M$11,$M$12) -> 0.032111323
B41: 44682 | C41: 58.41 | D41: 0.041733547 | F41: 32 | G41: =_xlfn.NORM.INV(RAND(), $M$11,$M$12) -> -0.066550297
B42: 44689 | C42: 50.93 | D42: -0.12806026 | F42: 33 | G42: =_xlfn.NORM.INV(RAND(), $M$11,$M$12) -> -0.022022962
B43: 44696 | C43: 62.45 | D43: 0.22619281 | F43: 34 | G43: =_xlfn.NORM.INV(RAND(), $M$11,$M$12) -> -0.01061012
B44: 44703 | C44: 65.62 | D44: 0.050760608 | F44: 35 | G44: =_xlfn.NORM.INV(RAND(), $M$11,$M$12) -> -0.076678489
B45: 44710 | C45: 56.82 | D45: -0.13410546 | F45: 36 | G45: =_xlfn.NORM.INV(RAND(), $M$11,$M$12) -> 0.065905881
B46: 44717 | C46: 56.02 | D46: -0.014079549 | F46: 37 | G46: =_xlfn.NORM.INV(RAND(), $M$11,$M$12) -> 0.083020487
B47: 44724 | C47: 52.26 | D47: -0.067118886 | F47: 38 | G47: =_xlfn.NORM.INV(RAND(), $M$11,$M$12) -> 0.047924459
B48: 44731 | C48: 52.89 | D48: 0.012055109 | F48: 39 | G48: =_xlfn.NORM.INV(RAND(), $M$11,$M$12) -> -0.060520234
... B269: 46278 | C269: 202.25 | D269: -0.036767157 | F269: 260 | G269: =_xlfn.NORM.INV(RAND(), $M$11,$M$12) -> -0.020309475
F270: 261 | G270: =_xlfn.NORM.INV(RAND(), $M$11,$M$12) -> 0.11170168
F271: 262 | G271: =_xlfn.NORM.INV(RAND(), $M$11,$M$12) -> -0.06843363
F272: 263 | G272: =_xlfn.NORM.INV(RAND(), $M$11,$M$12) -> 0.060279092
F273: 264 | G273: =_xlfn.NORM.INV(RAND(), $M$11,$M$12) -> 0.048120865
F274: 265 | G274: =_xlfn.NORM.INV(RAND(), $M$11,$M$12) -> -0.12026805
F275: 266 | G275: =_xlfn.NORM.INV(RAND(), $M$11,$M$12) -> 0.036014702
F276: 267 | G276: =_xlfn.NORM.INV(RAND(), $M$11,$M$12) -> 0.031460783
F277: 268 | G277: =_xlfn.NORM.INV(RAND(), $M$11,$M$12) -> 0.06697054
F278: 269 | G278: =_xlfn.NORM.INV(RAND(), $M$11,$M$12) -> -0.045067765
F279: 270 | G279: =_xlfn.NORM.INV(RAND(), $M$11,$M$12) -> 0.091111016
F280: 271 | G280: =_xlfn.NORM.INV(RAND(), $M$11,$M$12) -> 0.017713166
F281: 272 | G281: =_xlfn.NORM.INV(RAND(), $M$11,$M$12) -> -0.065522048
... F10009: 10000 | G10009: =_xlfn.NORM.INV(RAND(), $M$11,$M$12) -> -0.10214915

Sheet Comps Beta>>

Sheet NTPC
B1: NTPC
B2: Regression Beta - 5Y Weekly
B5: Adani Power Weekly returns | F5: NIFTY Weekly Return | I5: Beta Drifting
B9: Date | C9: Price | D9: Weekly Returns | F9: Price | G9: Return | I9: Levered Raw Beta | J9: =J17 -> 0.81950281
B10: 44458 | C10: 124.25 | D10: 0 | F10: 17853.2 | G10: 0 | I10: Raw Beta Weight | J10: 0.75
B11: 44465 | C11: 139.9 | D11: =C11/C10-1 -> 0.12595573 | F11: 17532.05 | G11: =F11/F10-1 -> -0.017988372 | I11: Market Beta | J11: 1
B12: 44472 | C12: 141.1 | D12: =C12/C11-1 -> 0.0085775554 | F12: 17895.2 | G12: =F12/F11-1 -> 0.020713493 | I12: Market Beta Weight | J12: 0.25
B13: 44479 | C13: 149.4 | D13: =C13/C12-1 -> 0.058823529 | F13: 18338.55 | G13: =F13/F12-1 -> 0.0247748
B14: 44486 | C14: 144.9 | D14: =C14/C13-1 -> -0.030120482 | F14: 18114.9 | G14: =F14/F13-1 -> -0.012195621 | I14: Adjusted Beta | J14: =(J9*J10)+(J11*J12) -> 0.86462711
B15: 44493 | C15: 132.65 | D15: =C15/C14-1 -> -0.084541063 | F15: 17671.65 | G15: =F15/F14-1 -> -0.024468807
B16: 44500 | C16: 137.15 | D16: =C16/C15-1 -> 0.03392386 | F16: 17916.8 | G16: =F16/F15-1 -> 0.013872502
B17: 44507 | C17: 136.45 | D17: =C17/C16-1 -> -0.0051039008 | F17: 18102.75 | G17: =F17/F16-1 -> 0.010378527 | I17: Beta1 | J17: =J36 -> 0.81950281
B18: 44514 | C18: 135.3 | D18: =C18/C17-1 -> -0.0084279956 | F18: 17764.8 | G18: =F18/F17-1 -> -0.018668434
B19: 44521 | C19: 128.85 | D19: =C19/C18-1 -> -0.04767184 | F19: 17026.45 | G19: =F19/F18-1 -> -0.041562528 | I19: SUMMARY OUTPUT
B20: 44528 | C20: 127 | D20: =C20/C19-1 -> -0.01435778 | F20: 17196.7 | G20: =F20/F19-1 -> 0.0099991484
B21: 44535 | C21: 126.15 | D21: =C21/C20-1 -> -0.0066929134 | F21: 17511.3 | G21: =F21/F20-1 -> 0.018294208 | I21: Regression Statistics
B22: 44542 | C22: 125.55 | D22: =C22/C21-1 -> -0.0047562426 | F22: 16985.2 | G22: =F22/F21-1 -> -0.030043458 | I22: Multiple R | J22: 0.44819924
B23: 44549 | C23: 121.25 | D23: =C23/C22-1 -> -0.034249303 | F23: 17003.75 | G23: =F23/F22-1 -> 0.0010921273 | I23: R Square | J23: 0.20088256
B24: 44556 | C24: 124.4 | D24: =C24/C23-1 -> 0.025979381 | F24: 17354.05 | G24: =F24/F23-1 -> 0.020601338 | I24: Adjusted R Square | J24: 0.1977852
B25: 44563 | C25: 131.35 | D25: =C25/C24-1 -> 0.055868167 | F25: 17812.7 | G25: =F25/F24-1 -> 0.026428989 | I25: Standard Error | J25: 0.029640216
B26: 44570 | C26: 135.35 | D26: =C26/C25-1 -> 0.030452988 | F26: 18255.75 | G26: =F26/F25-1 -> 0.024872703 | I26: Observations | J26: 260
B27: 44577 | C27: 134.1 | D27: =C27/C26-1 -> -0.0092353158 | F27: 17617.15 | G27: =F27/F26-1 -> -0.034980759
B28: 44584 | C28: 140.15 | D28: =C28/C27-1 -> 0.045115585 | F28: 17101.95 | G28: =F28/F27-1 -> -0.029244231 | I28: ANOVA
B29: 44591 | C29: 134.2 | D29: =C29/C28-1 -> -0.042454513 | F29: 17516.3 | G29: =F29/F28-1 -> 0.024228231 | J29: df | K29: SS | L29: MS | M29: F | N29: Significance F
B30: 44598 | C30: 137.15 | D30: =C30/C29-1 -> 0.021982116 | F30: 17374.75 | G30: =F30/F29-1 -> -0.0080810445 | I30: Regression | J30: 1 | K30: 0.056978899 | L30: 0.056978899 | M30: 64.856175 | N30: 2.9826136e-14
B31: 44605 | C31: 132.35 | D31: =C31/C30-1 -> -0.034998177 | F31: 17276.3 | G31: =F31/F30-1 -> -0.0056662686 | I31: Residual | J31: 258 | K31: 0.22666394 | L31: 0.0008785424
B32: 44612 | C32: 130.35 | D32: =C32/C31-1 -> -0.015111447 | F32: 16658.4 | G32: =F32/F31-1 -> -0.03576576 | I32: Total | J32: 259 | K32: 0.28364284
B33: 44619 | C33: 130.2 | D33: =C33/C32-1 -> -0.001150748 | F33: 16245.35 | G33: =F33/F32-1 -> -0.024795298
B34: 44626 | C34: 131.95 | D34: =C34/C33-1 -> 0.01344086 | F34: 16630.45 | G34: =F34/F33-1 -> 0.023705245 | J34: Coefficients | K34: Standard Error | L34: t Stat | M34: P-value | N34: Lower 95% | O34: Upper 95% | P34: Lower 95.0% | Q34: Upper 95.0%
B35: 44633 | C35: 132.9 | D35: =C35/C34-1 -> 0.0071996969 | F35: 17287.05 | G35: =F35/F34-1 -> 0.039481794 | I35: Intercept | J35: 0.0033617751 | K35: 0.0018422891 | L35: 1.8247815 | M35: 0.06919036 | N35: -0.00026606312 | O35: 0.0069896133 | P35: -0.00026606312 | Q35: 0.0069896133
B36: 44640 | C36: 134.75 | D36: =C36/C35-1 -> 0.013920241 | F36: 17153 | G36: =F36/F35-1 -> -0.0077543595 | I36: X Variable 1 | J36: 0.81950281 | K36: 0.10175946 | L36: 8.0533331 | M36: 2.9826136e-14 | N36: 0.61911794 | O36: 1.0198877 | P36: 0.61911794 | Q36: 1.0198877
B37: 44647 | C37: 142.95 | D37: =C37/C36-1 -> 0.060853432 | F37: 17670.45 | G37: =F37/F36-1 -> 0.030166735
B38: 44654 | C38: 152.05 | D38: =C38/C37-1 -> 0.063658622 | F38: 17784.35 | G38: =F38/F37-1 -> 0.0064457894
B39: 44661 | C39: 153.95 | D39: =C39/C38-1 -> 0.01249589 | F39: 17475.65 | G39: =F39/F38-1 -> -0.017357958
B40: 44668 | C40: 160.45 | D40: =C40/C39-1 -> 0.0422215 | F40: 17171.95 | G40: =F40/F39-1 -> -0.017378467
B41: 44675 | C41: 156.2 | D41: =C41/C40-1 -> -0.026488002 | F41: 17102.55 | G41: =F41/F40-1 -> -0.0040414746
B42: 44682 | C42: 159 | D42: =C42/C41-1 -> 0.017925736 | F42: 16411.25 | G42: =F42/F41-1 -> -0.040420873
B43: 44689 | C43: 144.15 | D43: =C43/C42-1 -> -0.093396226 | F43: 15782.15 | G43: =F43/F42-1 -> -0.03833346
B44: 44696 | C44: 149.6 | D44: =C44/C43-1 -> 0.037807839 | F44: 16266.15 | G44: =F44/F43-1 -> 0.030667558
B45: 44703 | C45: 150.45 | D45: =C45/C44-1 -> 0.0056818182 | F45: 16352.45 | G45: =F45/F44-1 -> 0.0053054964
B46: 44710 | C46: 155 | D46: =C46/C45-1 -> 0.030242606 | F46: 16584.3 | G46: =F46/F45-1 -> 0.014178304
B47: 44717 | C47: 155.25 | D47: =C47/C46-1 -> 0.0016129032 | F47: 16201.8 | G47: =F47/F46-1 -> -0.023063982
B48: 44724 | C48: 140.45 | D48: =C48/C47-1 -> -0.095330113 | F48: 15293.5 | G48: =F48/F47-1 -> -0.056061672
... B270: 46278 | C270: 329.5 | D270: =C270/C269-1 -> -0.01169766 | F270: 23118.6 | G270: =F270/F269-1 -> -0.011945414

Sheet Tata Power
B1: Tata Power
B2: Regression Beta - 5Y Weekly
B5: Adani Power Weekly returns | F5: NIFTY Weekly Return | I5: Beta Drifting
B9: Date | C9: Price | D9: Weekly Returns | F9: Price | G9: Return | I9: Levered Raw Beta | J9: =J17 -> 1.2766096
B10: 44458 | C10: 139.1 | D10: 0 | F10: 17853.2 | G10: 0 | I10: Raw Beta Weight | J10: 0.75
B11: 44465 | C11: 163.75 | D11: =C11/C10-1 -> 0.17721064 | F11: 17532.05 | G11: =F11/F10-1 -> -0.017988372 | I11: Market Beta | J11: 1
B12: 44472 | C12: 176.85 | D12: =C12/C11-1 -> 0.08 | F12: 17895.2 | G12: =F12/F11-1 -> 0.020713493 | I12: Market Beta Weight | J12: 0.25
B13: 44479 | C13: 222.6 | D13: =C13/C12-1 -> 0.25869381 | F13: 18338.55 | G13: =F13/F12-1 -> 0.0247748
B14: 44486 | C14: 222 | D14: =C14/C13-1 -> -0.0026954178 | F14: 18114.9 | G14: =F14/F13-1 -> -0.012195621 | I14: Adjusted Beta | J14: =(J9*J10)+(J11*J12) -> 1.2074572
B15: 44493 | C15: 214.3 | D15: =C15/C14-1 -> -0.034684685 | F15: 17671.65 | G15: =F15/F14-1 -> -0.024468807
B16: 44500 | C16: 231.35 | D16: =C16/C15-1 -> 0.079561363 | F16: 17916.8 | G16: =F16/F15-1 -> 0.013872502
B17: 44507 | C17: 239.85 | D17: =C17/C16-1 -> 0.036740869 | F17: 18102.75 | G17: =F17/F16-1 -> 0.010378527 | I17: Beta1 | J17: =J36 -> 1.2766096
B18: 44514 | C18: 237.1 | D18: =C18/C17-1 -> -0.011465499 | F18: 17764.8 | G18: =F18/F17-1 -> -0.018668434
B19: 44521 | C19: 227.35 | D19: =C19/C18-1 -> -0.041121889 | F19: 17026.45 | G19: =F19/F18-1 -> -0.041562528 | I19: SUMMARY OUTPUT
B20: 44528 | C20: 225.6 | D20: =C20/C19-1 -> -0.0076973829 | F20: 17196.7 | G20: =F20/F19-1 -> 0.0099991484
B21: 44535 | C21: 228 | D21: =C21/C20-1 -> 0.010638298 | F21: 17511.3 | G21: =F21/F20-1 -> 0.018294208 | I21: Regression Statistics
B22: 44542 | C22: 215.8 | D22: =C22/C21-1 -> -0.053508772 | F22: 16985.2 | G22: =F22/F21-1 -> -0.030043458 | I22: Multiple R | J22: 0.52219471
B23: 44549 | C23: 216.8 | D23: =C23/C22-1 -> 0.0046339203 | F23: 17003.75 | G23: =F23/F22-1 -> 0.0010921273 | I23: R Square | J23: 0.27268732
B24: 44556 | C24: 220.95 | D24: =C24/C23-1 -> 0.019142066 | F24: 17354.05 | G24: =F24/F23-1 -> 0.020601338 | I24: Adjusted R Square | J24: 0.26986828
B25: 44563 | C25: 229.8 | D25: =C25/C24-1 -> 0.040054311 | F25: 17812.7 | G25: =F25/F24-1 -> 0.026428989 | I25: Standard Error | J25: 0.037807934
B26: 44570 | C26: 244.4 | D26: =C26/C25-1 -> 0.063533507 | F26: 18255.75 | G26: =F26/F25-1 -> 0.024872703 | I26: Observations | J26: 260
B27: 44577 | C27: 241.95 | D27: =C27/C26-1 -> -0.01002455 | F27: 17617.15 | G27: =F27/F26-1 -> -0.034980759
B28: 44584 | C28: 244.05 | D28: =C28/C27-1 -> 0.0086794792 | F28: 17101.95 | G28: =F28/F27-1 -> -0.029244231 | I28: ANOVA
B29: 44591 | C29: 254.35 | D29: =C29/C28-1 -> 0.042204466 | F29: 17516.3 | G29: =F29/F28-1 -> 0.024228231 | J29: df | K29: SS | L29: MS | M29: F | N29: Significance F
B30: 44598 | C30: 232.3 | D30: =C30/C29-1 -> -0.086691567 | F30: 17374.75 | G30: =F30/F29-1 -> -0.0080810445 | I30: Regression | J30: 1 | K30: 0.13827045 | L30: 0.13827045 | M30: 96.730512 | N30: 1.3663416e-19
B31: 44605 | C31: 225.75 | D31: =C31/C30-1 -> -0.028196298 | F31: 17276.3 | G31: =F31/F30-1 -> -0.0056662686 | I31: Residual | J31: 258 | K31: 0.3687955 | L31: 0.0014294399
B32: 44612 | C32: 220 | D32: =C32/C31-1 -> -0.025470653 | F32: 16658.4 | G32: =F32/F31-1 -> -0.03576576 | I32: Total | J32: 259 | K32: 0.50706595
B33: 44619 | C33: 221.45 | D33: =C33/C32-1 -> 0.0065909091 | F33: 16245.35 | G33: =F33/F32-1 -> -0.024795298
B34: 44626 | C34: 233.15 | D34: =C34/C33-1 -> 0.052833597 | F34: 16630.45 | G34: =F34/F33-1 -> 0.023705245 | J34: Coefficients | K34: Standard Error | L34: t Stat | M34: P-value | N34: Lower 95% | O34: Upper 95% | P34: Lower 95.0% | Q34: Upper 95.0%
B35: 44633 | C35: 231.75 | D35: =C35/C34-1 -> -0.006004718 | F35: 17287.05 | G35: =F35/F34-1 -> 0.039481794 | I35: Intercept | J35: 0.0031226016 | K35: 0.002349954 | L35: 1.3287926 | M35: 0.18509041 | N35: -0.0015049312 | O35: 0.0077501343 | P35: -0.0015049312 | Q35: 0.0077501343
B36: 44640 | C36: 241.35 | D36: =C36/C35-1 -> 0.041423948 | F36: 17153 | G36: =F36/F35-1 -> -0.0077543595 | I36: X Variable 1 | J36: 1.2766096 | K36: 0.1298005 | L36: 9.8351671 | M36: 1.3663416e-19 | N36: 1.0210063 | O36: 1.5322129 | P36: 1.0210063 | Q36: 1.5322129
B37: 44647 | C37: 245.45 | D37: =C37/C36-1 -> 0.016987777 | F37: 17670.45 | G37: =F37/F36-1 -> 0.030166735
B38: 44654 | C38: 278.1 | D38: =C38/C37-1 -> 0.13302098 | F38: 17784.35 | G38: =F38/F37-1 -> 0.0064457894
B39: 44661 | C39: 273.1 | D39: =C39/C38-1 -> -0.017979144 | F39: 17475.65 | G39: =F39/F38-1 -> -0.017357958
B40: 44668 | C40: 253.1 | D40: =C40/C39-1 -> -0.073233248 | F40: 17171.95 | G40: =F40/F39-1 -> -0.017378467
B41: 44675 | C41: 242.35 | D41: =C41/C40-1 -> -0.042473331 | F41: 17102.55 | G41: =F41/F40-1 -> -0.0040414746
B42: 44682 | C42: 245.2 | D42: =C42/C41-1 -> 0.011759851 | F42: 16411.25 | G42: =F42/F41-1 -> -0.040420873
B43: 44689 | C43: 222.8 | D43: =C43/C42-1 -> -0.091353997 | F43: 15782.15 | G43: =F43/F42-1 -> -0.03833346
B44: 44696 | C44: 233.25 | D44: =C44/C43-1 -> 0.046903052 | F44: 16266.15 | G44: =F44/F43-1 -> 0.030667558
B45: 44703 | C45: 224.65 | D45: =C45/C44-1 -> -0.036870311 | F45: 16352.45 | G45: =F45/F44-1 -> 0.0053054964
B46: 44710 | C46: 231.05 | D46: =C46/C45-1 -> 0.02848876 | F46: 16584.3 | G46: =F46/F45-1 -> 0.014178304
B47: 44717 | C47: 230.25 | D47: =C47/C46-1 -> -0.003462454 | F47: 16201.8 | G47: =F47/F46-1 -> -0.023063982
B48: 44724 | C48: 210.3 | D48: =C48/C47-1 -> -0.086644951 | F48: 15293.5 | G48: =F48/F47-1 -> -0.056061672
... B270: 46278 | C270: 363 | D270: =C270/C269-1 -> -0.0045248869 | F270: 23118.6 | G270: =F270/F269-1 -> -0.011945414

Sheet JSW Energy
B1: JSW Energy
B2: Regression Beta - 5Y Weekly
B5: Adani Power Weekly returns | F5: NIFTY Weekly Return | I5: Beta Drifting
B9: Date | C9: Price | D9: Weekly Returns | F9: Price | G9: Return | I9: Levered Raw Beta | J9: =J17 -> 1.0268912
B10: 44458 | C10: 350.05 | D10: 0 | F10: 17853.2 | G10: 0 | I10: Raw Beta Weight | J10: 0.75
B11: 44465 | C11: 385.2 | D11: =C11/C10-1 -> 0.10041423 | F11: 17532.05 | G11: =F11/F10-1 -> -0.017988372 | I11: Market Beta | J11: 1
B12: 44472 | C12: 381.75 | D12: =C12/C11-1 -> -0.0089563863 | F12: 17895.2 | G12: =F12/F11-1 -> 0.020713493 | I12: Market Beta Weight | J12: 0.25
B13: 44479 | C13: 394 | D13: =C13/C12-1 -> 0.032089064 | F13: 18338.55 | G13: =F13/F12-1 -> 0.0247748
B14: 44486 | C14: 380.85 | D14: =C14/C13-1 -> -0.033375635 | F14: 18114.9 | G14: =F14/F13-1 -> -0.012195621 | I14: Adjusted Beta | J14: =(J9*J10)+(J11*J12) -> 1.0201684
B15: 44493 | C15: 348.65 | D15: =C15/C14-1 -> -0.084547722 | F15: 17671.65 | G15: =F15/F14-1 -> -0.024468807
B16: 44500 | C16: 332.5 | D16: =C16/C15-1 -> -0.046321526 | F16: 17916.8 | G16: =F16/F15-1 -> 0.013872502
B17: 44507 | C17: 322.6 | D17: =C17/C16-1 -> -0.029774436 | F17: 18102.75 | G17: =F17/F16-1 -> 0.010378527 | I17: Beta1 | J17: =J36 -> 1.0268912
B18: 44514 | C18: 295.3 | D18: =C18/C17-1 -> -0.084624923 | F18: 17764.8 | G18: =F18/F17-1 -> -0.018668434
B19: 44521 | C19: 301.9 | D19: =C19/C18-1 -> 0.022350152 | F19: 17026.45 | G19: =F19/F18-1 -> -0.041562528 | I19: SUMMARY OUTPUT
B20: 44528 | C20: 323.1 | D20: =C20/C19-1 -> 0.070221928 | F20: 17196.7 | G20: =F20/F19-1 -> 0.0099991484
B21: 44535 | C21: 299.35 | D21: =C21/C20-1 -> -0.073506654 | F21: 17511.3 | G21: =F21/F20-1 -> 0.018294208 | I21: Regression Statistics
B22: 44542 | C22: 286.8 | D22: =C22/C21-1 -> -0.041924169 | F22: 16985.2 | G22: =F22/F21-1 -> -0.030043458 | I22: Multiple R | J22: 0.32803948
B23: 44549 | C23: 302.35 | D23: =C23/C22-1 -> 0.054218968 | F23: 17003.75 | G23: =F23/F22-1 -> 0.0010921273 | I23: R Square | J23: 0.1076099
B24: 44556 | C24: 300.5 | D24: =C24/C23-1 -> -0.0061187366 | F24: 17354.05 | G24: =F24/F23-1 -> 0.020601338 | I24: Adjusted R Square | J24: 0.10415102
B25: 44563 | C25: 307.45 | D25: =C25/C24-1 -> 0.02312812 | F25: 17812.7 | G25: =F25/F24-1 -> 0.026428989 | I25: Standard Error | J25: 0.053625634
B26: 44570 | C26: 307.6 | D26: =C26/C25-1 -> 0.00048788421 | F26: 18255.75 | G26: =F26/F25-1 -> 0.024872703 | I26: Observations | J26: 260
B27: 44577 | C27: 308.85 | D27: =C27/C26-1 -> 0.0040637191 | F27: 17617.15 | G27: =F27/F26-1 -> -0.034980759
B28: 44584 | C28: 295.55 | D28: =C28/C27-1 -> -0.043062976 | F28: 17101.95 | G28: =F28/F27-1 -> -0.029244231 | I28: ANOVA
B29: 44591 | C29: 297.75 | D29: =C29/C28-1 -> 0.0074437489 | F29: 17516.3 | G29: =F29/F28-1 -> 0.024228231 | J29: df | K29: SS | L29: MS | M29: F | N29: Significance F
B30: 44598 | C30: 341.3 | D30: =C30/C29-1 -> 0.14626364 | F30: 17374.75 | G30: =F30/F29-1 -> -0.0080810445 | I30: Regression | J30: 1 | K30: 0.089466832 | L30: 0.089466832 | M30: 31.11123 | N30: 6.1439545e-08
B31: 44605 | C31: 340.1 | D31: =C31/C30-1 -> -0.0035159684 | F31: 17276.3 | G31: =F31/F30-1 -> -0.0056662686 | I31: Residual | J31: 258 | K31: 0.74193282 | L31: 0.0028757086
B32: 44612 | C32: 334 | D32: =C32/C31-1 -> -0.017935901 | F32: 16658.4 | G32: =F32/F31-1 -> -0.03576576 | I32: Total | J32: 259 | K32: 0.83139965
B33: 44619 | C33: 329.05 | D33: =C33/C32-1 -> -0.014820359 | F33: 16245.35 | G33: =F33/F32-1 -> -0.024795298
B34: 44626 | C34: 313.5 | D34: =C34/C33-1 -> -0.047257256 | F34: 16630.45 | G34: =F34/F33-1 -> 0.023705245 | J34: Coefficients | K34: Standard Error | L34: t Stat | M34: P-value | N34: Lower 95% | O34: Upper 95% | P34: Lower 95.0% | Q34: Upper 95.0%
B35: 44633 | C35: 298.7 | D35: =C35/C34-1 -> -0.047208931 | F35: 17287.05 | G35: =F35/F34-1 -> 0.039481794 | I35: Intercept | J35: 0.001908693 | K35: 0.0033331039 | L35: 0.57264732 | M35: 0.5673822 | N35: -0.0046548598 | O35: 0.0084722459 | P35: -0.0046548598 | Q35: 0.0084722459
B36: 44640 | C36: 296.5 | D36: =C36/C35-1 -> -0.0073652494 | F36: 17153 | G36: =F36/F35-1 -> -0.0077543595 | I36: X Variable 1 | J36: 1.0268912 | K36: 0.18410512 | L36: 5.5777442 | M36: 6.1439545e-08 | N36: 0.66435119 | O36: 1.3894313 | P36: 0.66435119 | Q36: 1.3894313
B37: 44647 | C37: 309.2 | D37: =C37/C36-1 -> 0.042833052 | F37: 17670.45 | G37: =F37/F36-1 -> 0.030166735
B38: 44654 | C38: 342.75 | D38: =C38/C37-1 -> 0.10850582 | F38: 17784.35 | G38: =F38/F37-1 -> 0.0064457894
B39: 44661 | C39: 325.9 | D39: =C39/C38-1 -> -0.049161196 | F39: 17475.65 | G39: =F39/F38-1 -> -0.017357958
B40: 44668 | C40: 343.7 | D40: =C40/C39-1 -> 0.054617981 | F40: 17171.95 | G40: =F40/F39-1 -> -0.017378467
B41: 44675 | C41: 317.65 | D41: =C41/C40-1 -> -0.075792843 | F41: 17102.55 | G41: =F41/F40-1 -> -0.0040414746
B42: 44682 | C42: 301.35 | D42: =C42/C41-1 -> -0.05131434 | F42: 16411.25 | G42: =F42/F41-1 -> -0.040420873
B43: 44689 | C43: 247.15 | D43: =C43/C42-1 -> -0.17985731 | F43: 15782.15 | G43: =F43/F42-1 -> -0.03833346
B44: 44696 | C44: 293.35 | D44: =C44/C43-1 -> 0.18693101 | F44: 16266.15 | G44: =F44/F43-1 -> 0.030667558
B45: 44703 | C45: 283.4 | D45: =C45/C44-1 -> -0.033918527 | F45: 16352.45 | G45: =F45/F44-1 -> 0.0053054964
B46: 44710 | C46: 260.55 | D46: =C46/C45-1 -> -0.080628088 | F46: 16584.3 | G46: =F46/F45-1 -> 0.014178304
B47: 44717 | C47: 247.75 | D47: =C47/C46-1 -> -0.049126847 | F47: 16201.8 | G47: =F47/F46-1 -> -0.023063982
B48: 44724 | C48: 210.15 | D48: =C48/C47-1 -> -0.15176589 | F48: 15293.5 | G48: =F48/F47-1 -> -0.056061672
... B270: 46278 | C270: 505 | D270: =C270/C269-1 -> -0.04074461 | F270: 23118.6 | G270: =F270/F269-1 -> -0.011945414

Sheet Torrent Power
B1: Torrent Power
B2: Regression Beta - 5Y Weekly
B5: Adani Power Weekly returns | F5: NIFTY Weekly Return | I5: Beta Drifting
B9: Date | C9: Price | D9: Weekly Returns | F9: Price | G9: Return | I9: Levered Raw Beta | J9: =J17 -> 1.1576003
B10: 44458 | C10: 486.04 | D10: 0 | F10: 17853.2 | G10: 0 | I10: Raw Beta Weight | J10: 0.75
B11: 44465 | C11: 488.82 | D11: =C11/C10-1 -> 0.0057196939 | F11: 17532.05 | G11: =F11/F10-1 -> -0.017988372 | I11: Market Beta | J11: 1
B12: 44472 | C12: 491.35 | D12: =C12/C11-1 -> 0.0051757293 | F12: 17895.2 | G12: =F12/F11-1 -> 0.020713493 | I12: Market Beta Weight | J12: 0.25
B13: 44479 | C13: 502.46 | D13: =C13/C12-1 -> 0.022611173 | F13: 18338.55 | G13: =F13/F12-1 -> 0.0247748
B14: 44486 | C14: 484.62 | D14: =C14/C13-1 -> -0.035505314 | F14: 18114.9 | G14: =F14/F13-1 -> -0.012195621 | I14: Adjusted Beta | J14: =(J9*J10)+(J11*J12) -> 1.1182002
B15: 44493 | C15: 487.4 | D15: =C15/C14-1 -> 0.0057364533 | F15: 17671.65 | G15: =F15/F14-1 -> -0.024468807
B16: 44500 | C16: 502.61 | D16: =C16/C15-1 -> 0.031206401 | F16: 17916.8 | G16: =F16/F15-1 -> 0.013872502
B17: 44507 | C17: 525.76 | D17: =C17/C16-1 -> 0.046059569 | F17: 18102.75 | G17: =F17/F16-1 -> 0.010378527 | I17: Beta1 | J17: =J36 -> 1.1576003
B18: 44514 | C18: 513.33 | D18: =C18/C17-1 -> -0.023641966 | F18: 17764.8 | G18: =F18/F17-1 -> -0.018668434
B19: 44521 | C19: 524.59 | D19: =C19/C18-1 -> 0.021935207 | F19: 17026.45 | G19: =F19/F18-1 -> -0.041562528 | I19: SUMMARY OUTPUT
B20: 44528 | C20: 551.11 | D20: =C20/C19-1 -> 0.050553766 | F20: 17196.7 | G20: =F20/F19-1 -> 0.0099991484
B21: 44535 | C21: 565.15 | D21: =C21/C20-1 -> 0.025475858 | F21: 17511.3 | G21: =F21/F20-1 -> 0.018294208 | I21: Regression Statistics
B22: 44542 | C22: 530.78 | D22: =C22/C21-1 -> -0.060815713 | F22: 16985.2 | G22: =F22/F21-1 -> -0.030043458 | I22: Multiple R | J22: 0.42044816
B23: 44549 | C23: 520.01 | D23: =C23/C22-1 -> -0.020290893 | F23: 17003.75 | G23: =F23/F22-1 -> 0.0010921273 | I23: R Square | J23: 0.17677665
B24: 44556 | C24: 539.66 | D24: =C24/C23-1 -> 0.037787735 | F24: 17354.05 | G24: =F24/F23-1 -> 0.020601338 | I24: Adjusted R Square | J24: 0.17358586
B25: 44563 | C25: 560.37 | D25: =C25/C24-1 -> 0.038376015 | F25: 17812.7 | G25: =F25/F24-1 -> 0.026428989 | I25: Standard Error | J25: 0.045300369
B26: 44570 | C26: 564.32 | D26: =C26/C25-1 -> 0.0070489141 | F26: 18255.75 | G26: =F26/F25-1 -> 0.024872703 | I26: Observations | J26: 260
B27: 44577 | C27: 536.73 | D27: =C27/C26-1 -> -0.0488907 | F27: 17617.15 | G27: =F27/F26-1 -> -0.034980759
B28: 44584 | C28: 528.4 | D28: =C28/C27-1 -> -0.015519908 | F28: 17101.95 | G28: =F28/F27-1 -> -0.029244231 | I28: ANOVA
B29: 44591 | C29: 565.78 | D29: =C29/C28-1 -> 0.070741862 | F29: 17516.3 | G29: =F29/F28-1 -> 0.024228231 | J29: df | K29: SS | L29: MS | M29: F | N29: Significance F
B30: 44598 | C30: 482.97 | D30: =C30/C29-1 -> -0.14636431 | F30: 17374.75 | G30: =F30/F29-1 -> -0.0080810445 | I30: Regression | J30: 1 | K30: 0.11369213 | L30: 0.11369213 | M30: 55.402189 | N30: 1.4666192e-12
B31: 44605 | C31: 467.46 | D31: =C31/C30-1 -> -0.032113796 | F31: 17276.3 | G31: =F31/F30-1 -> -0.0056662686 | I31: Residual | J31: 258 | K31: 0.52944784 | L31: 0.0020521234
B32: 44612 | C32: 453.18 | D32: =C32/C31-1 -> -0.030548068 | F32: 16658.4 | G32: =F32/F31-1 -> -0.03576576 | I32: Total | J32: 259 | K32: 0.64313997
B33: 44619 | C33: 456.98 | D33: =C33/C32-1 -> 0.0083851891 | F33: 16245.35 | G33: =F33/F32-1 -> -0.024795298
B34: 44626 | C34: 468.78 | D34: =C34/C33-1 -> 0.025821699 | F34: 16630.45 | G34: =F34/F33-1 -> 0.023705245 | J34: Coefficients | K34: Standard Error | L34: t Stat | M34: P-value | N34: Lower 95% | O34: Upper 95% | P34: Lower 95.0% | Q34: Upper 95.0%
B35: 44633 | C35: 471.07 | D35: =C35/C34-1 -> 0.0048850207 | F35: 17287.05 | G35: =F35/F34-1 -> 0.039481794 | I35: Intercept | J35: 0.0036091032 | K35: 0.0028156467 | L35: 1.2818026 | M35: 0.20106259 | N35: -0.0019354721 | O35: 0.0091536786 | P35: -0.0019354721 | Q35: 0.0091536786
B36: 44640 | C36: 473.75 | D36: =C36/C35-1 -> 0.0056891757 | F36: 17153 | G36: =F36/F35-1 -> -0.0077543595 | I36: X Variable 1 | J36: 1.1576003 | K36: 0.15552319 | L36: 7.4432647 | M36: 1.4666192e-12 | N36: 0.85134379 | O36: 1.4638568 | P36: 0.85134379 | Q36: 1.4638568
B37: 44647 | C37: 489.89 | D37: =C37/C36-1 -> 0.034068602 | F37: 17670.45 | G37: =F37/F36-1 -> 0.030166735
B38: 44654 | C38: 528.93 | D38: =C38/C37-1 -> 0.079691359 | F38: 17784.35 | G38: =F38/F37-1 -> 0.0064457894
B39: 44661 | C39: 534.29 | D39: =C39/C38-1 -> 0.010133666 | F39: 17475.65 | G39: =F39/F38-1 -> -0.017357958
B40: 44668 | C40: 528.01 | D40: =C40/C39-1 -> -0.011753916 | F40: 17171.95 | G40: =F40/F39-1 -> -0.017378467
B41: 44675 | C41: 519.77 | D41: =C41/C40-1 -> -0.015605765 | F41: 17102.55 | G41: =F41/F40-1 -> -0.0040414746
B42: 44682 | C42: 481.07 | D42: =C42/C41-1 -> -0.074456009 | F42: 16411.25 | G42: =F42/F41-1 -> -0.040420873
B43: 44689 | C43: 420.82 | D43: =C43/C42-1 -> -0.12524165 | F43: 15782.15 | G43: =F43/F42-1 -> -0.03833346
B44: 44696 | C44: 418.87 | D44: =C44/C43-1 -> -0.0046338102 | F44: 16266.15 | G44: =F44/F43-1 -> 0.030667558
B45: 44703 | C45: 422.23 | D45: =C45/C44-1 -> 0.0080215819 | F45: 16352.45 | G45: =F45/F44-1 -> 0.0053054964
B46: 44710 | C46: 453.86 | D46: =C46/C45-1 -> 0.074911778 | F46: 16584.3 | G46: =F46/F45-1 -> 0.014178304
B47: 44717 | C47: 454.3 | D47: =C47/C46-1 -> 0.00096946195 | F47: 16201.8 | G47: =F47/F46-1 -> -0.023063982
B48: 44724 | C48: 453.91 | D48: =C48/C47-1 -> -0.00085846357 | F48: 15293.5 | G48: =F48/F47-1 -> -0.056061672
... B270: 46278 | C270: 1300.9 | D270: =C270/C269-1 -> 0.0025431566 | F270: 23118.6 | G270: =F270/F269-1 -> -0.011945414

Sheet CESE
B1: CESE
B2: Regression Beta - 5Y Weekly
B5: Adani Power Weekly returns | F5: NIFTY Weekly Return | I5: Beta Drifting
B9: Date | C9: Price | D9: Weekly Returns | F9: Price | G9: Return | I9: Levered Raw Beta | J9: =J17 -> 1.0437014
B10: 44458 | C10: 84.1 | D10: 0 | F10: 17853.2 | G10: 0 | I10: Raw Beta Weight | J10: 0.75
B11: 44465 | C11: 91.4 | D11: =C11/C10-1 -> 0.086801427 | F11: 17532.05 | G11: =F11/F10-1 -> -0.017988372 | I11: Market Beta | J11: 1
B12: 44472 | C12: 88.7 | D12: =C12/C11-1 -> -0.029540481 | F12: 17895.2 | G12: =F12/F11-1 -> 0.020713493 | I12: Market Beta Weight | J12: 0.25
B13: 44479 | C13: 93.75 | D13: =C13/C12-1 -> 0.056933484 | F13: 18338.55 | G13: =F13/F12-1 -> 0.0247748
B14: 44486 | C14: 93 | D14: =C14/C13-1 -> -0.008 | F14: 18114.9 | G14: =F14/F13-1 -> -0.012195621 | I14: Adjusted Beta | J14: =(J9*J10)+(J11*J12) -> 1.032776
B15: 44493 | C15: 87.2 | D15: =C15/C14-1 -> -0.062365591 | F15: 17671.65 | G15: =F15/F14-1 -> -0.024468807
B16: 44500 | C16: 91.6 | D16: =C16/C15-1 -> 0.050458716 | F16: 17916.8 | G16: =F16/F15-1 -> 0.013872502
B17: 44507 | C17: 90.6 | D17: =C17/C16-1 -> -0.010917031 | F17: 18102.75 | G17: =F17/F16-1 -> 0.010378527 | I17: Beta1 | J17: =J36 -> 1.0437014
B18: 44514 | C18: 88.05 | D18: =C18/C17-1 -> -0.028145695 | F18: 17764.8 | G18: =F18/F17-1 -> -0.018668434
B19: 44521 | C19: 88.7 | D19: =C19/C18-1 -> 0.0073821692 | F19: 17026.45 | G19: =F19/F18-1 -> -0.041562528 | I19: SUMMARY OUTPUT
B20: 44528 | C20: 89.15 | D20: =C20/C19-1 -> 0.0050732807 | F20: 17196.7 | G20: =F20/F19-1 -> 0.0099991484
B21: 44535 | C21: 87.75 | D21: =C21/C20-1 -> -0.01570387 | F21: 17511.3 | G21: =F21/F20-1 -> 0.018294208 | I21: Regression Statistics
B22: 44542 | C22: 84.45 | D22: =C22/C21-1 -> -0.037606838 | F22: 16985.2 | G22: =F22/F21-1 -> -0.030043458 | I22: Multiple R | J22: 0.43209837
B23: 44549 | C23: 85.25 | D23: =C23/C22-1 -> 0.009473061 | F23: 17003.75 | G23: =F23/F22-1 -> 0.0010921273 | I23: R Square | J23: 0.186709
B24: 44556 | C24: 87.5 | D24: =C24/C23-1 -> 0.026392962 | F24: 17354.05 | G24: =F24/F23-1 -> 0.020601338 | I24: Adjusted R Square | J24: 0.18355671
B25: 44563 | C25: 90.55 | D25: =C25/C24-1 -> 0.034857143 | F25: 17812.7 | G25: =F25/F24-1 -> 0.026428989 | I25: Standard Error | J25: 0.039501478
B26: 44570 | C26: 92.55 | D26: =C26/C25-1 -> 0.022087245 | F26: 18255.75 | G26: =F26/F25-1 -> 0.024872703 | I26: Observations | J26: 260
B27: 44577 | C27: 90.85 | D27: =C27/C26-1 -> -0.018368449 | F27: 17617.15 | G27: =F27/F26-1 -> -0.034980759
B28: 44584 | C28: 84.6 | D28: =C28/C27-1 -> -0.068794717 | F28: 17101.95 | G28: =F28/F27-1 -> -0.029244231 | I28: ANOVA
B29: 44591 | C29: 83 | D29: =C29/C28-1 -> -0.01891253 | F29: 17516.3 | G29: =F29/F28-1 -> 0.024228231 | J29: df | K29: SS | L29: MS | M29: F | N29: Significance F
B30: 44598 | C30: 83.65 | D30: =C30/C29-1 -> 0.0078313253 | F30: 17374.75 | G30: =F30/F29-1 -> -0.0080810445 | I30: Regression | J30: 1 | K30: 0.092419937 | L30: 0.092419937 | M30: 59.229625 | N30: 2.9844239e-13
B31: 44605 | C31: 79.85 | D31: =C31/C30-1 -> -0.045427376 | F31: 17276.3 | G31: =F31/F30-1 -> -0.0056662686 | I31: Residual | J31: 258 | K31: 0.40257462 | L31: 0.0015603667
B32: 44612 | C32: 78.15 | D32: =C32/C31-1 -> -0.021289919 | F32: 16658.4 | G32: =F32/F31-1 -> -0.03576576 | I32: Total | J32: 259 | K32: 0.49499455
B33: 44619 | C33: 78.25 | D33: =C33/C32-1 -> 0.0012795905 | F33: 16245.35 | G33: =F33/F32-1 -> -0.024795298
B34: 44626 | C34: 77.5 | D34: =C34/C33-1 -> -0.0095846645 | F34: 16630.45 | G34: =F34/F33-1 -> 0.023705245 | J34: Coefficients | K34: Standard Error | L34: t Stat | M34: P-value | N34: Lower 95% | O34: Upper 95% | P34: Lower 95.0% | Q34: Upper 95.0%
B35: 44633 | C35: 73.6 | D35: =C35/C34-1 -> -0.050322581 | F35: 17287.05 | G35: =F35/F34-1 -> 0.039481794 | I35: Intercept | J35: 0.0017889771 | K35: 0.0024552163 | L35: 0.72864338 | M35: 0.4668807 | N35: -0.0030458382 | O35: 0.0066237924 | P35: -0.0030458382 | Q35: 0.0066237924
B36: 44640 | C36: 77.45 | D36: =C36/C35-1 -> 0.052309783 | F36: 17153 | G36: =F36/F35-1 -> -0.0077543595 | I36: X Variable 1 | J36: 1.0437014 | K36: 0.1356147 | L36: 7.6960786 | M36: 2.9844239e-13 | N36: 0.77664871 | O36: 1.310754 | P36: 0.77664871 | Q36: 1.310754
B37: 44647 | C37: 78.75 | D37: =C37/C36-1 -> 0.016785023 | F37: 17670.45 | G37: =F37/F36-1 -> 0.030166735
B38: 44654 | C38: 85.9 | D38: =C38/C37-1 -> 0.090793651 | F38: 17784.35 | G38: =F38/F37-1 -> 0.0064457894
B39: 44661 | C39: 84.2 | D39: =C39/C38-1 -> -0.019790454 | F39: 17475.65 | G39: =F39/F38-1 -> -0.017357958
B40: 44668 | C40: 84.2 | D40: =C40/C39-1 -> 0 | F40: 17171.95 | G40: =F40/F39-1 -> -0.017378467
B41: 44675 | C41: 85.65 | D41: =C41/C40-1 -> 0.017220903 | F41: 17102.55 | G41: =F41/F40-1 -> -0.0040414746
B42: 44682 | C42: 83.5 | D42: =C42/C41-1 -> -0.02510216 | F42: 16411.25 | G42: =F42/F41-1 -> -0.040420873
B43: 44689 | C43: 78.55 | D43: =C43/C42-1 -> -0.059281437 | F43: 15782.15 | G43: =F43/F42-1 -> -0.03833346
B44: 44696 | C44: 79.05 | D44: =C44/C43-1 -> 0.0063653724 | F44: 16266.15 | G44: =F44/F43-1 -> 0.030667558
B45: 44703 | C45: 78.9 | D45: =C45/C44-1 -> -0.0018975332 | F45: 16352.45 | G45: =F45/F44-1 -> 0.0053054964
B46: 44710 | C46: 79.25 | D46: =C46/C45-1 -> 0.0044359949 | F46: 16584.3 | G46: =F46/F45-1 -> 0.014178304
B47: 44717 | C47: 78.05 | D47: =C47/C46-1 -> -0.015141956 | F47: 16201.8 | G47: =F47/F46-1 -> -0.023063982
B48: 44724 | C48: 71.3 | D48: =C48/C47-1 -> -0.086483024 | F48: 15293.5 | G48: =F48/F47-1 -> -0.056061672
... B270: 46278 | C270: 141.7 | D270: =C270/C269-1 -> -0.025245924 | F270: 23118.6 | G270: =F270/F269-1 -> -0.011945414
